Workbook

Sheet 00_はじめに
A1: AIセキュリティロードマップ作成ツール（AIMF v0.1 β版：AIセキュリティ＆ガバナンス統合マスターフレームワーク準拠）
A2: 207問評価（6区分×37カテゴリ）→ 適用自動判定 → 施策抽出 → 優先順位付け → ロードマップ → ガントチャート → ダッシュボードまでを自動生成します。
A3: 評価質問と施策はAIMF v0.1（β版）の207コントロール（19基準対応：NIST CSF 2.0 / AI RMF / ISO 42001 / OWASP AISVS・LLM10・ASI10 / EU AI Act / MITRE ATLAS / ASDエージェントAIガイダンス / Five Eyes声明 ほか）から生成。
A6: ■ 使い方（基本フロー）
A7: ステップ | B7: シート | C7: 内容
A8: Step0 | B8: 00_はじめに | C8: AI利用プロファイル（下表）を設定。利用しないAI類型の質問は自動で「対象外」になります。
A9: Step1 | B9: 01_評価入力 | C9: 現状評価（黄色セル）を入力。影響度〜導入難易度は初期値入り（青字）で、必要に応じて調整可。
A10: Step2 | B10: 自動計算 | C10: 適用判定・ギャップ・優先度スコア・抽出対象が自動判定されます。
A11: Step3 | B11: 05/06 | C11: 抽出施策と推奨優先度が自動生成されます（閲覧のみ）。
A12: Step4 | B12: 07_短中長Top5 | C12: 短期・中期・長期それぞれの優先施策Top5を自動表示。
A13: Step5 | B13: 08_ロードマップ | C13: 区分別の実行計画一覧を自動生成。
A14: Step6 | B14: 09/10_ガント | C14: 依存関係を考慮した開始・終了月とガントチャート（36か月）を自動描画。
A15: Step7 | B15: 11_ダッシュボード | C15: 区分別レーダー・control-type別・AI類型別レディネスを確認し、12_PPT出力データを報告書へ転記。
A17: ■ 設定（必要に応じて変更可・黄色セル）
A18: 設定項目 | B18: 値 | C18: 説明
A19: 優先度スコア閾値 | B19: 40 | C19: 現状<目標でなくてもスコアがこの値以上なら施策を抽出
A20: 短期 開始月 | B20: 1 | C20: 短期施策の標準開始月（プロジェクト開始からの月数）
A21: 中期 開始月 | B21: 7 | C21: 中期施策の標準開始月
A22: 長期 開始月 | B22: 19 | C22: 長期施策の標準開始月
A23: ■ AI利用プロファイル（Y/N・黄色セル） | C23: 利用しない類型に固有の質問は自動で「対象外」となり、集計の分母から除外されます。
A24: 従来型AI（判別・分類モデル等）の利用 | B24: Y | C24: ai-scopeにtraditional-aiを含む質問の適用判定に使用
A25: 生成AI（LLM・RAG）の利用 | B25: Y | C25: ai-scopeにgenerative-aiを含む質問の適用判定に使用
A26: AIエージェント（単体）の利用 | B26: Y | C26: ai-scopeにai-agentを含む質問の適用判定に使用
A27: マルチエージェントの利用 | B27: Y | C27: ai-scopeにmulti-agentを含む質問の適用判定に使用
A29: ■ 評価基準・凡例
A30: 現状評価/目標評価 (0-4) | B30: 0=未実施 / 1=一部実施 / 2=限定運用 / 3=標準運用 / 4=高度運用・最適化 | C30: 入力例: 現状=2（限定運用）
A31: 優先度スコア | B31: ギャップ×影響度×発生可能性×ビジネス重要度×QuickWin×依存係数 ÷ 導入難易度 | C31: 影響度〜導入難易度(1-5)は施策属性から導出した初期値入り（青字）。ヒアリング結果に応じて調整可
A32: control-type | B32: AI-Expansion=AI特有の新設管理策 / AI-Enhancement=既存セキュリティ管理策のAI拡張 | C32: ダッシュボードで「AI固有統制の未整備」と「既存運用の適用漏れ」を分けて把握
A33: 目標評価の初期値 | B33: ベースライン(baseline)=4 / 拡張(extended)=3 | C33: 段階適用の考え方に基づく初期値。組織の方針に応じて調整可
A34: セルの色 | B34: 黄色=入力セル / 青字=調整可能な初期値 / 白=自動計算（編集不可）

Sheet 01_評価入力
A1: 質問ID | B1: 区分 | C1: カテゴリ | D1: コントロール名 | E1: 質問 | F1: Type | G1: ai-scope | H1: 適用 | I1: 現状評価 (0-4) | J1: 目標評価 (0-4) | K1: ギャップ | L1: 影響度 (1-5) | M1: 発生可能性 (1-5) | N1: ビジネス 重要度(1-5) | O1: QuickWin (1-5) | P1: 依存係数 (1-5) | Q1: 導入難易度 (1-5) | R1: 優先度 スコア | S1: 抽出対象 | T1: 推奨施策ID | U1: 推奨施策名 | V1: 調整スコア (内部) | W1: スコア順位 (内部) | X1: lineage (内部)
A2: AIMF-GV-ORG-001 | B2: GV | C2: ORG | D2: AIガバナンス委員会の設置 | E2: 経営層、CISO、法務、IT部門、事業部門の代表からなるクロスファンクショナルな統治組織を組成し、責任の所在を明確にしていますか。 | F2: AI-Enhancement | G2: all | H2: =IF(OR($G2="all",AND(00_はじめに!$B$24="Y",ISNUMBER(SEARCH("traditional",$G2))),AND(00_はじめに!$B$25="Y",ISNUMBER(SEARCH("generative",$G2))),AND(00_はじめに!$B$26="Y",ISNUMBER(SEARCH("ai-agent",$G2))),AND(00_はじめに!$B$27="Y",ISNUMBER(SEARCH("multi-agent",$G2)))),"○","対象外") -> ○ | J2: 4 | K2: =IF(OR($H2="対象外",$I2="",$J2=""),"",$J2-$I2) | L2: 4 | M2: 3 | N2: 5 | O2: 5 | P2: 4 | Q2: 2 | R2: =IF(OR($H2="対象外",$K2="",$L2="",$M2="",$N2="",$O2="",$P2="",$Q2=""),"",($K2*$L2*$M2*$N2*$O2*$P2)/$Q2) | S2: =IF($H2="対象外","",IF(OR($I2="",$J2=""),"",IF(OR($J2-$I2>0,AND($R2<>"",$R2>=00_はじめに!$B$19)),"○",""))) | T2: =IFERROR(VLOOKUP($A2,03_質問施策マッピング!$A:$B,2,0),"") -> AIMF-GV-ORG-001 | U2: =IF($T2="","",IFERROR(VLOOKUP($T2,02_施策マスター!$A:$B,2,0),"")) -> AIガバナンス委員会の設置 | V2: =IF($R2="","",$R2+(1000-ROW())/1000000) | W2: =IF($V2="","",COUNTIF($V$2:$V$208,">"&$V2)+1) | X2: baseline
A3: AIMF-GV-ORG-002 | B3: GV | C3: ORG | D3: AI活用基本方針・ガイドラインの策定 | E3: 全社的なAI利用の目的、許容リスクレベル、禁止事項（機密情報の公衆AIへの入力禁止等）を定義・規程化していますか。 | F3: AI-Enhancement | G3: all | H3: =IF(OR($G3="all",AND(00_はじめに!$B$24="Y",ISNUMBER(SEARCH("traditional",$G3))),AND(00_はじめに!$B$25="Y",ISNUMBER(SEARCH("generative",$G3))),AND(00_はじめに!$B$26="Y",ISNUMBER(SEARCH("ai-agent",$G3))),AND(00_はじめに!$B$27="Y",ISNUMBER(SEARCH("multi-agent",$G3)))),"○","対象外") -> ○ | J3: 4 | K3: =IF(OR($H3="対象外",$I3="",$J3=""),"",$J3-$I3) | L3: 4 | M3: 3 | N3: 5 | O3: 5 | P3: 4 | Q3: 2 | R3: =IF(OR($H3="対象外",$K3="",$L3="",$M3="",$N3="",$O3="",$P3="",$Q3=""),"",($K3*$L3*$M3*$N3*$O3*$P3)/$Q3) | S3: =IF($H3="対象外","",IF(OR($I3="",$J3=""),"",IF(OR($J3-$I3>0,AND($R3<>"",$R3>=00_はじめに!$B$19)),"○",""))) | T3: =IFERROR(VLOOKUP($A3,03_質問施策マッピング!$A:$B,2,0),"") -> AIMF-GV-ORG-002 | U3: =IF($T3="","",IFERROR(VLOOKUP($T3,02_施策マスター!$A:$B,2,0),"")) -> AI活用基本方針・ガイドラインの策定 | V3: =IF($R3="","",$R3+(1000-ROW())/1000000) | W3: =IF($V3="","",COUNTIF($V$2:$V$208,">"&$V3)+1) | X3: baseline
A4: AIMF-GV-ORG-003 | B4: GV | C4: ORG | D4: AIリスクアセスメント・プロジェクト承認プロセスの構築 | E4: 新規AIプロジェクト開始前に機密性・影響度に応じたセキュリティ審査を義務付け、継続的アセスメント体制へシフトしていますか。 | F4: AI-Enhancement | G4: all | H4: =IF(OR($G4="all",AND(00_はじめに!$B$24="Y",ISNUMBER(SEARCH("traditional",$G4))),AND(00_はじめに!$B$25="Y",ISNUMBER(SEARCH("generative",$G4))),AND(00_はじめに!$B$26="Y",ISNUMBER(SEARCH("ai-agent",$G4))),AND(00_はじめに!$B$27="Y",ISNUMBER(SEARCH("multi-agent",$G4)))),"○","対象外") -> ○ | J4: 4 | K4: =IF(OR($H4="対象外",$I4="",$J4=""),"",$J4-$I4) | L4: 4 | M4: 3 | N4: 5 | O4: 5 | P4: 4 | Q4: 2 | R4: =IF(OR($H4="対象外",$K4="",$L4="",$M4="",$N4="",$O4="",$P4="",$Q4=""),"",($K4*$L4*$M4*$N4*$O4*$P4)/$Q4) | S4: =IF($H4="対象外","",IF(OR($I4="",$J4=""),"",IF(OR($J4-$I4>0,AND($R4<>"",$R4>=00_はじめに!$B$19)),"○",""))) | T4: =IFERROR(VLOOKUP($A4,03_質問施策マッピング!$A:$B,2,0),"") -> AIMF-GV-ORG-003 | U4: =IF($T4="","",IFERROR(VLOOKUP($T4,02_施策マスター!$A:$B,2,0),"")) -> AIリスクアセスメント・プロジェクト承認プロセスの構築 | V4: =IF($R4="","",$R4+(1000-ROW())/1000000) | W4: =IF($V4="","",COUNTIF($V$2:$V$208,">"&$V4)+1) | X4: baseline
A5: AIMF-GV-ORG-004 | B5: GV | C5: ORG | D5: AIセキュリティ文化の醸成 | E5: 定期的な教育・啓発活動を通じ、全従業員がセキュリティを意識した行動をとれる文化を醸成していますか。 | F5: AI-Enhancement | G5: all | H5: =IF(OR($G5="all",AND(00_はじめに!$B$24="Y",ISNUMBER(SEARCH("traditional",$G5))),AND(00_はじめに!$B$25="Y",ISNUMBER(SEARCH("generative",$G5))),AND(00_はじめに!$B$26="Y",ISNUMBER(SEARCH("ai-agent",$G5))),AND(00_はじめに!$B$27="Y",ISNUMBER(SEARCH("multi-agent",$G5)))),"○","対象外") -> ○ | J5: 4 | K5: =IF(OR($H5="対象外",$I5="",$J5=""),"",$J5-$I5) | L5: 4 | M5: 3 | N5: 5 | O5: 5 | P5: 4 | Q5: 2 | R5: =IF(OR($H5="対象外",$K5="",$L5="",$M5="",$N5="",$O5="",$P5="",$Q5=""),"",($K5*$L5*$M5*$N5*$O5*$P5)/$Q5) | S5: =IF($H5="対象外","",IF(OR($I5="",$J5=""),"",IF(OR($J5-$I5>0,AND($R5<>"",$R5>=00_はじめに!$B$19)),"○",""))) | T5: =IFERROR(VLOOKUP($A5,03_質問施策マッピング!$A:$B,2,0),"") -> AIMF-GV-ORG-004 | U5: =IF($T5="","",IFERROR(VLOOKUP($T5,02_施策マスター!$A:$B,2,0),"")) -> AIセキュリティ文化の醸成 | V5: =IF($R5="","",$R5+(1000-ROW())/1000000) | W5: =IF($V5="","",COUNTIF($V$2:$V$208,">"&$V5)+1) | X5: baseline
A6: AIMF-GV-ORG-005 | B6: GV | C6: ORG | D6: AIセキュリティの社内コミュニケーション強化 | E6: AIセキュリティ情報・インシデントを迅速かつ透明に共有するコミュニケーションチャネルを確立していますか。 | F6: AI-Enhancement | G6: all | H6: =IF(OR($G6="all",AND(00_はじめに!$B$24="Y",ISNUMBER(SEARCH("traditional",$G6))),AND(00_はじめに!$B$25="Y",ISNUMBER(SEARCH("generative",$G6))),AND(00_はじめに!$B$26="Y",ISNUMBER(SEARCH("ai-agent",$G6))),AND(00_はじめに!$B$27="Y",ISNUMBER(SEARCH("multi-agent",$G6)))),"○","対象外") -> ○ | J6: 4 | K6: =IF(OR($H6="対象外",$I6="",$J6=""),"",$J6-$I6) | L6: 4 | M6: 3 | N6: 5 | O6: 5 | P6: 4 | Q6: 2 | R6: =IF(OR($H6="対象外",$K6="",$L6="",$M6="",$N6="",$O6="",$P6="",$Q6=""),"",($K6*$L6*$M6*$N6*$O6*$P6)/$Q6) | S6: =IF($H6="対象外","",IF(OR($I6="",$J6=""),"",IF(OR($J6-$I6>0,AND($R6<>"",$R6>=00_はじめに!$B$19)),"○",""))) | T6: =IFERROR(VLOOKUP($A6,03_質問施策マッピング!$A:$B,2,0),"") -> AIMF-GV-ORG-005 | U6: =IF($T6="","",IFERROR(VLOOKUP($T6,02_施策マスター!$A:$B,2,0),"")) -> AIセキュリティの社内コミュニケーション強化 | V6: =IF($R6="","",$R6+(1000-ROW())/1000000) | W6: =IF($V6="","",COUNTIF($V$2:$V$208,">"&$V6)+1) | X6: baseline
A7: AIMF-GV-ORG-006 | B7: GV | C7: ORG | D7: AI統括責任者（CAIO/AIセキュリティ責任者）の任命 | E7: AIのリスクとセキュリティに関する説明責任を負う役員級の責任者を任命し、取締役会への定期報告ラインを確立していますか。 | F7: AI-Enhancement | G7: all | H7: =IF(OR($G7="all",AND(00_はじめに!$B$24="Y",ISNUMBER(SEARCH("traditional",$G7))),AND(00_はじめに!$B$25="Y",ISNUMBER(SEARCH("generative",$G7))),AND(00_はじめに!$B$26="Y",ISNUMBER(SEARCH("ai-agent",$G7))),AND(00_はじめに!$B$27="Y",ISNUMBER(SEARCH("multi-agent",$G7)))),"○","対象外") -> ○ | J7: 3 | K7: =IF(OR($H7="対象外",$I7="",$J7=""),"",$J7-$I7) | L7: 4 | M7: 3 | N7: 5 | O7: 5 | P7: 4 | Q7: 2 | R7: =IF(OR($H7="対象外",$K7="",$L7="",$M7="",$N7="",$O7="",$P7="",$Q7=""),"",($K7*$L7*$M7*$N7*$O7*$P7)/$Q7) | S7: =IF($H7="対象外","",IF(OR($I7="",$J7=""),"",IF(OR($J7-$I7>0,AND($R7<>"",$R7>=00_はじめに!$B$19)),"○",""))) | T7: =IFERROR(VLOOKUP($A7,03_質問施策マッピング!$A:$B,2,0),"") -> AIMF-GV-ORG-006 | U7: =IF($T7="","",IFERROR(VLOOKUP($T7,02_施策マスター!$A:$B,2,0),"")) -> AI統括責任者（CAIO/AIセキュリティ責任者）の任命 | V7: =IF($R7="","",$R7+(1000-ROW())/1000000) | W7: =IF($V7="","",COUNTIF($V$2:$V$208,">"&$V7)+1) | X7: extended
A8: AIMF-GV-ORG-007 | B8: GV | C8: ORG | D8: AIセキュリティ予算・リソースの確保 | E8: AI脅威の進展速度に見合うセキュリティ投資（人員・ツール・訓練）を経営レベルで確保し、毎年見直していますか。 | F8: AI-Enhancement | G8: all | H8: =IF(OR($G8="all",AND(00_はじめに!$B$24="Y",ISNUMBER(SEARCH("traditional",$G8))),AND(00_はじめに!$B$25="Y",ISNUMBER(SEARCH("generative",$G8))),AND(00_はじめに!$B$26="Y",ISNUMBER(SEARCH("ai-agent",$G8))),AND(00_はじめに!$B$27="Y",ISNUMBER(SEARCH("multi-agent",$G8)))),"○","対象外") -> ○ | J8: 3 | K8: =IF(OR($H8="対象外",$I8="",$J8=""),"",$J8-$I8) | L8: 4 | M8: 3 | N8: 5 | O8: 5 | P8: 4 | Q8: 2 | R8: =IF(OR($H8="対象外",$K8="",$L8="",$M8="",$N8="",$O8="",$P8="",$Q8=""),"",($K8*$L8*$M8*$N8*$O8*$P8)/$Q8) | S8: =IF($H8="対象外","",IF(OR($I8="",$J8=""),"",IF(OR($J8-$I8>0,AND($R8<>"",$R8>=00_はじめに!$B$19)),"○",""))) | T8: =IFERROR(VLOOKUP($A8,03_質問施策マッピング!$A:$B,2,0),"") -> AIMF-GV-ORG-007 | U8: =IF($T8="","",IFERROR(VLOOKUP($T8,02_施策マスター!$A:$B,2,0),"")) -> AIセキュリティ予算・リソースの確保 | V8: =IF($R8="","",$R8+(1000-ROW())/1000000) | W8: =IF($V8="","",COUNTIF($V$2:$V$208,">"&$V8)+1) | X8: extended
A9: AIMF-GV-ORG-008 | B9: GV | C9: ORG | D9: AIライフサイクル全体のRACI定義 | E9: 企画・開発・評価・運用・廃棄の各フェーズにおける実行責任・説明責任・協業・報告先をRACIとして文書化していますか。 | F9: AI-Enhancement | G9: all | H9: =IF(OR($G9="all",AND(00_はじめに!$B$24="Y",ISNUMBER(SEARCH("traditional",$G9))),AND(00_はじめに!$B$25="Y",ISNUMBER(SEARCH("generative",$G9))),AND(00_はじめに!$B$26="Y",ISNUMBER(SEARCH("ai-agent",$G9))),AND(00_はじめに!$B$27="Y",ISNUMBER(SEARCH("multi-agent",$G9)))),"○","対象外") -> ○ | J9: 3 | K9: =IF(OR($H9="対象外",$I9="",$J9=""),"",$J9-$I9) | L9: 4 | M9: 3 | N9: 5 | O9: 5 | P9: 4 | Q9: 2 | R9: =IF(OR($H9="対象外",$K9="",$L9="",$M9="",$N9="",$O9="",$P9="",$Q9=""),"",($K9*$L9*$M9*$N9*$O9*$P9)/$Q9) | S9: =IF($H9="対象外","",IF(OR($I9="",$J9=""),"",IF(OR($J9-$I9>0,AND($R9<>"",$R9>=00_はじめに!$B$19)),"○",""))) | T9: =IFERROR(VLOOKUP($A9,03_質問施策マッピング!$A:$B,2,0),"") -> AIMF-GV-ORG-008 | U9: =IF($T9="","",IFERROR(VLOOKUP($T9,02_施策マスター!$A:$B,2,0),"")) -> AIライフサイクル全体のRACI定義 | V9: =IF($R9="","",$R9+(1000-ROW())/1000000) | W9: =IF($V9="","",COUNTIF($V$2:$V$208,">"&$V9)+1) | X9: extended
A10: AIMF-GV-ORG-009 | B10: GV | C10: ORG | D10: AI倫理審査との連携プロセス | E10: セキュリティ審査とAI倫理・責任あるAI審査の役割分担と連携手順を定義し、二重審査の漏れと重複を防いでいますか。 | F10: AI-Enhancement | G10: all | H10: =IF(OR($G10="all",AND(00_はじめに!$B$24="Y",ISNUMBER(SEARCH("traditional",$G10))),AND(00_はじめに!$B$25="Y",ISNUMBER(SEARCH("generative",$G10))),AND(00_はじめに!$B$26="Y",ISNUMBER(SEARCH("ai-agent",$G10))),AND(00_はじめに!$B$27="Y",ISNUMBER(SEARCH("multi-agent",$G10)))),"○","対象外") -> ○ | J10: 3 | K10: =IF(OR($H10="対象外",$I10="",$J10=""),"",$J10-$I10) | L10: 4 | M10: 3 | N10: 5 | O10: 5 | P10: 4 | Q10: 2 | R10: =IF(OR($H10="対象外",$K10="",$L10="",$M10="",$N10="",$O10="",$P10="",$Q10=""),"",($K10*$L10*$M10*$N10*$O10*$P10)/$Q10) | S10: =IF($H10="対象外","",IF(OR($I10="",$J10=""),"",IF(OR($J10-$I10>0,AND($R10<>"",$R10>=00_はじめに!$B$19)),"○",""))) | T10: =IFERROR(VLOOKUP($A10,03_質問施策マッピング!$A:$B,2,0),"") -> AIMF-GV-ORG-009 | U10: =IF($T10="","",IFERROR(VLOOKUP($T10,02_施策マスター!$A:$B,2,0),"")) -> AI倫理審査との連携プロセス | V10: =IF($R10="","",$R10+(1000-ROW())/1000000) | W10: =IF($V10="","",COUNTIF($V$2:$V$208,">"&$V10)+1) | X10: extended
A11: AIMF-GV-POL-001 | B11: GV | C11: POL | D11: AIポリシースイートの体系化 | E11: AI利用方針・開発方針・調達方針・データ利用方針を階層的な規程体系として整備し、相互参照と版管理を行っていますか。 | F11: AI-Enhancement | G11: all | H11: =IF(OR($G11="all",AND(00_はじめに!$B$24="Y",ISNUMBER(SEARCH("traditional",$G11))),AND(00_はじめに!$B$25="Y",ISNUMBER(SEARCH("generative",$G11))),AND(00_はじめに!$B$26="Y",ISNUMBER(SEARCH("ai-agent",$G11))),AND(00_はじめに!$B$27="Y",ISNUMBER(SEARCH("multi-agent",$G11)))),"○","対象外") -> ○ | J11: 3 | K11: =IF(OR($H11="対象外",$I11="",$J11=""),"",$J11-$I11) | L11: 4 | M11: 3 | N11: 5 | O11: 5 | P11: 4 | Q11: 2 | R11: =IF(OR($H11="対象外",$K11="",$L11="",$M11="",$N11="",$O11="",$P11="",$Q11=""),"",($K11*$L11*$M11*$N11*$O11*$P11)/$Q11) | S11: =IF($H11="対象外","",IF(OR($I11="",$J11=""),"",IF(OR($J11-$I11>0,AND($R11<>"",$R11>=00_はじめに!$B$19)),"○",""))) | T11: =IFERROR(VLOOKUP($A11,03_質問施策マッピング!$A:$B,2,0),"") -> AIMF-GV-POL-001 | U11: =IF($T11="","",IFERROR(VLOOKUP($T11,02_施策マスター!$A:$B,2,0),"")) -> AIポリシースイートの体系化 | V11: =IF($R11="","",$R11+(1000-ROW())/1000000) | W11: =IF($V11="","",COUNTIF($V$2:$V$208,">"&$V11)+1) | X11: extended
A12: AIMF-GV-POL-002 | B12: GV | C12: POL | D12: 生成AI利用細則（入力禁止情報・プロンプト取扱規程） | E12: 機密情報・個人情報の入力制限、プロンプトの取扱い、出力の業務利用条件を利用者向け細則として定めていますか。 | F12: AI-Expansion | G12: generative-ai | H12: =IF(OR($G12="all",AND(00_はじめに!$B$24="Y",ISNUMBER(SEARCH("traditional",$G12))),AND(00_はじめに!$B$25="Y",ISNUMBER(SEARCH("generative",$G12))),AND(00_はじめに!$B$26="Y",ISNUMBER(SEARCH("ai-agent",$G12))),AND(00_はじめに!$B$27="Y",ISNUMBER(SEARCH("multi-agent",$G12)))),"○","対象外") -> ○ | J12: 3 | K12: =IF(OR($H12="対象外",$I12="",$J12=""),"",$J12-$I12) | L12: 4 | M12: 3 | N12: 5 | O12: 3 | P12: 4 | Q12: 3 | R12: =IF(OR($H12="対象外",$K12="",$L12="",$M12="",$N12="",$O12="",$P12="",$Q12=""),"",($K12*$L12*$M12*$N12*$O12*$P12)/$Q12) | S12: =IF($H12="対象外","",IF(OR($I12="",$J12=""),"",IF(OR($J12-$I12>0,AND($R12<>"",$R12>=00_はじめに!$B$19)),"○",""))) | T12: =IFERROR(VLOOKUP($A12,03_質問施策マッピング!$A:$B,2,0),"") -> AIMF-GV-POL-002 | U12: =IF($T12="","",IFERROR(VLOOKUP($T12,02_施策マスター!$A:$B,2,0),"")) -> 生成AI利用細則（入力禁止情報・プロンプト取扱規程） | V12: =IF($R12="","",$R12+(1000-ROW())/1000000) | W12: =IF($V12="","",COUNTIF($V$2:$V$208,">"&$V12)+1) | X12: extended
A13: AIMF-GV-POL-003 | B13: GV | C13: POL | D13: 承認済みAIサービスカタログと例外管理 | E13: 利用を許可するAIサービス・モデルのカタログを維持し、カタログ外利用の例外承認・期限付き許可プロセスを運用していますか。 | F13: AI-Enhancement | G13: all | H13: =IF(OR($G13="all",AND(00_はじめに!$B$24="Y",ISNUMBER(SEARCH("traditional",$G13))),AND(00_はじめに!$B$25="Y",ISNUMBER(SEARCH("generative",$G13))),AND(00_はじめに!$B$26="Y",ISNUMBER(SEARCH("ai-agent",$G13))),AND(00_はじめに!$B$27="Y",ISNUMBER(SEARCH("multi-agent",$G13)))),"○","対象外") -> ○ | J13: 3 | K13: =IF(OR($H13="対象外",$I13="",$J13=""),"",$J13-$I13) | L13: 4 | M13: 3 | N13: 5 | O13: 5 | P13: 4 | Q13: 2 | R13: =IF(OR($H13="対象外",$K13="",$L13="",$M13="",$N13="",$O13="",$P13="",$Q13=""),"",($K13*$L13*$M13*$N13*$O13*$P13)/$Q13) | S13: =IF($H13="対象外","",IF(OR($I13="",$J13=""),"",IF(OR($J13-$I13>0,AND($R13<>"",$R13>=00_はじめに!$B$19)),"○",""))) | T13: =IFERROR(VLOOKUP($A13,03_質問施策マッピング!$A:$B,2,0),"") -> AIMF-GV-POL-003 | U13: =IF($T13="","",IFERROR(VLOOKUP($T13,02_施策マスター!$A:$B,2,0),"")) -> 承認済みAIサービスカタログと例外管理 | V13: =IF($R13="","",$R13+(1000-ROW())/1000000) | W13: =IF($V13="","",COUNTIF($V$2:$V$208,">"&$V13)+1) | X13: extended
... A208: AIMF-RC-PMM-001 | B208: RC | C208: PMM | D208: 市販後モニタリング計画（Post-market Monitoring） | E208: 提供中のAIシステムについて、性能・堅牢性・インシデント傾向を体系的に収集・分析する市販後モニタリング計画を策定し、リスクマネジメント（GV-1）へフィードバックしていますか。 | F208: AI-Expansion | G208: all | H208: =IF(OR($G208="all",AND(00_はじめに!$B$24="Y",ISNUMBER(SEARCH("traditional",$G208))),AND(00_はじめに!$B$25="Y",ISNUMBER(SEARCH("generative",$G208))),AND(00_はじめに!$B$26="Y",ISNUMBER(SEARCH("ai-agent",$G208))),AND(00_はじめに!$B$27="Y",ISNUMBER(SEARCH("multi-agent",$G208)))),"○","対象外") -> ○ | J208: 4 | K208: =IF(OR($H208="対象外",$I208="",$J208=""),"",$J208-$I208) | L208: 4 | M208: 3 | N208: 5 | O208: 2 | P208: 3 | Q208: 3 | R208: =IF(OR($H208="対象外",$K208="",$L208="",$M208="",$N208="",$O208="",$P208="",$Q208=""),"",($K208*$L208*$M208*$N208*$O208*$P208)/$Q208) | S208: =IF($H208="対象外","",IF(OR($I208="",$J208=""),"",IF(OR($J208-$I208>0,AND($R208<>"",$R208>=00_はじめに!$B$19)),"○",""))) | T208: =IFERROR(VLOOKUP($A208,03_質問施策マッピング!$A:$B,2,0),"") -> AIMF-RC-PMM-001 | U208: =IF($T208="","",IFERROR(VLOOKUP($T208,02_施策マスター!$A:$B,2,0),"")) -> 市販後モニタリング計画（Post-market Monitoring） | V208: =IF($R208="","",$R208+(1000-ROW())/1000000) | W208: =IF($V208="","",COUNTIF($V$2:$V$208,">"&$V208)+1) | X208: baseline

Sheet 02_施策マスター
A1: 施策ID | B1: 施策名 | C1: 区分 | D1: カテゴリ | E1: 施策概要 | F1: 目的 | G1: 期待効果(1-5) | H1: 導入難易度(1-5) | I1: 標準期間(月) | J1: 概算費用区分 | K1: QuickWin係数 | L1: 依存施策ID | M1: control-type | N1: 主な参照基準 | O1: ロードマップ区分 | P1: 優先度補正係数 | Q1: 主担当部門 | R1: 標準成果物 | S1: 顧客説明用価値 | T1: 確認証跡例 | U1: 関連質問ID | V1: introduced-in
A2: AIMF-GV-ORG-001 | B2: AIガバナンス委員会の設置 | C2: GV | D2: ORG | E2: 経営層、CISO、法務、IT部門、事業部門の代表からなるクロスファンクショナルな統治組織を組成し、責任の所在を明確にする。 | F2: ガバナンス・組織体制の確立と文化の醸成に関するリスクを低減し、AIMF GV区分（ORGカテゴリ）の要求に対応する。 | G2: 4 | H2: 2 | I2: 3 | J2: 低 | K2: 1.5 | M2: AI-Enhancement | N2: AI事業者GL, NIST AI RMF, ISO 42001, CSA AICM, EU AI Act | O2: 短期 | P2: 1.2 | Q2: 経営層/リスク管理/法務 | R2: 方針・規程、会議体議事録、リスク登録簿、監査報告 | S2: AIガバナンス委員会の設置により、経営として説明可能なAIガバナンス体制を示せる状態になります。 | T2: 規程・議事録・登録簿・監査記録 | U2: AIMF-GV-ORG-001 | V2: baseline
A3: AIMF-GV-ORG-002 | B3: AI活用基本方針・ガイドラインの策定 | C3: GV | D3: ORG | E3: 全社的なAI利用の目的、許容リスクレベル、禁止事項（機密情報の公衆AIへの入力禁止等）を定義・規程化する。 | F3: ガバナンス・組織体制の確立と文化の醸成に関するリスクを低減し、AIMF GV区分（ORGカテゴリ）の要求に対応する。 | G3: 4 | H3: 2 | I3: 3 | J3: 低 | K3: 1.5 | M3: AI-Enhancement | N3: AI事業者GL, NIST AI RMF, ISO 42001, CSA AICM, NCSC/CISA | O3: 短期 | P3: 1 | Q3: 経営層/リスク管理/法務 | R3: 方針・規程、会議体議事録、リスク登録簿、監査報告 | S3: AI活用基本方針・ガイドラインの策定により、経営として説明可能なAIガバナンス体制を示せる状態になります。 | T3: 規程・議事録・登録簿・監査記録 | U3: AIMF-GV-ORG-002 | V3: baseline
A4: AIMF-GV-ORG-003 | B4: AIリスクアセスメント・プロジェクト承認プロセスの構築 | C4: GV | D4: ORG | E4: 新規AIプロジェクト開始前に機密性・影響度に応じたセキュリティ審査を義務付け、継続的アセスメント体制へシフトする。 | F4: ガバナンス・組織体制の確立と文化の醸成に関するリスクを低減し、AIMF GV区分（ORGカテゴリ）の要求に対応する。 | G4: 4 | H4: 2 | I4: 3 | J4: 低 | K4: 1.5 | M4: AI-Enhancement | N4: NIST AI RMF, ISO 42001, EU AI Act, CSA AICM, NCSC/CISA, AI事業者GL | O4: 短期 | P4: 1.2 | Q4: 経営層/リスク管理/法務 | R4: 方針・規程、会議体議事録、リスク登録簿、監査報告 | S4: AIリスクアセスメント・プロジェクト承認プロセスの構築により、経営として説明可能なAIガバナンス体制を示せる状態になります。 | T4: 規程・議事録・登録簿・監査記録 | U4: AIMF-GV-ORG-003 | V4: baseline
A5: AIMF-GV-ORG-004 | B5: AIセキュリティ文化の醸成 | C5: GV | D5: ORG | E5: 定期的な教育・啓発活動を通じ、全従業員がセキュリティを意識した行動をとれる文化を醸成する。 | F5: ガバナンス・組織体制の確立と文化の醸成に関するリスクを低減し、AIMF GV区分（ORGカテゴリ）の要求に対応する。 | G5: 4 | H5: 2 | I5: 3 | J5: 低 | K5: 1.5 | M5: AI-Enhancement | N5: NIST AI RMF, ISO 42001, AI事業者GL, EU AI Act, CSA AICM | O5: 短期 | P5: 1.2 | Q5: 経営層/リスク管理/法務 | R5: 方針・規程、会議体議事録、リスク登録簿、監査報告 | S5: AIセキュリティ文化の醸成により、経営として説明可能なAIガバナンス体制を示せる状態になります。 | T5: 規程・議事録・登録簿・監査記録 | U5: AIMF-GV-ORG-004 | V5: baseline
A6: AIMF-GV-ORG-005 | B6: AIセキュリティの社内コミュニケーション強化 | C6: GV | D6: ORG | E6: AIセキュリティ情報・インシデントを迅速かつ透明に共有するコミュニケーションチャネルを確立する。 | F6: ガバナンス・組織体制の確立と文化の醸成に関するリスクを低減し、AIMF GV区分（ORGカテゴリ）の要求に対応する。 | G6: 4 | H6: 2 | I6: 3 | J6: 低 | K6: 1.5 | M6: AI-Enhancement | N6: ISO 42001, NIST AI RMF, CSA AICM | O6: 短期 | P6: 1 | Q6: 経営層/リスク管理/法務 | R6: 方針・規程、会議体議事録、リスク登録簿、監査報告 | S6: AIセキュリティの社内コミュニケーション強化により、経営として説明可能なAIガバナンス体制を示せる状態になります。 | T6: 規程・議事録・登録簿・監査記録 | U6: AIMF-GV-ORG-005 | V6: baseline
A7: AIMF-GV-ORG-006 | B7: AI統括責任者（CAIO/AIセキュリティ責任者）の任命 | C7: GV | D7: ORG | E7: AIのリスクとセキュリティに関する説明責任を負う役員級の責任者を任命し、取締役会への定期報告ラインを確立する。 | F7: ガバナンス・組織体制の確立と文化の醸成に関するリスクを低減し、AIMF GV区分（ORGカテゴリ）の要求に対応する。 | G7: 4 | H7: 2 | I7: 3 | J7: 低 | K7: 1.5 | M7: AI-Enhancement | N7: NIST AI RMF, ISO 42001, Five Eyes声明, SANS AIMM | O7: 短期 | P7: 1 | Q7: 経営層/リスク管理/法務 | R7: 方針・規程、会議体議事録、リスク登録簿、監査報告 | S7: AI統括責任者（CAIO/AIセキュリティ責任者）の任命により、経営として説明可能なAIガバナンス体制を示せる状態になります。 | T7: 規程・議事録・登録簿・監査記録 | U7: AIMF-GV-ORG-006 | V7: extended
A8: AIMF-GV-ORG-007 | B8: AIセキュリティ予算・リソースの確保 | C8: GV | D8: ORG | E8: AI脅威の進展速度に見合うセキュリティ投資（人員・ツール・訓練）を経営レベルで確保し、毎年見直す。 | F8: ガバナンス・組織体制の確立と文化の醸成に関するリスクを低減し、AIMF GV区分（ORGカテゴリ）の要求に対応する。 | G8: 4 | H8: 2 | I8: 3 | J8: 低 | K8: 1.5 | M8: AI-Enhancement | N8: Five Eyes声明, NIST AI RMF, CSA AICM | O8: 短期 | P8: 1 | Q8: 経営層/リスク管理/法務 | R8: 方針・規程、会議体議事録、リスク登録簿、監査報告 | S8: AIセキュリティ予算・リソースの確保により、経営として説明可能なAIガバナンス体制を示せる状態になります。 | T8: 規程・議事録・登録簿・監査記録 | U8: AIMF-GV-ORG-007 | V8: extended
A9: AIMF-GV-ORG-008 | B9: AIライフサイクル全体のRACI定義 | C9: GV | D9: ORG | E9: 企画・開発・評価・運用・廃棄の各フェーズにおける実行責任・説明責任・協業・報告先をRACIとして文書化する。 | F9: ガバナンス・組織体制の確立と文化の醸成に関するリスクを低減し、AIMF GV区分（ORGカテゴリ）の要求に対応する。 | G9: 4 | H9: 2 | I9: 3 | J9: 低 | K9: 1.5 | M9: AI-Enhancement | N9: ISO 42001, NIST AI RMF, ASDエージェントAI | O9: 短期 | P9: 1 | Q9: 経営層/リスク管理/法務 | R9: 方針・規程、会議体議事録、リスク登録簿、監査報告 | S9: AIライフサイクル全体のRACI定義により、経営として説明可能なAIガバナンス体制を示せる状態になります。 | T9: 規程・議事録・登録簿・監査記録 | U9: AIMF-GV-ORG-008 | V9: extended
A10: AIMF-GV-ORG-009 | B10: AI倫理審査との連携プロセス | C10: GV | D10: ORG | E10: セキュリティ審査とAI倫理・責任あるAI審査の役割分担と連携手順を定義し、二重審査の漏れと重複を防ぐ。 | F10: ガバナンス・組織体制の確立と文化の醸成に関するリスクを低減し、AIMF GV区分（ORGカテゴリ）の要求に対応する。 | G10: 4 | H10: 2 | I10: 3 | J10: 低 | K10: 1.5 | M10: AI-Enhancement | N10: AI事業者GL, ISO 42001, NIST AI RMF | O10: 短期 | P10: 1 | Q10: 経営層/リスク管理/法務 | R10: 方針・規程、会議体議事録、リスク登録簿、監査報告 | S10: AI倫理審査との連携プロセスにより、経営として説明可能なAIガバナンス体制を示せる状態になります。 | T10: 規程・議事録・登録簿・監査記録 | U10: AIMF-GV-ORG-009 | V10: extended
A11: AIMF-GV-POL-001 | B11: AIポリシースイートの体系化 | C11: GV | D11: POL | E11: AI利用方針・開発方針・調達方針・データ利用方針を階層的な規程体系として整備し、相互参照と版管理を行う。 | F11: AI方針・規程体系に関するリスクを低減し、AIMF GV区分（POLカテゴリ）の要求に対応する。 | G11: 4 | H11: 2 | I11: 3 | J11: 低 | K11: 1.5 | M11: AI-Enhancement | N11: ISO 42001, NIST AI RMF, SANS AIMM | O11: 短期 | P11: 1 | Q11: 経営層/リスク管理/法務 | R11: 方針・規程、会議体議事録、リスク登録簿、監査報告 | S11: AIポリシースイートの体系化により、経営として説明可能なAIガバナンス体制を示せる状態になります。 | T11: 規程・議事録・登録簿・監査記録 | U11: AIMF-GV-POL-001 | V11: extended
A12: AIMF-GV-POL-002 | B12: 生成AI利用細則（入力禁止情報・プロンプト取扱規程） | C12: GV | D12: POL | E12: 機密情報・個人情報の入力制限、プロンプトの取扱い、出力の業務利用条件を利用者向け細則として定める。 | F12: AI方針・規程体系に関するリスクを低減し、AIMF GV区分（POLカテゴリ）の要求に対応する。 | G12: 4 | H12: 3 | I12: 6 | J12: 中 | K12: 1.2 | M12: AI-Expansion | N12: デジタル庁GL, AI事業者GL, 総務省AIセキュリティGL | O12: 中期 | P12: 1 | Q12: 経営層/リスク管理/法務 | R12: 方針・規程、会議体議事録、リスク登録簿、監査報告 | S12: 生成AI利用細則（入力禁止情報・プロンプト取扱規程）により、経営として説明可能なAIガバナンス体制を示せる状態になります。 | T12: 規程・議事録・登録簿・監査記録 | U12: AIMF-GV-POL-002 | V12: extended
A13: AIMF-GV-POL-003 | B13: 承認済みAIサービスカタログと例外管理 | C13: GV | D13: POL | E13: 利用を許可するAIサービス・モデルのカタログを維持し、カタログ外利用の例外承認・期限付き許可プロセスを運用する。 | F13: AI方針・規程体系に関するリスクを低減し、AIMF GV区分（POLカテゴリ）の要求に対応する。 | G13: 4 | H13: 2 | I13: 3 | J13: 低 | K13: 1.5 | M13: AI-Enhancement | N13: CIS v8.1, NIST AI RMF, デジタル庁GL | O13: 短期 | P13: 1 | Q13: 経営層/リスク管理/法務 | R13: 方針・規程、会議体議事録、リスク登録簿、監査報告 | S13: 承認済みAIサービスカタログと例外管理により、経営として説明可能なAIガバナンス体制を示せる状態になります。 | T13: 規程・議事録・登録簿・監査記録 | U13: AIMF-GV-POL-003 | V13: extended
... A78: AIMF-PR-INF-007 | B78: AIリソース設定のセキュリティベースライン | C78: PR | D78: INF | E78: ベクトルDB・推論サーバー・オーケストレーターのセキュア設定基準を定義し、IaCスキャンで逸脱を継続検出する。 | F78: AIインフラ・ネットワークの要塞化に関するリスクを低減し、AIMF PR区分（INFカテゴリ）の要求に対応する。 | G78: 4 | H78: 3 | I78: 6 | J78: 中 | K78: 1.5 | M78: AI-Enhancement | N78: CIS v8.1, CSA AICM, ASDエージェントAI | O78: 中期 | P78: 1 | Q78: セキュリティ部門/AI開発/IT基盤 | R78: 設計書、設定記録、評価レポート、教育記録 | S78: AIリソース設定のセキュリティベースラインにより、AI固有の攻撃・誤動作を未然に防ぐ実装統制が整います。 | T78: 設定画面・テスト結果・パイプライン定義 | U78: AIMF-PR-INF-007 | V78: extended
A79: AIMF-PR-IAM-001 | B79: RAGデータアクセス権（ACL）の同期 | C79: PR | D79: IAM | E79: 社内のアイデンティティ／ファイル権限とRAGのベクトルDBを完全同期し、閲覧権限を超えた情報のプロンプト混入をシステム的に防ぐ。 | F79: アイデンティティ・アクセス制御に関するリスクを低減し、AIMF PR区分（IAMカテゴリ）の要求に対応する。 | G79: 5 | H79: 4 | I79: 9 | J79: 高 | K79: 1 | L79: AIMF-ID-AST-002 | M79: AI-Expansion | N79: OWASP AISVS, CSA AICM, 総務省AIセキュリティGL, EU AI Act, NCSC/CISA, NIST AI RMF | O79: 長期 | P79: 1.2 | Q79: セキュリティ部門/AI開発/IT基盤 | R79: 設計書、設定記録、評価レポート、教育記録 | S79: RAGデータアクセス権（ACL）の同期により、AI固有の攻撃・誤動作を未然に防ぐ実装統制が整います。 | T79: 設定画面・テスト結果・パイプライン定義 | U79: AIMF-PR-IAM-001 | V79: baseline
A80: AIMF-PR-IAM-002 | B80: AIエージェントへの最小権限原則の適用 | C80: PR | D80: IAM | E80: 自律エージェントに付与するAPIキー・操作権限を担当業務に必要な最小限に制限する。 | F80: アイデンティティ・アクセス制御に関するリスクを低減し、AIMF PR区分（IAMカテゴリ）の要求に対応する。 | G80: 5 | H80: 4 | I80: 9 | J80: 高 | K80: 1 | L80: AIMF-ID-AST-003 | M80: AI-Expansion | N80: OWASP AISVS, CSA AICM, NCSC/CISA, EU AI Act | O80: 長期 | P80: 1.2 | Q80: セキュリティ部門/AI開発/IT基盤 | R80: 設計書、設定記録、評価レポート、教育記録 | S80: AIエージェントへの最小権限原則の適用により、AI固有の攻撃・誤動作を未然に防ぐ実装統制が整います。 | T80: 設定画面・テスト結果・パイプライン定義 | U80: AIMF-PR-IAM-002 | V80: baseline
A81: AIMF-PR-IAM-003 | B81: AIクレデンシャル・APIキーの暗号化管理 | C81: PR | D81: IAM | E81: 各種キーをハードコードせず、シークレットマネージャーで暗号化し動的に呼び出す。 | F81: アイデンティティ・アクセス制御に関するリスクを低減し、AIMF PR区分（IAMカテゴリ）の要求に対応する。 | G81: 5 | H81: 3 | I81: 6 | J81: 中 | K81: 1.5 | M81: AI-Enhancement | N81: OWASP AISVS, CSA AICM, 総務省AIセキュリティGL, NCSC/CISA | O81: 中期 | P81: 1 | Q81: セキュリティ部門/AI開発/IT基盤 | R81: 設計書、設定記録、評価レポート、教育記録 | S81: AIクレデンシャル・APIキーの暗号化管理により、AI固有の攻撃・誤動作を未然に防ぐ実装統制が整います。 | T81: 設定画面・テスト結果・パイプライン定義 | U81: AIMF-PR-IAM-003 | V81: baseline
A82: AIMF-PR-IAM-004 | B82: フィッシング耐性MFAの適用（AI管理者・特権） | C82: PR | D82: IAM | E82: AI基盤の管理者・モデルレジストリ・学習パイプラインへのアクセスにフィッシング耐性認証（AAL2以上、パスキー/FIDO2等）を義務付ける。 | F82: アイデンティティ・アクセス制御に関するリスクを低減し、AIMF PR区分（IAMカテゴリ）の要求に対応する。 | G82: 5 | H82: 3 | I82: 6 | J82: 中 | K82: 1.5 | M82: AI-Enhancement | N82: NIST 800-63-4, CIS v8.1, Five Eyes声明 | O82: 中期 | P82: 1 | Q82: セキュリティ部門/AI開発/IT基盤 | R82: 設計書、設定記録、評価レポート、教育記録 | S82: フィッシング耐性MFAの適用（AI管理者・特権）により、AI固有の攻撃・誤動作を未然に防ぐ実装統制が整います。 | T82: 設定画面・テスト結果・パイプライン定義 | U82: AIMF-PR-IAM-004 | V82: extended
A83: AIMF-PR-IAM-005 | B83: エージェント・サービスアカウントのライフサイクル管理 | C83: PR | D83: IAM | E83: 各エージェントに専用の非人間アイデンティティを発行し、作成・権限変更・棚卸し・廃止をライフサイクル管理する。 | F83: アイデンティティ・アクセス制御に関するリスクを低減し、AIMF PR区分（IAMカテゴリ）の要求に対応する。 | G83: 5 | H83: 4 | I83: 9 | J83: 高 | K83: 1 | M83: AI-Expansion | N83: OWASP ASI10, NIST 800-63-4, CSA AICM | O83: 長期 | P83: 1 | Q83: セキュリティ部門/AI開発/IT基盤 | R83: 設計書、設定記録、評価レポート、教育記録 | S83: エージェント・サービスアカウントのライフサイクル管理により、AI固有の攻撃・誤動作を未然に防ぐ実装統制が整います。 | T83: 設定画面・テスト結果・パイプライン定義 | U83: AIMF-PR-IAM-005 | V83: extended
A84: AIMF-PR-IAM-006 | B84: 短命トークン・タスクバウンド認可 | C84: PR | D84: IAM | E84: エージェントの認可を短命トークンとタスク単位のスコープに限定し、恒久的な広域クレデンシャルの付与を禁止する。 | F84: アイデンティティ・アクセス制御に関するリスクを低減し、AIMF PR区分（IAMカテゴリ）の要求に対応する。 | G84: 5 | H84: 4 | I84: 9 | J84: 高 | K84: 1 | L84: AIMF-PR-IAM-005 | M84: AI-Expansion | N84: OWASP ASI10, ASDエージェントAI | O84: 長期 | P84: 1 | Q84: セキュリティ部門/AI開発/IT基盤 | R84: 設計書、設定記録、評価レポート、教育記録 | S84: 短命トークン・タスクバウンド認可により、AI固有の攻撃・誤動作を未然に防ぐ実装統制が整います。 | T84: 設定画面・テスト結果・パイプライン定義 | U84: AIMF-PR-IAM-006 | V84: extended
A85: AIMF-PR-IAM-007 | B85: 動的な権限昇格の禁止とJITアクセス | C85: PR | D85: IAM | E85: エージェントによる実行時の権限昇格・スコープ拡大を禁止し、例外は人間承認付きのJIT（Just-in-Time）アクセスに限定する。 | F85: アイデンティティ・アクセス制御に関するリスクを低減し、AIMF PR区分（IAMカテゴリ）の要求に対応する。 | G85: 5 | H85: 4 | I85: 9 | J85: 高 | K85: 1 | M85: AI-Expansion | N85: OWASP ASI10, CIS v8.1, ASDエージェントAI | O85: 長期 | P85: 1 | Q85: セキュリティ部門/AI開発/IT基盤 | R85: 設計書、設定記録、評価レポート、教育記録 | S85: 動的な権限昇格の禁止とJITアクセスにより、AI固有の攻撃・誤動作を未然に防ぐ実装統制が整います。 | T85: 設定画面・テスト結果・パイプライン定義 | U85: AIMF-PR-IAM-007 | V85: extended
A86: AIMF-PR-IAM-008 | B86: AIプラットフォームのRBAC/ABAC設計 | C86: PR | D86: IAM | E86: モデル・データセット・プロンプト・評価結果への操作権限をロール・属性ベースで設計し、職務分離を実装する。 | F86: アイデンティティ・アクセス制御に関するリスクを低減し、AIMF PR区分（IAMカテゴリ）の要求に対応する。 | G86: 5 | H86: 3 | I86: 6 | J86: 中 | K86: 1.5 | M86: AI-Enhancement | N86: OWASP AISVS, CIS v8.1, CSA AICM | O86: 中期 | P86: 1 | Q86: セキュリティ部門/AI開発/IT基盤 | R86: 設計書、設定記録、評価レポート、教育記録 | S86: AIプラットフォームのRBAC/ABAC設計により、AI固有の攻撃・誤動作を未然に防ぐ実装統制が整います。 | T86: 設定画面・テスト結果・パイプライン定義 | U86: AIMF-PR-IAM-008 | V86: extended
A87: AIMF-PR-DAT-001 | B87: プロンプト・出力へのDLP統制 | C87: PR | D87: DAT | E87: プロンプト入力および出力経路にDLPを適用し、機密情報・個人情報の外部AIサービスへの送信と出力経由の漏えいを制御する。 | F87: AIデータ保護に関するリスクを低減し、AIMF PR区分（DATカテゴリ）の要求に対応する。 | G87: 5 | H87: 4 | I87: 9 | J87: 高 | K87: 1 | M87: AI-Expansion | N87: CIS v8.1, デジタル庁GL, OWASP AISVS | O87: 長期 | P87: 1 | Q87: セキュリティ部門/AI開発/IT基盤 | R87: 設計書、設定記録、評価レポート、教育記録 | S87: プロンプト・出力へのDLP統制により、AI固有の攻撃・誤動作を未然に防ぐ実装統制が整います。 | T87: 設定画面・テスト結果・パイプライン定義 | U87: AIMF-PR-DAT-001 | V87: extended
A88: AIMF-PR-DAT-002 | B88: 学習・RAG投入前の仮名化・匿名化 | C88: PR | D88: DAT | E88: 学習・RAGへ投入する個人データに仮名化・匿名化・トークナイゼーションを適用し、再識別リスクを評価する。 | F88: AIデータ保護に関するリスクを低減し、AIMF PR区分（DATカテゴリ）の要求に対応する。 | G88: 5 | H88: 4 | I88: 9 | J88: 高 | K88: 1 | M88: AI-Expansion | N88: OWASP AISVS, EU AI Act, ISO 42001 | O88: 長期 | P88: 1.2 | Q88: セキュリティ部門/AI開発/IT基盤 | R88: 設計書、設定記録、評価レポート、教育記録 | S88: 学習・RAG投入前の仮名化・匿名化により、AI固有の攻撃・誤動作を未然に防ぐ実装統制が整います。 | T88: 設定画面・テスト結果・パイプライン定義 | U88: AIMF-PR-DAT-002 | V88: extended
A89: AIMF-PR-DAT-003 | B89: 出力データへの機密区分の継承 | C89: PR | D89: DAT | E89: 機密データを参照して生成された出力に元データの機密区分を継承させ、取扱い・保存・共有の制限を適用する。 | F89: AIデータ保護に関するリスクを低減し、AIMF PR区分（DATカテゴリ）の要求に対応する。 | G89: 5 | H89: 4 | I89: 9 | J89: 高 | K89: 1 | M89: AI-Expansion | N89: CIS v8.1, ISO 42001, OWASP AISVS | O89: 長期 | P89: 1 | Q89: セキュリティ部門/AI開発/IT基盤 | R89: 設計書、設定記録、評価レポート、教育記録 | S89: 出力データへの機密区分の継承により、AI固有の攻撃・誤動作を未然に防ぐ実装統制が整います。 | T89: 設定画面・テスト結果・パイプライン定義 | U89: AIMF-PR-DAT-003 | V89: extended
A90: AIMF-PR-DAT-004 | B90: モデル重み・チェックポイントの厳格アクセス管理 | C90: PR | D90: DAT | E90: モデル重み・チェックポイント・アダプタへのアクセスを職務上必要な主体に限定し、持出し検知と併せて知財流出を防ぐ。 | F90: AIデータ保護に関するリスクを低減し、AIMF PR区分（DATカテゴリ）の要求に対応する。 | G90: 5 | H90: 4 | I90: 9 | J90: 高 | K90: 1 | M90: AI-Expansion | N90: NCSC/CISA, OWASP AISVS, MITRE ATLAS | O90: 長期 | P90: 1 | Q90: セキュリティ部門/AI開発/IT基盤 | R90: 設計書、設定記録、評価レポート、教育記録 | S90: モデル重み・チェックポイントの厳格アクセス管理により、AI固有の攻撃・誤動作を未然に防ぐ実装統制が整います。 | T90: 設定画面・テスト結果・パイプライン定義 | U90: AIMF-PR-DAT-004 | V90: extended
A91: AIMF-PR-DAT-005 | B91: 機密コンピューティングによる推論保護 | C91: PR | D91: DAT | E91: 高機微ユースケースにおいて、TEE等の機密コンピューティングにより推論時のデータ・モデルをメモリ上でも保護する。 | F91: AIデータ保護に関するリスクを低減し、AIMF PR区分（DATカテゴリ）の要求に対応する。 | G91: 5 | H91: 4 | I91: 9 | J91: 高 | K91: 1 | M91: AI-Expansion | N91: CSA AICM, NCSC/CISA | O91: 長期 | P91: 1 | Q91: セキュリティ部門/AI開発/IT基盤 | R91: 設計書、設定記録、評価レポート、教育記録 | S91: 機密コンピューティングによる推論保護により、AI固有の攻撃・誤動作を未然に防ぐ実装統制が整います。 | T91: 設定画面・テスト結果・パイプライン定義 | U91: AIMF-PR-DAT-005 | V91: extended
A92: AIMF-PR-MDL-001 | B92: モデルライフサイクル管理・リリース前評価 | C92: PR | D92: MDL | E92: モデル・プロンプト・設定の変更管理、リリース前のセキュリティ／性能受入基準、承認ゲート、ロールバック手順を定義する。 | F92: モデルライフサイクル・成果物完全性に関するリスクを低減し、AIMF PR区分（MDLカテゴリ）の要求に対応する。 | G92: 4 | H92: 4 | I92: 9 | J92: 高 | K92: 1 | M92: AI-Expansion | N92: OWASP AISVS, ISO 42001, NCSC/CISA, EU AI Act, NIST AI RMF, 総務省AIセキュリティGL | O92: 長期 | P92: 1.2 | Q92: セキュリティ部門/AI開発/IT基盤 | R92: 設計書、設定記録、評価レポート、教育記録 | S92: モデルライフサイクル管理・リリース前評価により、AI固有の攻撃・誤動作を未然に防ぐ実装統制が整います。 | T92: 設定画面・テスト結果・パイプライン定義 | U92: AIMF-PR-MDL-001 | V92: baseline
A93: AIMF-PR-MDL-002 | B93: モデル成果物の完全性保護 | C93: PR | D93: MDL | E93: モデルファイルの署名・ハッシュ検証、安全でないデシリアライゼーション（pickle等）対策、モデルリポジトリからの取得時のTrojan/悪性レイヤースキャンを実装する。 | F93: モデルライフサイクル・成果物完全性に関するリスクを低減し、AIMF PR区分（MDLカテゴリ）の要求に対応する。 | G93: 4 | H93: 4 | I93: 9 | J93: 高 | K93: 1 | M93: AI-Expansion | N93: OWASP AISVS, NCSC/CISA, CSA AICM, 総務省AIセキュリティGL | O93: 長期 | P93: 1 | Q93: セキュリティ部門/AI開発/IT基盤 | R93: 設計書、設定記録、評価レポート、教育記録 | S93: モデル成果物の完全性保護により、AI固有の攻撃・誤動作を未然に防ぐ実装統制が整います。 | T93: 設定画面・テスト結果・パイプライン定義 | U93: AIMF-PR-MDL-002 | V93: baseline
A94: AIMF-PR-MDL-003 | B94: セキュア学習パイプラインの統制 | C94: PR | D94: MDL | E94: 学習ジョブの実行権限・データアクセス・成果物出力を統制し、パイプライン定義自体を版管理・レビュー対象とする。 | F94: モデルライフサイクル・成果物完全性に関するリスクを低減し、AIMF PR区分（MDLカテゴリ）の要求に対応する。 | G94: 4 | H94: 4 | I94: 9 | J94: 高 | K94: 1 | M94: AI-Expansion | N94: OWASP AISVS, NCSC/CISA, CIS v8.1 | O94: 長期 | P94: 1 | Q94: セキュリティ部門/AI開発/IT基盤 | R94: 設計書、設定記録、評価レポート、教育記録 | S94: セキュア学習パイプラインの統制により、AI固有の攻撃・誤動作を未然に防ぐ実装統制が整います。 | T94: 設定画面・テスト結果・パイプライン定義 | U94: AIMF-PR-MDL-003 | V94: extended
A95: AIMF-PR-MDL-004 | B95: モデルレジストリ統制（承認済みモデルのみデプロイ） | C95: PR | D95: MDL | E95: 本番デプロイをレジストリ登録済み・承認済み・署名検証済みのモデルに限定し、レジストリ外モデルの実行を技術的に遮断する。 | F95: モデルライフサイクル・成果物完全性に関するリスクを低減し、AIMF PR区分（MDLカテゴリ）の要求に対応する。 | G95: 4 | H95: 4 | I95: 9 | J95: 高 | K95: 1 | L95: AIMF-ID-SCM-003 | M95: AI-Expansion | N95: OWASP AISVS, NCSC/CISA | O95: 長期 | P95: 1 | Q95: セキュリティ部門/AI開発/IT基盤 | R95: 設計書、設定記録、評価レポート、教育記録 | S95: モデルレジストリ統制（承認済みモデルのみデプロイ）により、AI固有の攻撃・誤動作を未然に防ぐ実装統制が整います。 | T95: 設定画面・テスト結果・パイプライン定義 | U95: AIMF-PR-MDL-004 | V95: extended
A96: AIMF-PR-MDL-005 | B96: ファインチューニング・継続学習の変更管理 | C96: PR | D96: MDL | E96: ファインチューニング・RLHF・継続学習を変更管理の対象とし、実施前のデータ審査と実施後の安全性再評価を義務付ける。 | F96: モデルライフサイクル・成果物完全性に関するリスクを低減し、AIMF PR区分（MDLカテゴリ）の要求に対応する。 | G96: 4 | H96: 4 | I96: 9 | J96: 高 | K96: 1 | M96: AI-Expansion | N96: OWASP AISVS, EU AI Act, NIST AI RMF | O96: 長期 | P96: 1.2 | Q96: セキュリティ部門/AI開発/IT基盤 | R96: 設計書、設定記録、評価レポート、教育記録 | S96: ファインチューニング・継続学習の変更管理により、AI固有の攻撃・誤動作を未然に防ぐ実装統制が整います。 | T96: 設定画面・テスト結果・パイプライン定義 | U96: AIMF-PR-MDL-005 | V96: extended
A97: AIMF-PR-MDL-006 | B97: 量子化・蒸留・最適化後の安全性再評価 | C97: PR | D97: MDL | E97: 量子化・蒸留・プルーニング等の最適化後に、安全性・ガードレール有効性・堅牢性の劣化がないことを再評価する。 | F97: モデルライフサイクル・成果物完全性に関するリスクを低減し、AIMF PR区分（MDLカテゴリ）の要求に対応する。 | G97: 4 | H97: 4 | I97: 9 | J97: 高 | K97: 1 | M97: AI-Expansion | N97: OWASP AISVS, NIST AI RMF | O97: 長期 | P97: 1 | Q97: セキュリティ部門/AI開発/IT基盤 | R97: 設計書、設定記録、評価レポート、教育記録 | S97: 量子化・蒸留・最適化後の安全性再評価により、AI固有の攻撃・誤動作を未然に防ぐ実装統制が整います。 | T97: 設定画面・テスト結果・パイプライン定義 | U97: AIMF-PR-MDL-006 | V97: extended
A98: AIMF-PR-MDL-007 | B98: システムプロンプトの版管理と保護 | C98: PR | D98: MDL | E98: システムプロンプトを機密構成情報として版管理・アクセス制限し、機密情報や認可ロジックをプロンプト内に置かない設計を強制する。 | F98: モデルライフサイクル・成果物完全性に関するリスクを低減し、AIMF PR区分（MDLカテゴリ）の要求に対応する。 | G98: 4 | H98: 4 | I98: 9 | J98: 高 | K98: 1 | M98: AI-Expansion | N98: OWASP LLM10, OWASP AISVS, 総務省AIセキュリティGL | O98: 長期 | P98: 1 | Q98: セキュリティ部門/AI開発/IT基盤 | R98: 設計書、設定記録、評価レポート、教育記録 | S98: システムプロンプトの版管理と保護により、AI固有の攻撃・誤動作を未然に防ぐ実装統制が整います。 | T98: 設定画面・テスト結果・パイプライン定義 | U98: AIMF-PR-MDL-007 | V98: extended
A99: AIMF-PR-RED-001 | B99: AIレッドチーミングの定期的実施 | C99: PR | D99: RED | E99: 専門チームが擬似攻撃者として脱獄や間接的プロンプトインジェクションを試行し、稼働前システムの脆弱性を洗い出す。 | F99: プロアクティブなリスク評価・実戦演習に関するリスクを低減し、AIMF PR区分（REDカテゴリ）の要求に対応する。 | G99: 4 | H99: 4 | I99: 9 | J99: 高 | K99: 1 | M99: AI-Expansion | N99: NIST AI RMF, EU AI Act, OWASP AISVS, 総務省AIセキュリティGL, ISO 42001, CSA AICM, NCSC/CISA, AI事業者GL | O99: 長期 | P99: 1.2 | Q99: セキュリティ部門/AI開発/IT基盤 | R99: 設計書、設定記録、評価レポート、教育記録 | S99: AIレッドチーミングの定期的実施により、AI固有の攻撃・誤動作を未然に防ぐ実装統制が整います。 | T99: 設定画面・テスト結果・パイプライン定義 | U99: AIMF-PR-RED-001 | V99: baseline
A100: AIMF-PR-RED-002 | B100: 自動化されたAI脆弱性スキャン（LLM-assisted Red Teaming） | C100: PR | D100: RED | E100: 攻撃用にチューニングしたAIエージェントで攻撃プロンプトを高速自動投入し、脱獄パターンを継続的・網羅的に探索する。 | F100: プロアクティブなリスク評価・実戦演習に関するリスクを低減し、AIMF PR区分（REDカテゴリ）の要求に対応する。 | G100: 4 | H100: 4 | I100: 9 | J100: 高 | K100: 1 | M100: AI-Expansion | N100: OWASP AISVS, CSA AICM, 総務省AIセキュリティGL | O100: 長期 | P100: 1 | Q100: セキュリティ部門/AI開発/IT基盤 | R100: 設計書、設定記録、評価レポート、教育記録 | S100: 自動化されたAI脆弱性スキャン（LLM-assisted Red Teaming）により、AI固有の攻撃・誤動作を未然に防ぐ実装統制が整います。 | T100: 設定画面・テスト結果・パイプライン定義 | U100: AIMF-PR-RED-002 | V100: baseline
A101: AIMF-PR-RED-003 | B101: RAG知識ベースの動的スキャン | C101: PR | D101: RED | E101: 検索対象のファイルサーバー・DBを常時スキャンし、不正プロンプト（ポイズニングデータ）や誤格納された機密情報を自動検知・隔離する。 | F101: プロアクティブなリスク評価・実戦演習に関するリスクを低減し、AIMF PR区分（REDカテゴリ）の要求に対応する。 | G101: 4 | H101: 4 | I101: 9 | J101: 高 | K101: 1 | M101: AI-Expansion | N101: OWASP AISVS, 総務省AIセキュリティGL, CSA AICM | O101: 長期 | P101: 1 | Q101: セキュリティ部門/AI開発/IT基盤 | R101: 設計書、設定記録、評価レポート、教育記録 | S101: RAG知識ベースの動的スキャンにより、AI固有の攻撃・誤動作を未然に防ぐ実装統制が整います。 | T101: 設定画面・テスト結果・パイプライン定義 | U101: AIMF-PR-RED-003 | V101: baseline
A102: AIMF-PR-RED-004 | B102: リリース前の安全性・セキュリティ評価スイート | C102: PR | D102: RED | E102: リリース前にベンチマーク・有害性評価・セキュリティ評価からなる標準評価スイートを実行し、受入基準への適合を承認条件とする。 | F102: プロアクティブなリスク評価・実戦演習に関するリスクを低減し、AIMF PR区分（REDカテゴリ）の要求に対応する。 | G102: 4 | H102: 4 | I102: 9 | J102: 高 | K102: 1 | M102: AI-Expansion | N102: NIST AI RMF, EU AI Act, NCSC/CISA | O102: 長期 | P102: 1.2 | Q102: セキュリティ部門/AI開発/IT基盤 | R102: 設計書、設定記録、評価レポート、教育記録 | S102: リリース前の安全性・セキュリティ評価スイートにより、AI固有の攻撃・誤動作を未然に防ぐ実装統制が整います。 | T102: 設定画面・テスト結果・パイプライン定義 | U102: AIMF-PR-RED-004 | V102: extended
A103: AIMF-PR-RED-005 | B103: CI/CDへの継続的評価（eval）の組み込み | C103: PR | D103: RED | E103: モデル・プロンプト・ガードレールの変更ごとに自動評価をCI/CDで実行し、回帰（安全性低下）を検出してデプロイを停止する。 | F103: プロアクティブなリスク評価・実戦演習に関するリスクを低減し、AIMF PR区分（REDカテゴリ）の要求に対応する。 | G103: 4 | H103: 4 | I103: 9 | J103: 高 | K103: 1 | L103: AIMF-PR-RED-004 | M103: AI-Expansion | N103: OWASP AISVS, NIST AI RMF | O103: 長期 | P103: 1 | Q103: セキュリティ部門/AI開発/IT基盤 | R103: 設計書、設定記録、評価レポート、教育記録 | S103: CI/CDへの継続的評価（eval）の組み込みにより、AI固有の攻撃・誤動作を未然に防ぐ実装統制が整います。 | T103: 設定画面・テスト結果・パイプライン定義 | U103: AIMF-PR-RED-005 | V103: extended
A104: AIMF-PR-RED-006 | B104: ATLASベースの敵対的演習 | C104: PR | D104: RED | E104: ATLASのTTPに基づく攻撃シナリオでパープルチーミングを実施し、防御と検知の実効性を同時に検証する。 | F104: プロアクティブなリスク評価・実戦演習に関するリスクを低減し、AIMF PR区分（REDカテゴリ）の要求に対応する。 | G104: 4 | H104: 4 | I104: 9 | J104: 高 | K104: 1 | M104: AI-Expansion | N104: MITRE ATLAS, CIS v8.1, NCSC/CISA | O104: 長期 | P104: 1 | Q104: セキュリティ部門/AI開発/IT基盤 | R104: 設計書、設定記録、評価レポート、教育記録 | S104: ATLASベースの敵対的演習により、AI固有の攻撃・誤動作を未然に防ぐ実装統制が整います。 | T104: 設定画面・テスト結果・パイプライン定義 | U104: AIMF-PR-RED-006 | V104: extended
A105: AIMF-PR-GRD-001 | B105: 多層インライン・ガードレール（入出力フィルタ）の実装 | C105: PR | D105: GRD | E105: 入力側でプロンプトインジェクション・脱獄・有害入力を検知遮断し、出力側でPII・機密情報・極端なハルシネーションをリアルタイムにマスク・遮断する。 | F105: ガードレール・出力統制に関するリスクを低減し、AIMF PR区分（GRDカテゴリ）の要求に対応する。 | G105: 5 | H105: 4 | I105: 9 | J105: 高 | K105: 1 | L105: AIMF-ID-AST-001 | M105: AI-Expansion | N105: OWASP AISVS, 総務省AIセキュリティGL, EU AI Act, NIST AI RMF, CSA AICM, NCSC/CISA, AI事業者GL | O105: 長期 | P105: 1.2 | Q105: セキュリティ部門/AI開発/IT基盤 | R105: 設計書、設定記録、評価レポート、教育記録 | S105: 多層インライン・ガードレール（入出力フィルタ）の実装により、AI固有の攻撃・誤動作を未然に防ぐ実装統制が整います。 | T105: 設定画面・テスト結果・パイプライン定義 | U105: AIMF-PR-GRD-001 | V105: baseline
A106: AIMF-PR-GRD-002 | B106: AIエージェント実行環境の隔離（サンドボックス化） | C106: PR | D106: GRD | E106: エージェントのコード自動実行時に、ホストOS・社内ネットワークを保護する隔離コンテナ環境で実行させる。 | F106: ガードレール・出力統制に関するリスクを低減し、AIMF PR区分（GRDカテゴリ）の要求に対応する。 | G106: 5 | H106: 2 | I106: 3 | J106: 低 | K106: 1.5 | M106: AI-Enhancement | N106: OWASP AISVS, NCSC/CISA, CSA AICM | O106: 短期 | P106: 1 | Q106: セキュリティ部門/AI開発/IT基盤 | R106: 設計書、設定記録、評価レポート、教育記録 | S106: AIエージェント実行環境の隔離（サンドボックス化）により、AI固有の攻撃・誤動作を未然に防ぐ実装統制が整います。 | T106: 設定画面・テスト結果・パイプライン定義 | U106: AIMF-PR-GRD-002 | V106: baseline
A107: AIMF-PR-GRD-003 | B107: Human-in-the-Loopのシステム強制 | C107: PR | D107: GRD | E107: 外部送信・本番データ更新削除・高額決済の直前に人間のレビュー・承認ステップをシステム的に組み込む。 | F107: ガードレール・出力統制に関するリスクを低減し、AIMF PR区分（GRDカテゴリ）の要求に対応する。 | G107: 5 | H107: 4 | I107: 9 | J107: 高 | K107: 1 | M107: AI-Expansion | N107: OWASP AISVS, EU AI Act, NIST AI RMF, ISO 42001, AI事業者GL | O107: 長期 | P107: 1.2 | Q107: セキュリティ部門/AI開発/IT基盤 | R107: 設計書、設定記録、評価レポート、教育記録 | S107: Human-in-the-Loopのシステム強制により、AI固有の攻撃・誤動作を未然に防ぐ実装統制が整います。 | T107: 設定画面・テスト結果・パイプライン定義 | U107: AIMF-PR-GRD-003 | V107: baseline
A108: AIMF-PR-GRD-004 | B108: 出力の安全な取扱い（Improper Output Handling対策） | C108: PR | D108: GRD | E108: モデル出力を信頼できない入力として扱い、下流でのレンダリング・実行前にエンコーディング・サニタイズ・権限検証を強制する。 | F108: ガードレール・出力統制に関するリスクを低減し、AIMF PR区分（GRDカテゴリ）の要求に対応する。 | G108: 5 | H108: 4 | I108: 9 | J108: 高 | K108: 1 | M108: AI-Expansion | N108: OWASP LLM10, OWASP AISVS | O108: 長期 | P108: 1 | Q108: セキュリティ部門/AI開発/IT基盤 | R108: 設計書、設定記録、評価レポート、教育記録 | S108: 出力の安全な取扱い（Improper Output Handling対策）により、AI固有の攻撃・誤動作を未然に防ぐ実装統制が整います。 | T108: 設定画面・テスト結果・パイプライン定義 | U108: AIMF-PR-GRD-004 | V108: extended
A109: AIMF-PR-GRD-005 | B109: 構造化出力・スキーマ検証の強制 | C109: PR | D109: GRD | E109: ツール呼び出し・下流連携に用いる出力を構造化形式に限定し、スキーマ検証違反の出力を破棄・再試行する。 | F109: ガードレール・出力統制に関するリスクを低減し、AIMF PR区分（GRDカテゴリ）の要求に対応する。 | G109: 5 | H109: 4 | I109: 9 | J109: 高 | K109: 1 | M109: AI-Expansion | N109: OWASP AISVS, OWASP LLM10, 総務省AIセキュリティGL | O109: 長期 | P109: 1 | Q109: セキュリティ部門/AI開発/IT基盤 | R109: 設計書、設定記録、評価レポート、教育記録 | S109: 構造化出力・スキーマ検証の強制により、AI固有の攻撃・誤動作を未然に防ぐ実装統制が整います。 | T109: 設定画面・テスト結果・パイプライン定義 | U109: AIMF-PR-GRD-005 | V109: extended
A110: AIMF-PR-GRD-006 | B110: 過剰な自律性（Excessive Agency）の制限 | C110: PR | D110: GRD | E110: モデル・エージェントに付与する機能・権限・自律性を業務要件の最小限に設計し、破壊的操作は既定で無効化する。 | F110: ガードレール・出力統制に関するリスクを低減し、AIMF PR区分（GRDカテゴリ）の要求に対応する。 | G110: 5 | H110: 4 | I110: 9 | J110: 高 | K110: 1 | M110: AI-Expansion | N110: OWASP LLM10, ASDエージェントAI, OWASP AISVS | O110: 長期 | P110: 1 | Q110: セキュリティ部門/AI開発/IT基盤 | R110: 設計書、設定記録、評価レポート、教育記録 | S110: 過剰な自律性（Excessive Agency）の制限により、AI固有の攻撃・誤動作を未然に防ぐ実装統制が整います。 | T110: 設定画面・テスト結果・パイプライン定義 | U110: AIMF-PR-GRD-006 | V110: extended
A111: AIMF-PR-GRD-007 | B111: RAGコンテキストの検証と出典の強制 | C111: PR | D111: GRD | E111: RAG検索結果の信頼度・出典検証を行い、根拠のない生成を抑制するとともに出典表示を出力要件とする。 | F111: ガードレール・出力統制に関するリスクを低減し、AIMF PR区分（GRDカテゴリ）の要求に対応する。 | G111: 5 | H111: 4 | I111: 9 | J111: 高 | K111: 1 | M111: AI-Expansion | N111: OWASP LLM10, OWASP AISVS | O111: 長期 | P111: 1 | Q111: セキュリティ部門/AI開発/IT基盤 | R111: 設計書、設定記録、評価レポート、教育記録 | S111: RAGコンテキストの検証と出典の強制により、AI固有の攻撃・誤動作を未然に防ぐ実装統制が整います。 | T111: 設定画面・テスト結果・パイプライン定義 | U111: AIMF-PR-GRD-007 | V111: extended
A112: AIMF-PR-GRD-008 | B112: リソース消費上限の強制（Unbounded Consumption対策） | C112: PR | D112: GRD | E112: リクエスト・セッション・テナント単位のトークン/計算資源/コスト上限を強制し、経済的DoSと暴走消費を防ぐ。 | F112: ガードレール・出力統制に関するリスクを低減し、AIMF PR区分（GRDカテゴリ）の要求に対応する。 | G112: 5 | H112: 4 | I112: 9 | J112: 高 | K112: 1 | M112: AI-Expansion | N112: OWASP LLM10, 総務省AIセキュリティGL, OWASP AISVS | O112: 長期 | P112: 1 | Q112: セキュリティ部門/AI開発/IT基盤 | R112: 設計書、設定記録、評価レポート、教育記録 | S112: リソース消費上限の強制（Unbounded Consumption対策）により、AI固有の攻撃・誤動作を未然に防ぐ実装統制が整います。 | T112: 設定画面・テスト結果・パイプライン定義 | U112: AIMF-PR-GRD-008 | V112: extended
A113: AIMF-PR-AGT-001 | B113: エージェントID管理・相互認証 | C113: PR | D113: AGT | E113: 各エージェントに一意のアイデンティティを付与し、エージェント間（A2A）通信・ツール呼び出しにおける相互認証・認可を強制する。 | F113: エージェント・ツール接続セキュリティに関するリスクを低減し、AIMF PR区分（AGTカテゴリ）の要求に対応する。 | G113: 5 | H113: 4 | I113: 9 | J113: 高 | K113: 1 | M113: AI-Expansion | N113: OWASP AISVS, CSA AICM, NCSC/CISA | O113: 長期 | P113: 1 | Q113: セキュリティ部門/AI開発/IT基盤 | R113: 設計書、設定記録、評価レポート、教育記録 | S113: エージェントID管理・相互認証により、AI固有の攻撃・誤動作を未然に防ぐ実装統制が整います。 | T113: 設定画面・テスト結果・パイプライン定義 | U113: AIMF-PR-AGT-001 | V113: baseline
A114: AIMF-PR-AGT-002 | B114: MCP等ツール接続プロトコルのセキュリティ | C114: PR | D114: AGT | E114: MCPサーバー等の外部ツール接続について、ツール定義の検証（ツールポイズニング対策）、認可スコープによるツール発見のフィルタリング、呼び出しごとのサーバーサイド認可、認証付き暗号化トランスポートを義務付ける。 | F114: エージェント・ツール接続セキュリティに関するリスクを低減し、AIMF PR区分（AGTカテゴリ）の要求に対応する。 | G114: 5 | H114: 4 | I114: 9 | J114: 高 | K114: 1 | M114: AI-Expansion | N114: OWASP AISVS, 総務省AIセキュリティGL, NCSC/CISA | O114: 長期 | P114: 1 | Q114: セキュリティ部門/AI開発/IT基盤 | R114: 設計書、設定記録、評価レポート、教育記録 | S114: MCP等ツール接続プロトコルのセキュリティにより、AI固有の攻撃・誤動作を未然に防ぐ実装統制が整います。 | T114: 設定画面・テスト結果・パイプライン定義 | U114: AIMF-PR-AGT-002 | V114: baseline
A115: AIMF-PR-AGT-003 | B115: エージェントメモリ（長期記憶）の保護と汚染対策 | C115: PR | D115: AGT | E115: エージェントのセッションメモリ・長期記憶ストアへの書き込み検証、記憶経由の間接的インジェクション対策、記憶の定期的な検疫・失効を実装する。 | F115: エージェント・ツール接続セキュリティに関するリスクを低減し、AIMF PR区分（AGTカテゴリ）の要求に対応する。 | G115: 5 | H115: 4 | I115: 9 | J115: 高 | K115: 1 | M115: AI-Expansion | N115: OWASP AISVS | O115: 長期 | P115: 1 | Q115: セキュリティ部門/AI開発/IT基盤 | R115: 設計書、設定記録、評価レポート、教育記録 | S115: エージェントメモリ（長期記憶）の保護と汚染対策により、AI固有の攻撃・誤動作を未然に防ぐ実装統制が整います。 | T115: 設定画面・テスト結果・パイプライン定義 | U115: AIMF-PR-AGT-003 | V115: baseline
A116: AIMF-PR-AGT-004 | B116: 最小エージェンシー原則（行動範囲・目標境界の定義） | C116: PR | D116: AGT | E116: エージェントごとに許可される目標・行動範囲・禁止行為を明文化し、範囲外の行動をポリシーエンジンで技術的に拒否する。 | F116: エージェント・ツール接続セキュリティに関するリスクを低減し、AIMF PR区分（AGTカテゴリ）の要求に対応する。 | G116: 5 | H116: 4 | I116: 9 | J116: 高 | K116: 1 | M116: AI-Expansion | N116: ASDエージェントAI, OWASP ASI10, OWASP AISVS | O116: 長期 | P116: 1 | Q116: セキュリティ部門/AI開発/IT基盤 | R116: 設計書、設定記録、評価レポート、教育記録 | S116: 最小エージェンシー原則（行動範囲・目標境界の定義）により、AI固有の攻撃・誤動作を未然に防ぐ実装統制が整います。 | T116: 設定画面・テスト結果・パイプライン定義 | U116: AIMF-PR-AGT-004 | V116: extended
A117: AIMF-PR-AGT-005 | B117: ツールACLマトリクスによる呼出可否管理 | C117: PR | D117: AGT | E117: エージェント×ツール×操作のACLマトリクスを定義し、許可されない組合せのツール呼出をオーケストレーション層で遮断する。 | F117: エージェント・ツール接続セキュリティに関するリスクを低減し、AIMF PR区分（AGTカテゴリ）の要求に対応する。 | G117: 5 | H117: 4 | I117: 9 | J117: 高 | K117: 1 | L117: AIMF-ID-SCM-005 | M117: AI-Expansion | N117: OWASP ASI10, OWASP AISVS | O117: 長期 | P117: 1 | Q117: セキュリティ部門/AI開発/IT基盤 | R117: 設計書、設定記録、評価レポート、教育記録 | S117: ツールACLマトリクスによる呼出可否管理により、AI固有の攻撃・誤動作を未然に防ぐ実装統制が整います。 | T117: 設定画面・テスト結果・パイプライン定義 | U117: AIMF-PR-AGT-005 | V117: extended
A118: AIMF-PR-AGT-006 | B118: タスク計画の事前検証と逸脱制御 | C118: PR | D118: AGT | E118: エージェントの実行計画（プラン）を実行前にポリシー検証し、承認済み計画からの逸脱時は停止・再承認を要求する。 | F118: エージェント・ツール接続セキュリティに関するリスクを低減し、AIMF PR区分（AGTカテゴリ）の要求に対応する。 | G118: 5 | H118: 4 | I118: 9 | J118: 高 | K118: 1 | M118: AI-Expansion | N118: OWASP ASI10, ASDエージェントAI | O118: 長期 | P118: 1 | Q118: セキュリティ部門/AI開発/IT基盤 | R118: 設計書、設定記録、評価レポート、教育記録 | S118: タスク計画の事前検証と逸脱制御により、AI固有の攻撃・誤動作を未然に防ぐ実装統制が整います。 | T118: 設定画面・テスト結果・パイプライン定義 | U118: AIMF-PR-AGT-006 | V118: extended
A119: AIMF-PR-AGT-007 | B119: エージェント生成コードの実行統制 | C119: PR | D119: AGT | E119: エージェントが生成・変更するコードの実行を制限付きランタイムに限定し、危険API・ネットワーク到達性・永続化を既定で禁止する。 | F119: エージェント・ツール接続セキュリティに関するリスクを低減し、AIMF PR区分（AGTカテゴリ）の要求に対応する。 | G119: 5 | H119: 4 | I119: 9 | J119: 高 | K119: 1 | M119: AI-Expansion | N119: OWASP ASI10, OWASP AISVS | O119: 長期 | P119: 1 | Q119: セキュリティ部門/AI開発/IT基盤 | R119: 設計書、設定記録、評価レポート、教育記録 | S119: エージェント生成コードの実行統制により、AI固有の攻撃・誤動作を未然に防ぐ実装統制が整います。 | T119: 設定画面・テスト結果・パイプライン定義 | U119: AIMF-PR-AGT-007 | V119: extended
A120: AIMF-PR-AGT-008 | B120: 委任チェーン・エージェント間信頼境界の設計 | C120: PR | D120: AGT | E120: エージェント間の委任関係と信頼境界を明示的に設計し、委任の深さ・伝播可能な権限を制限して連鎖的な侵害を防ぐ。 | F120: エージェント・ツール接続セキュリティに関するリスクを低減し、AIMF PR区分（AGTカテゴリ）の要求に対応する。 | G120: 5 | H120: 4 | I120: 9 | J120: 高 | K120: 1 | M120: AI-Expansion | N120: OWASP ASI10, ASDエージェントAI | O120: 長期 | P120: 1 | Q120: セキュリティ部門/AI開発/IT基盤 | R120: 設計書、設定記録、評価レポート、教育記録 | S120: 委任チェーン・エージェント間信頼境界の設計により、AI固有の攻撃・誤動作を未然に防ぐ実装統制が整います。 | T120: 設定画面・テスト結果・パイプライン定義 | U120: AIMF-PR-AGT-008 | V120: extended
A121: AIMF-PR-AGT-009 | B121: エージェント設定のセキュアベースライン | C121: PR | D121: AGT | E121: エージェントフレームワーク・オーケストレーターのセキュア設定基準（デフォルト無効化・タイムアウト・再試行上限等）を定義し逸脱を検出する。 | F121: エージェント・ツール接続セキュリティに関するリスクを低減し、AIMF PR区分（AGTカテゴリ）の要求に対応する。 | G121: 5 | H121: 4 | I121: 9 | J121: 高 | K121: 1 | M121: AI-Expansion | N121: ASDエージェントAI, CIS v8.1 | O121: 長期 | P121: 1 | Q121: セキュリティ部門/AI開発/IT基盤 | R121: 設計書、設定記録、評価レポート、教育記録 | S121: エージェント設定のセキュアベースラインにより、AI固有の攻撃・誤動作を未然に防ぐ実装統制が整います。 | T121: 設定画面・テスト結果・パイプライン定義 | U121: AIMF-PR-AGT-009 | V121: extended
A122: AIMF-PR-AGT-010 | B122: オーケストレーターの単一障害点・乗っ取り対策 | C122: PR | D122: AGT | E122: オーケストレーターを重要資産として冗長化・アクセス制限し、単一エージェントの侵害が調停役の信頼を奪えない設計とする。 | F122: エージェント・ツール接続セキュリティに関するリスクを低減し、AIMF PR区分（AGTカテゴリ）の要求に対応する。 | G122: 5 | H122: 4 | I122: 9 | J122: 高 | K122: 1 | M122: AI-Expansion | N122: OWASP ASI10, ASDエージェントAI | O122: 長期 | P122: 1 | Q122: セキュリティ部門/AI開発/IT基盤 | R122: 設計書、設定記録、評価レポート、教育記録 | S122: オーケストレーターの単一障害点・乗っ取り対策により、AI固有の攻撃・誤動作を未然に防ぐ実装統制が整います。 | T122: 設定画面・テスト結果・パイプライン定義 | U122: AIMF-PR-AGT-010 | V122: extended
A123: AIMF-PR-HOV-001 | B123: 人間による監督（Human Oversight）の全体設計 | C123: PR | D123: HOV | E123: 高リスクAIシステム全般について、監督者の力量要件、自動化バイアスへの注意、出力の解釈・無効化・介入手段を含む監督設計を行う（エージェントHITLに限定しない）。 | F123: 人間による監督に関するリスクを低減し、AIMF PR区分（HOVカテゴリ）の要求に対応する。 | G123: 4 | H123: 4 | I123: 9 | J123: 高 | K123: 1 | M123: AI-Expansion | N123: EU AI Act, OWASP AISVS, AI事業者GL, ISO 42001, NIST AI RMF | O123: 長期 | P123: 1.2 | Q123: セキュリティ部門/AI開発/IT基盤 | R123: 設計書、設定記録、評価レポート、教育記録 | S123: 人間による監督（Human Oversight）の全体設計により、AI固有の攻撃・誤動作を未然に防ぐ実装統制が整います。 | T123: 設定画面・テスト結果・パイプライン定義 | U123: AIMF-PR-HOV-001 | V123: baseline
A124: AIMF-PR-HOV-002 | B124: 監督者の力量要件と自動化バイアス対策 | C124: PR | D124: HOV | E124: AI監督担当者の力量要件・訓練を定め、自動化バイアス（AI出力の無批判な受容）への対策を監督手順に組み込む。 | F124: 人間による監督に関するリスクを低減し、AIMF PR区分（HOVカテゴリ）の要求に対応する。 | G124: 4 | H124: 4 | I124: 9 | J124: 高 | K124: 1 | M124: AI-Expansion | N124: EU AI Act, OWASP AISVS | O124: 長期 | P124: 1.2 | Q124: セキュリティ部門/AI開発/IT基盤 | R124: 設計書、設定記録、評価レポート、教育記録 | S124: 監督者の力量要件と自動化バイアス対策により、AI固有の攻撃・誤動作を未然に防ぐ実装統制が整います。 | T124: 設定画面・テスト結果・パイプライン定義 | U124: AIMF-PR-HOV-002 | V124: extended
A125: AIMF-PR-HOV-003 | B125: 人間・エージェント間の信頼悪用対策 | C125: PR | D125: HOV | E125: 承認疲れ・説得的出力による不安全な承認誘導を防ぐため、重要承認は帯域外・要約強制・冷却時間付きのUXとして設計する。 | F125: 人間による監督に関するリスクを低減し、AIMF PR区分（HOVカテゴリ）の要求に対応する。 | G125: 4 | H125: 4 | I125: 9 | J125: 高 | K125: 1 | M125: AI-Expansion | N125: OWASP ASI10, OWASP AISVS | O125: 長期 | P125: 1 | Q125: セキュリティ部門/AI開発/IT基盤 | R125: 設計書、設定記録、評価レポート、教育記録 | S125: 人間・エージェント間の信頼悪用対策により、AI固有の攻撃・誤動作を未然に防ぐ実装統制が整います。 | T125: 設定画面・テスト結果・パイプライン定義 | U125: AIMF-PR-HOV-003 | V125: extended
A126: AIMF-PR-ADV-001 | B126: 従来型ML特有の敵対的攻撃対策 | C126: PR | D126: ADV | E126: 画像分類・異常検知等の従来型MLモデルに対する回避攻撃（Evasion）、モデル抽出、メンバーシップ推論、モデル反転への対策（敵対的学習、出力制限、クエリ監視）を実装する。 | F126: 敵対的堅牢性に関するリスクを低減し、AIMF PR区分（ADVカテゴリ）の要求に対応する。 | G126: 4 | H126: 4 | I126: 9 | J126: 高 | K126: 1 | M126: AI-Expansion | N126: OWASP AISVS, 総務省AIセキュリティGL, EU AI Act, NCSC/CISA, NIST AI RMF | O126: 長期 | P126: 1.2 | Q126: セキュリティ部門/AI開発/IT基盤 | R126: 設計書、設定記録、評価レポート、教育記録 | S126: 従来型ML特有の敵対的攻撃対策により、AI固有の攻撃・誤動作を未然に防ぐ実装統制が整います。 | T126: 設定画面・テスト結果・パイプライン定義 | U126: AIMF-PR-ADV-001 | V126: baseline
A127: AIMF-PR-ADV-002 | B127: モデル抽出・スティーリング対策 | C127: PR | D127: ADV | E127: 推論APIへのクエリ制限・出力情報量の制御・透かし（フィンガープリント）により、モデル複製・抽出攻撃を抑止する。 | F127: 敵対的堅牢性に関するリスクを低減し、AIMF PR区分（ADVカテゴリ）の要求に対応する。 | G127: 4 | H127: 4 | I127: 9 | J127: 高 | K127: 1 | M127: AI-Expansion | N127: MITRE ATLAS, OWASP AISVS, OWASP LLM10 | O127: 長期 | P127: 1 | Q127: セキュリティ部門/AI開発/IT基盤 | R127: 設計書、設定記録、評価レポート、教育記録 | S127: モデル抽出・スティーリング対策により、AI固有の攻撃・誤動作を未然に防ぐ実装統制が整います。 | T127: 設定画面・テスト結果・パイプライン定義 | U127: AIMF-PR-ADV-002 | V127: extended
A128: AIMF-PR-ADV-003 | B128: メンバーシップ推論・モデル反転対策 | C128: PR | D128: ADV | E128: 差分プライバシー・正則化・出力確信度の制御により、学習データの推定・復元攻撃への耐性を確保する。 | F128: 敵対的堅牢性に関するリスクを低減し、AIMF PR区分（ADVカテゴリ）の要求に対応する。 | G128: 4 | H128: 4 | I128: 9 | J128: 高 | K128: 1 | M128: AI-Expansion | N128: OWASP AISVS, EU AI Act, ISO 42001 | O128: 長期 | P128: 1.2 | Q128: セキュリティ部門/AI開発/IT基盤 | R128: 設計書、設定記録、評価レポート、教育記録 | S128: メンバーシップ推論・モデル反転対策により、AI固有の攻撃・誤動作を未然に防ぐ実装統制が整います。 | T128: 設定画面・テスト結果・パイプライン定義 | U128: AIMF-PR-ADV-003 | V128: extended
A129: AIMF-PR-ADV-004 | B129: 回避攻撃（敵対的サンプル）対策 | C129: PR | D129: ADV | E129: 敵対的学習・入力前処理・アンサンブルにより、判別モデルへの回避攻撃耐性を確保し、耐性を定期評価する。 | F129: 敵対的堅牢性に関するリスクを低減し、AIMF PR区分（ADVカテゴリ）の要求に対応する。 | G129: 4 | H129: 4 | I129: 9 | J129: 高 | K129: 1 | M129: AI-Expansion | N129: MITRE ATLAS, OWASP AISVS, 総務省AIセキュリティGL | O129: 長期 | P129: 1 | Q129: セキュリティ部門/AI開発/IT基盤 | R129: 設計書、設定記録、評価レポート、教育記録 | S129: 回避攻撃（敵対的サンプル）対策により、AI固有の攻撃・誤動作を未然に防ぐ実装統制が整います。 | T129: 設定画面・テスト結果・パイプライン定義 | U129: AIMF-PR-ADV-004 | V129: extended
... A140: AIMF-PR-EDU-004 | B140: 経営層向けAIサイバーリスクブリーフィング | C140: PR | D140: EDU | E140: 取締役・経営層に対しAIサイバーリスクの定期ブリーフィングを行い、投資判断・リスク受容の質を高める。 | F140: 層別AIセキュリティ教育に関するリスクを低減し、AIMF PR区分（EDUカテゴリ）の要求に対応する。 | G140: 4 | H140: 2 | I140: 3 | J140: 低 | K140: 1.5 | M140: AI-Enhancement | N140: Five Eyes声明, SANS AIMM, AI事業者GL | O140: 短期 | P140: 1 | Q140: セキュリティ部門/AI開発/IT基盤 | R140: 設計書、設定記録、評価レポート、教育記録 | S140: 経営層向けAIサイバーリスクブリーフィングにより、AI固有の攻撃・誤動作を未然に防ぐ実装統制が整います。 | T140: 設定画面・テスト結果・パイプライン定義 | U140: AIMF-PR-EDU-004 | V140: extended
A141: AIMF-DE-VUL-001 | B141: SBOM/AI-BOMの継続的脆弱性スキャン | C141: DE | D141: VUL | E141: 新たな脆弱性情報（NVD/CVE）の公開時にSBOM/AI-BOMとリアルタイムまたは日次で自動マッチングし、脆弱コンポーネントを即座に特定する。 | F141: サプライチェーン脆弱性の継続的・動的検知に関するリスクを低減し、AIMF DE区分（VULカテゴリ）の要求に対応する。 | G141: 4 | H141: 3 | I141: 6 | J141: 中 | K141: 1.5 | L141: AIMF-ID-SCM-002 | M141: AI-Enhancement | N141: OWASP AISVS, CSA AICM, NCSC/CISA, 総務省AIセキュリティGL | O141: 中期 | P141: 1 | Q141: SOC/セキュリティ運用 | R141: 検知ルール定義、監視ダッシュボード、ログ保管記録 | S141: SBOM/AI-BOMの継続的脆弱性スキャンにより、AI環境の異常を早期に発見し被害を最小化できます。 | T141: 検知ルール・アラート履歴・ログ | U141: AIMF-DE-VUL-001 | V141: baseline
A142: AIMF-DE-VUL-002 | B142: 悪性パッケージ・依存関係侵害の検知 | C142: DE | D142: VUL | E142: タイポスクワッティング・侵害されたAIライブラリ・悪性モデルローダーを、取得時スキャンと挙動監視の両面で検知する。 | F142: サプライチェーン脆弱性の継続的・動的検知に関するリスクを低減し、AIMF DE区分（VULカテゴリ）の要求に対応する。 | G142: 4 | H142: 3 | I142: 6 | J142: 中 | K142: 1.5 | M142: AI-Enhancement | N142: OWASP AISVS, MITRE ATLAS, CIS v8.1 | O142: 中期 | P142: 1 | Q142: SOC/セキュリティ運用 | R142: 検知ルール定義、監視ダッシュボード、ログ保管記録 | S142: 悪性パッケージ・依存関係侵害の検知により、AI環境の異常を早期に発見し被害を最小化できます。 | T142: 検知ルール・アラート履歴・ログ | U142: AIMF-DE-VUL-002 | V142: extended
A143: AIMF-DE-VUL-003 | B143: モデルレジストリ・リポジトリの改ざん検知 | C143: DE | D143: VUL | E143: レジストリ内モデルのハッシュ・署名を継続検証し、未承認の差替え・改ざんを即時検知する。 | F143: サプライチェーン脆弱性の継続的・動的検知に関するリスクを低減し、AIMF DE区分（VULカテゴリ）の要求に対応する。 | G143: 4 | H143: 4 | I143: 9 | J143: 高 | K143: 1 | M143: AI-Expansion | N143: OWASP AISVS, NCSC/CISA | O143: 長期 | P143: 1 | Q143: SOC/セキュリティ運用 | R143: 検知ルール定義、監視ダッシュボード、ログ保管記録 | S143: モデルレジストリ・リポジトリの改ざん検知により、AI環境の異常を早期に発見し被害を最小化できます。 | T143: 検知ルール・アラート履歴・ログ | U143: AIMF-DE-VUL-003 | V143: extended
A144: AIMF-DE-IOM-001 | B144: セマンティック・アノマリー検知 | C144: DE | D144: IOM | E144: 不自然な質問の繰り返しやシステムプロンプト構造を探るプローブ行為など、意味的異常を検知する。 | F144: 意味論・入出力監視に関するリスクを低減し、AIMF DE区分（IOMカテゴリ）の要求に対応する。 | G144: 5 | H144: 4 | I144: 9 | J144: 高 | K144: 1 | M144: AI-Expansion | N144: OWASP AISVS, 総務省AIセキュリティGL, CSA AICM, NIST AI RMF, NCSC/CISA | O144: 長期 | P144: 1 | Q144: SOC/セキュリティ運用 | R144: 検知ルール定義、監視ダッシュボード、ログ保管記録 | S144: セマンティック・アノマリー検知により、AI環境の異常を早期に発見し被害を最小化できます。 | T144: 検知ルール・アラート履歴・ログ | U144: AIMF-DE-IOM-001 | V144: baseline
A145: AIMF-DE-IOM-002 | B145: LLM監査ログ（プロンプト・レスポンス）の一元記録 | C145: DE | D145: IOM | E145: 誰が・いつ・どのプロンプトを入力し・AIがどう応答したかを改ざん不可能な形でフルログ記録する。 | F145: 意味論・入出力監視に関するリスクを低減し、AIMF DE区分（IOMカテゴリ）の要求に対応する。 | G145: 5 | H145: 4 | I145: 9 | J145: 高 | K145: 1 | M145: AI-Expansion | N145: OWASP AISVS, EU AI Act, ISO 42001, CSA AICM, 総務省AIセキュリティGL, NCSC/CISA | O145: 長期 | P145: 1.2 | Q145: SOC/セキュリティ運用 | R145: 検知ルール定義、監視ダッシュボード、ログ保管記録 | S145: LLM監査ログ（プロンプト・レスポンス）の一元記録により、AI環境の異常を早期に発見し被害を最小化できます。 | T145: 検知ルール・アラート履歴・ログ | U145: AIMF-DE-IOM-002 | V145: baseline
A146: AIMF-DE-IOM-003 | B146: ハルシネーション・信頼度の動的監視 | C146: DE | D146: IOM | E146: 回答の信頼度スコアやRAG参照ソースとの整合性をスコアリングし、一定基準超の出力を自動検知・ブロックする。 | F146: 意味論・入出力監視に関するリスクを低減し、AIMF DE区分（IOMカテゴリ）の要求に対応する。 | G146: 5 | H146: 4 | I146: 9 | J146: 高 | K146: 1 | M146: AI-Expansion | N146: OWASP AISVS, NIST AI RMF, EU AI Act, AI事業者GL | O146: 長期 | P146: 1.2 | Q146: SOC/セキュリティ運用 | R146: 検知ルール定義、監視ダッシュボード、ログ保管記録 | S146: ハルシネーション・信頼度の動的監視により、AI環境の異常を早期に発見し被害を最小化できます。 | T146: 検知ルール・アラート履歴・ログ | U146: AIMF-DE-IOM-003 | V146: baseline
A147: AIMF-DE-IOM-004 | B147: プロンプトインジェクション検知ルールの管理 | C147: DE | D147: IOM | E147: 直接・間接プロンプトインジェクションの検知シグネチャ・分類器を管理し、新手法の公開に追随して更新する。 | F147: 意味論・入出力監視に関するリスクを低減し、AIMF DE区分（IOMカテゴリ）の要求に対応する。 | G147: 5 | H147: 4 | I147: 9 | J147: 高 | K147: 1 | M147: AI-Expansion | N147: MITRE ATLAS, 総務省AIセキュリティGL, OWASP LLM10 | O147: 長期 | P147: 1 | Q147: SOC/セキュリティ運用 | R147: 検知ルール定義、監視ダッシュボード、ログ保管記録 | S147: プロンプトインジェクション検知ルールの管理により、AI環境の異常を早期に発見し被害を最小化できます。 | T147: 検知ルール・アラート履歴・ログ | U147: AIMF-DE-IOM-004 | V147: extended
A148: AIMF-DE-IOM-005 | B148: 脱獄・ポリシー回避試行のスコアリング検知 | C148: DE | D148: IOM | E148: 脱獄・安全策回避の試行をセッション横断でスコアリングし、閾値超過ユーザー・APIキーを段階的に制限する。 | F148: 意味論・入出力監視に関するリスクを低減し、AIMF DE区分（IOMカテゴリ）の要求に対応する。 | G148: 5 | H148: 4 | I148: 9 | J148: 高 | K148: 1 | M148: AI-Expansion | N148: OWASP LLM10, OWASP AISVS | O148: 長期 | P148: 1 | Q148: SOC/セキュリティ運用 | R148: 検知ルール定義、監視ダッシュボード、ログ保管記録 | S148: 脱獄・ポリシー回避試行のスコアリング検知により、AI環境の異常を早期に発見し被害を最小化できます。 | T148: 検知ルール・アラート履歴・ログ | U148: AIMF-DE-IOM-005 | V148: extended
A149: AIMF-DE-IOM-006 | B149: 出力へのPII・機微情報混入検知 | C149: DE | D149: IOM | E149: 出力ストリームをPII・秘密情報・認証情報の観点で走査し、機微情報漏えい（Sensitive Information Disclosure）を遮断・記録する。 | F149: 意味論・入出力監視に関するリスクを低減し、AIMF DE区分（IOMカテゴリ）の要求に対応する。 | G149: 5 | H149: 4 | I149: 9 | J149: 高 | K149: 1 | M149: AI-Expansion | N149: OWASP LLM10, OWASP AISVS | O149: 長期 | P149: 1 | Q149: SOC/セキュリティ運用 | R149: 検知ルール定義、監視ダッシュボード、ログ保管記録 | S149: 出力へのPII・機微情報混入検知により、AI環境の異常を早期に発見し被害を最小化できます。 | T149: 検知ルール・アラート履歴・ログ | U149: AIMF-DE-IOM-006 | V149: extended
A150: AIMF-DE-IOM-007 | B150: システムプロンプト漏えい・プローブの検知 | C150: DE | D150: IOM | E150: システムプロンプトの窃取を狙うプローブと、出力へのプロンプト断片の混入を検知し、漏えい時は当該プロンプトを失効・更新する。 | F150: 意味論・入出力監視に関するリスクを低減し、AIMF DE区分（IOMカテゴリ）の要求に対応する。 | G150: 5 | H150: 4 | I150: 9 | J150: 高 | K150: 1 | M150: AI-Expansion | N150: OWASP LLM10, OWASP AISVS | O150: 長期 | P150: 1 | Q150: SOC/セキュリティ運用 | R150: 検知ルール定義、監視ダッシュボード、ログ保管記録 | S150: システムプロンプト漏えい・プローブの検知により、AI環境の異常を早期に発見し被害を最小化できます。 | T150: 検知ルール・アラート履歴・ログ | U150: AIMF-DE-IOM-007 | V150: extended
A151: AIMF-DE-IOM-008 | B151: 利用者行動分析（UEBA）によるAI悪用検知 | C151: DE | D151: IOM | E151: 利用者・APIキー単位の利用パターンをベースライン化し、データ収集型の悪用・内部不正の兆候を検知する。 | F151: 意味論・入出力監視に関するリスクを低減し、AIMF DE区分（IOMカテゴリ）の要求に対応する。 | G151: 5 | H151: 2 | I151: 3 | J151: 低 | K151: 1.5 | M151: AI-Enhancement | N151: CIS v8.1, CSA AICM | O151: 短期 | P151: 1 | Q151: SOC/セキュリティ運用 | R151: 検知ルール定義、監視ダッシュボード、ログ保管記録 | S151: 利用者行動分析（UEBA）によるAI悪用検知により、AI環境の異常を早期に発見し被害を最小化できます。 | T151: 検知ルール・アラート履歴・ログ | U151: AIMF-DE-IOM-008 | V151: extended
A152: AIMF-DE-AGT-001 | B152: エージェント状態遷移・思考プロセスの可視化監視 | C152: DE | D152: AGT | E152: エージェントの推論・ツール選択・実行のサイクルをリアルタイム監視し、異常な意思決定ルートを検知する。 | F152: エージェント挙動・ツール実行の動的監視に関するリスクを低減し、AIMF DE区分（AGTカテゴリ）の要求に対応する。 | G152: 4 | H152: 4 | I152: 9 | J152: 高 | K152: 1 | M152: AI-Expansion | N152: OWASP AISVS, NIST AI RMF, NCSC/CISA | O152: 長期 | P152: 1 | Q152: SOC/セキュリティ運用 | R152: 検知ルール定義、監視ダッシュボード、ログ保管記録 | S152: エージェント状態遷移・思考プロセスの可視化監視により、AI環境の異常を早期に発見し被害を最小化できます。 | T152: 検知ルール・アラート履歴・ログ | U152: AIMF-DE-AGT-001 | V152: baseline
A153: AIMF-DE-AGT-002 | B153: エージェント間通信の相互セキュリティスキャン | C153: DE | D153: AGT | E153: エージェント同士の内部メッセージ通信を監視し、乗っ取られたエージェントによる不正命令の伝播をスキャンする。 | F153: エージェント挙動・ツール実行の動的監視に関するリスクを低減し、AIMF DE区分（AGTカテゴリ）の要求に対応する。 | G153: 4 | H153: 4 | I153: 9 | J153: 高 | K153: 1 | M153: AI-Expansion | N153: OWASP AISVS, CSA AICM | O153: 長期 | P153: 1 | Q153: SOC/セキュリティ運用 | R153: 検知ルール定義、監視ダッシュボード、ログ保管記録 | S153: エージェント間通信の相互セキュリティスキャンにより、AI環境の異常を早期に発見し被害を最小化できます。 | T153: 検知ルール・アラート履歴・ログ | U153: AIMF-DE-AGT-002 | V153: baseline
A154: AIMF-DE-AGT-003 | B154: ツール呼出の異常検知 | C154: DE | D154: AGT | E154: ツール呼出の頻度・順序・パラメータをベースライン化し、パラメータ汚染・想定外のツール連鎖・大量実行を検知する。 | F154: エージェント挙動・ツール実行の動的監視に関するリスクを低減し、AIMF DE区分（AGTカテゴリ）の要求に対応する。 | G154: 4 | H154: 4 | I154: 9 | J154: 高 | K154: 1 | M154: AI-Expansion | N154: OWASP ASI10, OWASP AISVS | O154: 長期 | P154: 1 | Q154: SOC/セキュリティ運用 | R154: 検知ルール定義、監視ダッシュボード、ログ保管記録 | S154: ツール呼出の異常検知により、AI環境の異常を早期に発見し被害を最小化できます。 | T154: 検知ルール・アラート履歴・ログ | U154: AIMF-DE-AGT-003 | V154: extended
A155: AIMF-DE-AGT-004 | B155: 目標逸脱（ゴールドリフト）の検知 | C155: DE | D155: AGT | E155: エージェントの行動系列を承認済み目標・計画と突合し、目標改変・逸脱の兆候をリアルタイムに検知する。 | F155: エージェント挙動・ツール実行の動的監視に関するリスクを低減し、AIMF DE区分（AGTカテゴリ）の要求に対応する。 | G155: 4 | H155: 4 | I155: 9 | J155: 高 | K155: 1 | L155: AIMF-PR-AGT-004 | M155: AI-Expansion | N155: OWASP ASI10, ASDエージェントAI | O155: 長期 | P155: 1 | Q155: SOC/セキュリティ運用 | R155: 検知ルール定義、監視ダッシュボード、ログ保管記録 | S155: 目標逸脱（ゴールドリフト）の検知により、AI環境の異常を早期に発見し被害を最小化できます。 | T155: 検知ルール・アラート履歴・ログ | U155: AIMF-DE-AGT-004 | V155: extended
A156: AIMF-DE-AGT-005 | B156: 暴走・連鎖障害の予兆検知 | C156: DE | D156: AGT | E156: 無限ループ・再帰的自己呼出・障害の連鎖伝播をリソース消費と呼出グラフから予兆検知し、自動ブレーキと連動させる。 | F156: エージェント挙動・ツール実行の動的監視に関するリスクを低減し、AIMF DE区分（AGTカテゴリ）の要求に対応する。 | G156: 4 | H156: 4 | I156: 9 | J156: 高 | K156: 1 | M156: AI-Expansion | N156: OWASP ASI10, 総務省AIセキュリティGL | O156: 長期 | P156: 1 | Q156: SOC/セキュリティ運用 | R156: 検知ルール定義、監視ダッシュボード、ログ保管記録 | S156: 暴走・連鎖障害の予兆検知により、AI環境の異常を早期に発見し被害を最小化できます。 | T156: 検知ルール・アラート履歴・ログ | U156: AIMF-DE-AGT-005 | V156: extended
A157: AIMF-DE-AGT-006 | B157: エージェントメモリ・コンテキスト改ざんの検知 | C157: DE | D157: AGT | E157: 長期記憶・セッションコンテキストへの書込みを検証・監査し、記憶経由の汚染・操作を検知して検疫する。 | F157: エージェント挙動・ツール実行の動的監視に関するリスクを低減し、AIMF DE区分（AGTカテゴリ）の要求に対応する。 | G157: 4 | H157: 4 | I157: 9 | J157: 高 | K157: 1 | M157: AI-Expansion | N157: OWASP ASI10, OWASP AISVS | O157: 長期 | P157: 1 | Q157: SOC/セキュリティ運用 | R157: 検知ルール定義、監視ダッシュボード、ログ保管記録 | S157: エージェントメモリ・コンテキスト改ざんの検知により、AI環境の異常を早期に発見し被害を最小化できます。 | T157: 検知ルール・アラート履歴・ログ | U157: AIMF-DE-AGT-006 | V157: extended
A158: AIMF-DE-AGT-007 | B158: ローグエージェント（逸脱挙動）の検知 | C158: DE | D158: AGT | E158: エージェントごとの正常挙動ベースラインからの持続的逸脱・ミスアライン挙動を検知し、隔離判断につなげる。 | F158: エージェント挙動・ツール実行の動的監視に関するリスクを低減し、AIMF DE区分（AGTカテゴリ）の要求に対応する。 | G158: 4 | H158: 4 | I158: 9 | J158: 高 | K158: 1 | M158: AI-Expansion | N158: OWASP ASI10, ASDエージェントAI | O158: 長期 | P158: 1 | Q158: SOC/セキュリティ運用 | R158: 検知ルール定義、監視ダッシュボード、ログ保管記録 | S158: ローグエージェント（逸脱挙動）の検知により、AI環境の異常を早期に発見し被害を最小化できます。 | T158: 検知ルール・アラート履歴・ログ | U158: AIMF-DE-AGT-007 | V158: extended
A159: AIMF-DE-HLT-001 | B159: AIインフラ構成監査とリソース監視（DoS検知） | C159: DE | D159: HLT | E159: LLM-DoSやエージェント無限ループを検知するためGPU・メモリ・トークン消費を常時監視し、コンテナ改ざん・K8s不審設定変更をRuntime Securityで監視する。 | F159: インフラ・データ・モデルの健全性監視に関するリスクを低減し、AIMF DE区分（HLTカテゴリ）の要求に対応する。 | G159: 4 | H159: 3 | I159: 6 | J159: 中 | K159: 1.5 | M159: AI-Enhancement | N159: 総務省AIセキュリティGL, OWASP AISVS, CSA AICM, EU AI Act, NCSC/CISA | O159: 中期 | P159: 1.2 | Q159: SOC/セキュリティ運用 | R159: 検知ルール定義、監視ダッシュボード、ログ保管記録 | S159: AIインフラ構成監査とリソース監視（DoS検知）により、AI環境の異常を早期に発見し被害を最小化できます。 | T159: 検知ルール・アラート履歴・ログ | U159: AIMF-DE-HLT-001 | V159: baseline
A160: AIMF-DE-HLT-002 | B160: データポイズニング・ドリフトの監視 | C160: DE | D160: HLT | E160: RAGデータストアの不正プロンプト・PIIを検知し、プロンプト傾向やデータ性質の経時変化（ドリフト）を監視して防御フィルターの機能不全を防ぐ。 | F160: インフラ・データ・モデルの健全性監視に関するリスクを低減し、AIMF DE区分（HLTカテゴリ）の要求に対応する。 | G160: 4 | H160: 4 | I160: 9 | J160: 高 | K160: 1 | M160: AI-Expansion | N160: OWASP AISVS, 総務省AIセキュリティGL, NIST AI RMF, NCSC/CISA, CSA AICM | O160: 長期 | P160: 1 | Q160: SOC/セキュリティ運用 | R160: 検知ルール定義、監視ダッシュボード、ログ保管記録 | S160: データポイズニング・ドリフトの監視により、AI環境の異常を早期に発見し被害を最小化できます。 | T160: 検知ルール・アラート履歴・ログ | U160: AIMF-DE-HLT-002 | V160: baseline
A161: AIMF-DE-HLT-003 | B161: モデル性能・品質劣化の継続監視 | C161: DE | D161: HLT | E161: 本番モデルの精度・品質指標を継続測定し、劣化の検知を市販後モニタリング計画・再学習判断に連動させる。 | F161: インフラ・データ・モデルの健全性監視に関するリスクを低減し、AIMF DE区分（HLTカテゴリ）の要求に対応する。 | G161: 4 | H161: 4 | I161: 9 | J161: 高 | K161: 1 | M161: AI-Expansion | N161: NIST AI RMF, EU AI Act, ISO 42001 | O161: 長期 | P161: 1.2 | Q161: SOC/セキュリティ運用 | R161: 検知ルール定義、監視ダッシュボード、ログ保管記録 | S161: モデル性能・品質劣化の継続監視により、AI環境の異常を早期に発見し被害を最小化できます。 | T161: 検知ルール・アラート履歴・ログ | U161: AIMF-DE-HLT-003 | V161: extended
A162: AIMF-DE-HLT-004 | B162: 埋め込み空間・ベクトルDBの異常検知 | C162: DE | D162: HLT | E162: 埋め込み分布の急変・異常クラスタ・不審な近傍構造を監視し、ベクトルDB汚染・埋め込み反転の兆候を検知する。 | F162: インフラ・データ・モデルの健全性監視に関するリスクを低減し、AIMF DE区分（HLTカテゴリ）の要求に対応する。 | G162: 4 | H162: 4 | I162: 9 | J162: 高 | K162: 1 | M162: AI-Expansion | N162: OWASP LLM10, OWASP AISVS | O162: 長期 | P162: 1 | Q162: SOC/セキュリティ運用 | R162: 検知ルール定義、監視ダッシュボード、ログ保管記録 | S162: 埋め込み空間・ベクトルDBの異常検知により、AI環境の異常を早期に発見し被害を最小化できます。 | T162: 検知ルール・アラート履歴・ログ | U162: AIMF-DE-HLT-004 | V162: extended
A163: AIMF-DE-HLT-005 | B163: GPUリソースの不正利用検知 | C163: DE | D163: HLT | E163: GPU使用率・ジョブ内容を監視し、クリプトマイニング・未承認の学習ジョブ等の不正利用を検知する。 | F163: インフラ・データ・モデルの健全性監視に関するリスクを低減し、AIMF DE区分（HLTカテゴリ）の要求に対応する。 | G163: 4 | H163: 3 | I163: 6 | J163: 中 | K163: 1.5 | M163: AI-Enhancement | N163: CIS v8.1, CSA AICM | O163: 中期 | P163: 1 | Q163: SOC/セキュリティ運用 | R163: 検知ルール定義、監視ダッシュボード、ログ保管記録 | S163: GPUリソースの不正利用検知により、AI環境の異常を早期に発見し被害を最小化できます。 | T163: 検知ルール・アラート履歴・ログ | U163: AIMF-DE-HLT-005 | V163: extended
A164: AIMF-DE-HLT-006 | B164: AI利用コスト・トークン消費の異常監視 | C164: DE | D164: HLT | E164: テナント・ユースケース単位のコスト/トークン消費を監視し、経済的DoS・暴走・悪用による異常増加を早期検知する。 | F164: インフラ・データ・モデルの健全性監視に関するリスクを低減し、AIMF DE区分（HLTカテゴリ）の要求に対応する。 | G164: 4 | H164: 4 | I164: 9 | J164: 高 | K164: 1 | M164: AI-Expansion | N164: OWASP LLM10, OWASP AISVS | O164: 長期 | P164: 1 | Q164: SOC/セキュリティ運用 | R164: 検知ルール定義、監視ダッシュボード、ログ保管記録 | S164: AI利用コスト・トークン消費の異常監視により、AI環境の異常を早期に発見し被害を最小化できます。 | T164: 検知ルール・アラート履歴・ログ | U164: AIMF-DE-HLT-006 | V164: extended
A165: AIMF-DE-SOC-001 | B165: AIテレメトリのSIEM統合と相関分析 | C165: DE | D165: SOC | E165: モデル・ガードレール・エージェント・インフラのテレメトリをSIEMへ統合し、既存セキュリティイベントと相関分析する。 | F165: SOC統合・検知運用に関するリスクを低減し、AIMF DE区分（SOCカテゴリ）の要求に対応する。 | G165: 4 | H165: 3 | I165: 6 | J165: 中 | K165: 1.5 | L165: AIMF-DE-LOG-001 | M165: AI-Enhancement | N165: CIS v8.1, CSA AICM | O165: 中期 | P165: 1 | Q165: SOC/セキュリティ運用 | R165: 検知ルール定義、監視ダッシュボード、ログ保管記録 | S165: AIテレメトリのSIEM統合と相関分析により、AI環境の異常を早期に発見し被害を最小化できます。 | T165: 検知ルール・アラート履歴・ログ | U165: AIMF-DE-SOC-001 | V165: extended
A166: AIMF-DE-SOC-002 | B166: ATLAS対応の検知ルールカバレッジ管理 | C166: DE | D166: SOC | E166: 検知ルールをATLASの技術（テクニック）にマッピングし、カバレッジの穴を可視化して優先的に解消する。 | F166: SOC統合・検知運用に関するリスクを低減し、AIMF DE区分（SOCカテゴリ）の要求に対応する。 | G166: 4 | H166: 4 | I166: 9 | J166: 高 | K166: 1 | L166: AIMF-ID-THR-001 | M166: AI-Expansion | N166: MITRE ATLAS, CIS v8.1 | O166: 長期 | P166: 1 | Q166: SOC/セキュリティ運用 | R166: 検知ルール定義、監視ダッシュボード、ログ保管記録 | S166: ATLAS対応の検知ルールカバレッジ管理により、AI環境の異常を早期に発見し被害を最小化できます。 | T166: 検知ルール・アラート履歴・ログ | U166: AIMF-DE-SOC-002 | V166: extended
A167: AIMF-DE-SOC-003 | B167: AIアラートのトリアージ基準 | C167: DE | D167: SOC | E167: AI固有アラート（インジェクション検知・逸脱検知等）の重大度判定・初動基準を定義し、SOC運用手順へ統合する。 | F167: SOC統合・検知運用に関するリスクを低減し、AIMF DE区分（SOCカテゴリ）の要求に対応する。 | G167: 4 | H167: 3 | I167: 6 | J167: 中 | K167: 1.5 | M167: AI-Enhancement | N167: CIS v8.1, NIST AI RMF | O167: 中期 | P167: 1 | Q167: SOC/セキュリティ運用 | R167: 検知ルール定義、監視ダッシュボード、ログ保管記録 | S167: AIアラートのトリアージ基準により、AI環境の異常を早期に発見し被害を最小化できます。 | T167: 検知ルール・アラート履歴・ログ | U167: AIMF-DE-SOC-003 | V167: extended
A168: AIMF-DE-SOC-004 | B168: AI環境の脅威ハンティング | C168: DE | D168: SOC | E168: ATLASのTTPと自組織の脅威シナリオに基づき、AI環境を対象とした仮説駆動の脅威ハンティングを定期実施する。 | F168: SOC統合・検知運用に関するリスクを低減し、AIMF DE区分（SOCカテゴリ）の要求に対応する。 | G168: 4 | H168: 3 | I168: 6 | J168: 中 | K168: 1.5 | L168: AIMF-DE-SOC-001 | M168: AI-Enhancement | N168: MITRE ATLAS, CIS v8.1 | O168: 中期 | P168: 1 | Q168: SOC/セキュリティ運用 | R168: 検知ルール定義、監視ダッシュボード、ログ保管記録 | S168: AI環境の脅威ハンティングにより、AI環境の異常を早期に発見し被害を最小化できます。 | T168: 検知ルール・アラート履歴・ログ | U168: AIMF-DE-SOC-004 | V168: extended
A169: AIMF-DE-SOC-005 | B169: 検知有効性の定期テスト | C169: DE | D169: SOC | E169: レッドチーム演習・攻撃シミュレーションと連動して検知ルールの発報有効性を検証し、検知漏れを改善サイクルに乗せる。 | F169: SOC統合・検知運用に関するリスクを低減し、AIMF DE区分（SOCカテゴリ）の要求に対応する。 | G169: 4 | H169: 3 | I169: 6 | J169: 中 | K169: 1.5 | M169: AI-Enhancement | N169: CIS v8.1, MITRE ATLAS | O169: 中期 | P169: 1 | Q169: SOC/セキュリティ運用 | R169: 検知ルール定義、監視ダッシュボード、ログ保管記録 | S169: 検知有効性の定期テストにより、AI環境の異常を早期に発見し被害を最小化できます。 | T169: 検知ルール・アラート履歴・ログ | U169: AIMF-DE-SOC-005 | V169: extended
A170: AIMF-DE-LOG-001 | B170: AIコンポーネント横断のログ標準化 | C170: DE | D170: LOG | E170: モデル・オーケストレーター・ツール・ガードレールのログ形式と相関IDを標準化し、一連の処理を横断追跡可能にする。 | F170: ログ・証跡基盤に関するリスクを低減し、AIMF DE区分（LOGカテゴリ）の要求に対応する。 | G170: 4 | H170: 3 | I170: 6 | J170: 中 | K170: 1.5 | M170: AI-Enhancement | N170: CIS v8.1, OWASP AISVS | O170: 中期 | P170: 1 | Q170: SOC/セキュリティ運用 | R170: 検知ルール定義、監視ダッシュボード、ログ保管記録 | S170: AIコンポーネント横断のログ標準化により、AI環境の異常を早期に発見し被害を最小化できます。 | T170: 検知ルール・アラート履歴・ログ | U170: AIMF-DE-LOG-001 | V170: extended
A171: AIMF-DE-LOG-002 | B171: ログの完全性保護 | C171: DE | D171: LOG | E171: AI監査ログにWORM保管・署名・改ざん検知を適用し、説明責任・法的証拠としての証跡価値を確保する。 | F171: ログ・証跡基盤に関するリスクを低減し、AIMF DE区分（LOGカテゴリ）の要求に対応する。 | G171: 4 | H171: 3 | I171: 6 | J171: 中 | K171: 1.5 | M171: AI-Enhancement | N171: EU AI Act, CIS v8.1, OWASP AISVS | O171: 中期 | P171: 1.2 | Q171: SOC/セキュリティ運用 | R171: 検知ルール定義、監視ダッシュボード、ログ保管記録 | S171: ログの完全性保護により、AI環境の異常を早期に発見し被害を最小化できます。 | T171: 検知ルール・アラート履歴・ログ | U171: AIMF-DE-LOG-002 | V171: extended
A172: AIMF-DE-LOG-003 | B172: ログ保持とプライバシーの両立 | C172: DE | D172: LOG | E172: プロンプトログ等に含まれる個人情報の保持期間・アクセス制限・マスキング方針を定め、監査要件とプライバシーを両立する。 | F172: ログ・証跡基盤に関するリスクを低減し、AIMF DE区分（LOGカテゴリ）の要求に対応する。 | G172: 4 | H172: 3 | I172: 6 | J172: 中 | K172: 1.5 | M172: AI-Enhancement | N172: EU AI Act, AI事業者GL, CIS v8.1 | O172: 中期 | P172: 1.2 | Q172: SOC/セキュリティ運用 | R172: 検知ルール定義、監視ダッシュボード、ログ保管記録 | S172: ログ保持とプライバシーの両立により、AI環境の異常を早期に発見し被害を最小化できます。 | T172: 検知ルール・アラート履歴・ログ | U172: AIMF-DE-LOG-003 | V172: extended
A173: AIMF-RS-IRP-001 | B173: CSIRTのAI拡張とプレイブック整備 | C173: RS | D173: IRP | E173: AI特有のインシデントとサプライチェーン上の重大脆弱性をインシデント定義に追加し、対応手順書を整備する。 | F173: インシデントレスポンス体制の拡張と自動化に関するリスクを低減し、AIMF RS区分（IRPカテゴリ）の要求に対応する。 | G173: 4 | H173: 2 | I173: 3 | J173: 低 | K173: 1.5 | M173: AI-Enhancement | N173: NIST AI RMF, CSA AICM, ISO 42001, NCSC/CISA, 総務省AIセキュリティGL | O173: 短期 | P173: 1 | Q173: CSIRT/セキュリティ部門 | R173: プレイブック、訓練記録、対応記録、報告書控え | S173: CSIRTのAI拡張とプレイブック整備により、AIインシデントに迅速・確実に対応できる体制になります。 | T173: 対応チケット・訓練記録・報告書 | U173: AIMF-RS-IRP-001 | V173: baseline
A174: AIMF-RS-IRP-002 | B174: セキュリティ運用の自動化（SOAR） | C174: RS | D174: IRP | E174: AIによる超高速攻撃に対抗し、検知から一次対応（アカウントロック・通信遮断・コンテナ強制終了）を秒単位で自動実行する。 | F174: インシデントレスポンス体制の拡張と自動化に関するリスクを低減し、AIMF RS区分（IRPカテゴリ）の要求に対応する。 | G174: 4 | H174: 2 | I174: 3 | J174: 低 | K174: 1.5 | M174: AI-Enhancement | N174: CSA AICM, NCSC/CISA | O174: 短期 | P174: 1 | Q174: CSIRT/セキュリティ部門 | R174: プレイブック、訓練記録、対応記録、報告書控え | S174: セキュリティ運用の自動化（SOAR）により、AIインシデントに迅速・確実に対応できる体制になります。 | T174: 対応チケット・訓練記録・報告書 | U174: AIMF-RS-IRP-002 | V174: baseline
...

Sheet 03_質問施策マッピング
A1: 質問ID | B1: 候補施策ID | C1: 候補施策名 | D1: 区分 | E1: マッピング理由 | F1: 優先抽出条件
A2: AIMF-GV-ORG-001 | B2: AIMF-GV-ORG-001 | C2: AIガバナンス委員会の設置 | D2: GV | E2: 質問はコントロール実装状況を問うため、同一コントロールの実装施策と1:1で対応する。 | F2: 現状評価が目標評価未満、または優先度スコアが閾値以上（対象外を除く）
A3: AIMF-GV-ORG-002 | B3: AIMF-GV-ORG-002 | C3: AI活用基本方針・ガイドラインの策定 | D3: GV | E3: 質問はコントロール実装状況を問うため、同一コントロールの実装施策と1:1で対応する。 | F3: 現状評価が目標評価未満、または優先度スコアが閾値以上（対象外を除く）
A4: AIMF-GV-ORG-003 | B4: AIMF-GV-ORG-003 | C4: AIリスクアセスメント・プロジェクト承認プロセスの構築 | D4: GV | E4: 質問はコントロール実装状況を問うため、同一コントロールの実装施策と1:1で対応する。 | F4: 現状評価が目標評価未満、または優先度スコアが閾値以上（対象外を除く）
A5: AIMF-GV-ORG-004 | B5: AIMF-GV-ORG-004 | C5: AIセキュリティ文化の醸成 | D5: GV | E5: 質問はコントロール実装状況を問うため、同一コントロールの実装施策と1:1で対応する。 | F5: 現状評価が目標評価未満、または優先度スコアが閾値以上（対象外を除く）
A6: AIMF-GV-ORG-005 | B6: AIMF-GV-ORG-005 | C6: AIセキュリティの社内コミュニケーション強化 | D6: GV | E6: 質問はコントロール実装状況を問うため、同一コントロールの実装施策と1:1で対応する。 | F6: 現状評価が目標評価未満、または優先度スコアが閾値以上（対象外を除く）
A7: AIMF-GV-ORG-006 | B7: AIMF-GV-ORG-006 | C7: AI統括責任者（CAIO/AIセキュリティ責任者）の任命 | D7: GV | E7: 質問はコントロール実装状況を問うため、同一コントロールの実装施策と1:1で対応する。 | F7: 現状評価が目標評価未満、または優先度スコアが閾値以上（対象外を除く）
A8: AIMF-GV-ORG-007 | B8: AIMF-GV-ORG-007 | C8: AIセキュリティ予算・リソースの確保 | D8: GV | E8: 質問はコントロール実装状況を問うため、同一コントロールの実装施策と1:1で対応する。 | F8: 現状評価が目標評価未満、または優先度スコアが閾値以上（対象外を除く）
A9: AIMF-GV-ORG-008 | B9: AIMF-GV-ORG-008 | C9: AIライフサイクル全体のRACI定義 | D9: GV | E9: 質問はコントロール実装状況を問うため、同一コントロールの実装施策と1:1で対応する。 | F9: 現状評価が目標評価未満、または優先度スコアが閾値以上（対象外を除く）
A10: AIMF-GV-ORG-009 | B10: AIMF-GV-ORG-009 | C10: AI倫理審査との連携プロセス | D10: GV | E10: 質問はコントロール実装状況を問うため、同一コントロールの実装施策と1:1で対応する。 | F10: 現状評価が目標評価未満、または優先度スコアが閾値以上（対象外を除く）
A11: AIMF-GV-POL-001 | B11: AIMF-GV-POL-001 | C11: AIポリシースイートの体系化 | D11: GV | E11: 質問はコントロール実装状況を問うため、同一コントロールの実装施策と1:1で対応する。 | F11: 現状評価が目標評価未満、または優先度スコアが閾値以上（対象外を除く）
A12: AIMF-GV-POL-002 | B12: AIMF-GV-POL-002 | C12: 生成AI利用細則（入力禁止情報・プロンプト取扱規程） | D12: GV | E12: 質問はコントロール実装状況を問うため、同一コントロールの実装施策と1:1で対応する。 | F12: 現状評価が目標評価未満、または優先度スコアが閾値以上（対象外を除く）
... A208: AIMF-RC-PMM-001 | B208: AIMF-RC-PMM-001 | C208: 市販後モニタリング計画（Post-market Monitoring） | D208: RC | E208: 質問はコントロール実装状況を問うため、同一コントロールの実装施策と1:1で対応する。 | F208: 現状評価が目標評価未満、または優先度スコアが閾値以上（対象外を除く）

Sheet 04_依存関係マスター
A1: 施策ID | B1: 施策名 | C1: 依存施策ID | D1: 依存施策名 | E1: 依存理由 | F1: 配置ルール
A2: AIMF-PR-IAM-001 | B2: RAGデータアクセス権（ACL）の同期 | C2: AIMF-ID-AST-002 | D2: RAG知識ベース・データソースの棚卸し | E2: 権限同期の範囲定義に棚卸しが必要 | F2: 棚卸し→ACL同期
A3: AIMF-DE-VUL-001 | B3: SBOM/AI-BOMの継続的脆弱性スキャン | C3: AIMF-ID-SCM-002 | D3: SBOMの自動生成・継続的管理 | E3: スキャン対象のSBOM整備が前提 | F3: SBOM生成→継続スキャン
A4: AIMF-PR-IAM-002 | B4: AIエージェントへの最小権限原則の適用 | C4: AIMF-ID-AST-003 | D4: AIエージェントの権限・ツールトポロジー管理 | E4: 権限の現状把握が最小化設計の前提 | F4: トポロジー把握→最小権限
A5: AIMF-PR-AGT-005 | B5: ツールACLマトリクスによる呼出可否管理 | C5: AIMF-ID-SCM-005 | D5: MCPサーバー・プラグイン・エージェントツールの事前審査 | E5: 承認済みツールリストがACLの前提 | F5: ツール審査→ACL
A6: AIMF-DE-SOC-001 | B6: AIテレメトリのSIEM統合と相関分析 | C6: AIMF-DE-LOG-001 | D6: AIコンポーネント横断のログ標準化 | E6: 相関分析にはログ形式の標準化が必要 | F6: ログ標準化→SIEM統合
A7: AIMF-DE-SOC-004 | B7: AI環境の脅威ハンティング | C7: AIMF-DE-SOC-001 | D7: AIテレメトリのSIEM統合と相関分析 | E7: ハンティングは統合テレメトリが前提 | F7: SIEM統合→ハンティング
A8: AIMF-DE-SOC-002 | B8: ATLAS対応の検知ルールカバレッジ管理 | C8: AIMF-ID-THR-001 | D8: MITRE ATLASに基づくAI脅威モデリング | E8: 対象TTPの特定が先行 | F8: 脅威モデリング→カバレッジ管理
A9: AIMF-PR-GRD-001 | B9: 多層インライン・ガードレール（入出力フィルタ）の実装 | C9: AIMF-ID-AST-001 | D9: AIモデル・サービス管理台帳の整備 | E9: 適用対象システムの可視化が前提 | F9: 台帳→ガードレール
A10: AIMF-DE-AGT-004 | B10: 目標逸脱（ゴールドリフト）の検知 | C10: AIMF-PR-AGT-004 | D10: 最小エージェンシー原則（行動範囲・目標境界の定義） | E10: 承認済み目標の定義が検知基準になる | F10: 目標定義→逸脱検知
A11: AIMF-RS-CON-001 | B11: AIエージェントのキルスイッチ実装 | C11: AIMF-DE-AGT-001 | D11: エージェント状態遷移・思考プロセスの可視化監視 | E11: 停止判断には状態監視が必要 | F11: 状態監視→キルスイッチ
A12: AIMF-PR-MDL-004 | B12: モデルレジストリ統制（承認済みモデルのみデプロイ） | C12: AIMF-ID-SCM-003 | D12: AI-BOMによるAI特有資産の管理 | E12: モデル資産の台帳化が前提 | F12: AI-BOM→レジストリ統制
... A16: AIMF-RS-RPT-001 | B16: インシデントの外部報告・ステークホルダー通知 | C16: AIMF-RS-IRP-004 | D16: AI固有インシデントの分類・重大度基準 | E16: 法定報告該当性の判断基準が前提 | F16: 分類基準→外部報告

Sheet 05_施策抽出
A1: 質問ID | B1: 抽出 | C1: 優先度スコア | D1: ギャップ | E1: 施策ID | F1: 施策名 | G1: 区分
A2: =01_評価入力!A2 -> AIMF-GV-ORG-001 | B2: =01_評価入力!S2 | C2: =01_評価入力!R2 | D2: =01_評価入力!K2 | E2: =01_評価入力!T2 -> AIMF-GV-ORG-001 | F2: =01_評価入力!U2 -> AIガバナンス委員会の設置 | G2: =IF($E2="","",IFERROR(VLOOKUP($E2,02_施策マスター!$A:$C,3,0),"")) -> GV
A3: =01_評価入力!A3 -> AIMF-GV-ORG-002 | B3: =01_評価入力!S3 | C3: =01_評価入力!R3 | D3: =01_評価入力!K3 | E3: =01_評価入力!T3 -> AIMF-GV-ORG-002 | F3: =01_評価入力!U3 -> AI活用基本方針・ガイドラインの策定 | G3: =IF($E3="","",IFERROR(VLOOKUP($E3,02_施策マスター!$A:$C,3,0),"")) -> GV
A4: =01_評価入力!A4 -> AIMF-GV-ORG-003 | B4: =01_評価入力!S4 | C4: =01_評価入力!R4 | D4: =01_評価入力!K4 | E4: =01_評価入力!T4 -> AIMF-GV-ORG-003 | F4: =01_評価入力!U4 -> AIリスクアセスメント・プロジェクト承認プロセスの構築 | G4: =IF($E4="","",IFERROR(VLOOKUP($E4,02_施策マスター!$A:$C,3,0),"")) -> GV
A5: =01_評価入力!A5 -> AIMF-GV-ORG-004 | B5: =01_評価入力!S5 | C5: =01_評価入力!R5 | D5: =01_評価入力!K5 | E5: =01_評価入力!T5 -> AIMF-GV-ORG-004 | F5: =01_評価入力!U5 -> AIセキュリティ文化の醸成 | G5: =IF($E5="","",IFERROR(VLOOKUP($E5,02_施策マスター!$A:$C,3,0),"")) -> GV
A6: =01_評価入力!A6 -> AIMF-GV-ORG-005 | B6: =01_評価入力!S6 | C6: =01_評価入力!R6 | D6: =01_評価入力!K6 | E6: =01_評価入力!T6 -> AIMF-GV-ORG-005 | F6: =01_評価入力!U6 -> AIセキュリティの社内コミュニケーション強化 | G6: =IF($E6="","",IFERROR(VLOOKUP($E6,02_施策マスター!$A:$C,3,0),"")) -> GV
A7: =01_評価入力!A7 -> AIMF-GV-ORG-006 | B7: =01_評価入力!S7 | C7: =01_評価入力!R7 | D7: =01_評価入力!K7 | E7: =01_評価入力!T7 -> AIMF-GV-ORG-006 | F7: =01_評価入力!U7 -> AI統括責任者（CAIO/AIセキュリティ責任者）の任命 | G7: =IF($E7="","",IFERROR(VLOOKUP($E7,02_施策マスター!$A:$C,3,0),"")) -> GV
A8: =01_評価入力!A8 -> AIMF-GV-ORG-007 | B8: =01_評価入力!S8 | C8: =01_評価入力!R8 | D8: =01_評価入力!K8 | E8: =01_評価入力!T8 -> AIMF-GV-ORG-007 | F8: =01_評価入力!U8 -> AIセキュリティ予算・リソースの確保 | G8: =IF($E8="","",IFERROR(VLOOKUP($E8,02_施策マスター!$A:$C,3,0),"")) -> GV
A9: =01_評価入力!A9 -> AIMF-GV-ORG-008 | B9: =01_評価入力!S9 | C9: =01_評価入力!R9 | D9: =01_評価入力!K9 | E9: =01_評価入力!T9 -> AIMF-GV-ORG-008 | F9: =01_評価入力!U9 -> AIライフサイクル全体のRACI定義 | G9: =IF($E9="","",IFERROR(VLOOKUP($E9,02_施策マスター!$A:$C,3,0),"")) -> GV
A10: =01_評価入力!A10 -> AIMF-GV-ORG-009 | B10: =01_評価入力!S10 | C10: =01_評価入力!R10 | D10: =01_評価入力!K10 | E10: =01_評価入力!T10 -> AIMF-GV-ORG-009 | F10: =01_評価入力!U10 -> AI倫理審査との連携プロセス | G10: =IF($E10="","",IFERROR(VLOOKUP($E10,02_施策マスター!$A:$C,3,0),"")) -> GV
A11: =01_評価入力!A11 -> AIMF-GV-POL-001 | B11: =01_評価入力!S11 | C11: =01_評価入力!R11 | D11: =01_評価入力!K11 | E11: =01_評価入力!T11 -> AIMF-GV-POL-001 | F11: =01_評価入力!U11 -> AIポリシースイートの体系化 | G11: =IF($E11="","",IFERROR(VLOOKUP($E11,02_施策マスター!$A:$C,3,0),"")) -> GV
A12: =01_評価入力!A12 -> AIMF-GV-POL-002 | B12: =01_評価入力!S12 | C12: =01_評価入力!R12 | D12: =01_評価入力!K12 | E12: =01_評価入力!T12 -> AIMF-GV-POL-002 | F12: =01_評価入力!U12 -> 生成AI利用細則（入力禁止情報・プロンプト取扱規程） | G12: =IF($E12="","",IFERROR(VLOOKUP($E12,02_施策マスター!$A:$C,3,0),"")) -> GV
A13: =01_評価入力!A13 -> AIMF-GV-POL-003 | B13: =01_評価入力!S13 | C13: =01_評価入力!R13 | D13: =01_評価入力!K13 | E13: =01_評価入力!T13 -> AIMF-GV-POL-003 | F13: =01_評価入力!U13 -> 承認済みAIサービスカタログと例外管理 | G13: =IF($E13="","",IFERROR(VLOOKUP($E13,02_施策マスター!$A:$C,3,0),"")) -> GV
... A208: =01_評価入力!A208 -> AIMF-RC-PMM-001 | B208: =01_評価入力!S208 | C208: =01_評価入力!R208 | D208: =01_評価入力!K208 | E208: =01_評価入力!T208 -> AIMF-RC-PMM-001 | F208: =01_評価入力!U208 -> 市販後モニタリング計画（Post-market Monitoring） | G208: =IF($E208="","",IFERROR(VLOOKUP($E208,02_施策マスター!$A:$C,3,0),"")) -> RC

Sheet 06_重複排除後
A1: 施策ID | B1: 施策名 | C1: 区分 | D1: ロードマップ区分 | E1: 標準期間(月) | F1: 導入難易度 | G1: 抽出回数 | H1: 採用 | I1: 推奨優先度 | J1: 調整優先度(内部) | K1: 区分内順位(内部) | L1: 順位キー(内部)
A2: =02_施策マスター!A2 -> AIMF-GV-ORG-001 | B2: =02_施策マスター!B2 -> AIガバナンス委員会の設置 | C2: =02_施策マスター!C2 -> GV | D2: =02_施策マスター!O2 -> 短期 | E2: =02_施策マスター!I2 -> 3 | F2: =02_施策マスター!H2 -> 2 | G2: =COUNTIFS(05_施策抽出!$E:$E,$A2,05_施策抽出!$B:$B,"○") -> 0 | H2: =IF($G2>0,"○","") | I2: =IF($H2="","",ROUND(SUMIFS(05_施策抽出!$C:$C,05_施策抽出!$E:$E,$A2,05_施策抽出!$B:$B,"○")*02_施策マスター!$P2*02_施策マスター!$K2,1)) | J2: =IF($I2="","",$I2+(1000-ROW())/1000000) | K2: =IF($H2="","",COUNTIFS($D$2:$D$208,$D2,$J$2:$J$208,">"&$J2)+1) | L2: =IF($K2="","",$D2&"-"&$K2)
A3: =02_施策マスター!A3 -> AIMF-GV-ORG-002 | B3: =02_施策マスター!B3 -> AI活用基本方針・ガイドラインの策定 | C3: =02_施策マスター!C3 -> GV | D3: =02_施策マスター!O3 -> 短期 | E3: =02_施策マスター!I3 -> 3 | F3: =02_施策マスター!H3 -> 2 | G3: =COUNTIFS(05_施策抽出!$E:$E,$A3,05_施策抽出!$B:$B,"○") -> 0 | H3: =IF($G3>0,"○","") | I3: =IF($H3="","",ROUND(SUMIFS(05_施策抽出!$C:$C,05_施策抽出!$E:$E,$A3,05_施策抽出!$B:$B,"○")*02_施策マスター!$P3*02_施策マスター!$K3,1)) | J3: =IF($I3="","",$I3+(1000-ROW())/1000000) | K3: =IF($H3="","",COUNTIFS($D$2:$D$208,$D3,$J$2:$J$208,">"&$J3)+1) | L3: =IF($K3="","",$D3&"-"&$K3)
A4: =02_施策マスター!A4 -> AIMF-GV-ORG-003 | B4: =02_施策マスター!B4 -> AIリスクアセスメント・プロジェクト承認プロセスの構築 | C4: =02_施策マスター!C4 -> GV | D4: =02_施策マスター!O4 -> 短期 | E4: =02_施策マスター!I4 -> 3 | F4: =02_施策マスター!H4 -> 2 | G4: =COUNTIFS(05_施策抽出!$E:$E,$A4,05_施策抽出!$B:$B,"○") -> 0 | H4: =IF($G4>0,"○","") | I4: =IF($H4="","",ROUND(SUMIFS(05_施策抽出!$C:$C,05_施策抽出!$E:$E,$A4,05_施策抽出!$B:$B,"○")*02_施策マスター!$P4*02_施策マスター!$K4,1)) | J4: =IF($I4="","",$I4+(1000-ROW())/1000000) | K4: =IF($H4="","",COUNTIFS($D$2:$D$208,$D4,$J$2:$J$208,">"&$J4)+1) | L4: =IF($K4="","",$D4&"-"&$K4)
A5: =02_施策マスター!A5 -> AIMF-GV-ORG-004 | B5: =02_施策マスター!B5 -> AIセキュリティ文化の醸成 | C5: =02_施策マスター!C5 -> GV | D5: =02_施策マスター!O5 -> 短期 | E5: =02_施策マスター!I5 -> 3 | F5: =02_施策マスター!H5 -> 2 | G5: =COUNTIFS(05_施策抽出!$E:$E,$A5,05_施策抽出!$B:$B,"○") -> 0 | H5: =IF($G5>0,"○","") | I5: =IF($H5="","",ROUND(SUMIFS(05_施策抽出!$C:$C,05_施策抽出!$E:$E,$A5,05_施策抽出!$B:$B,"○")*02_施策マスター!$P5*02_施策マスター!$K5,1)) | J5: =IF($I5="","",$I5+(1000-ROW())/1000000) | K5: =IF($H5="","",COUNTIFS($D$2:$D$208,$D5,$J$2:$J$208,">"&$J5)+1) | L5: =IF($K5="","",$D5&"-"&$K5)
A6: =02_施策マスター!A6 -> AIMF-GV-ORG-005 | B6: =02_施策マスター!B6 -> AIセキュリティの社内コミュニケーション強化 | C6: =02_施策マスター!C6 -> GV | D6: =02_施策マスター!O6 -> 短期 | E6: =02_施策マスター!I6 -> 3 | F6: =02_施策マスター!H6 -> 2 | G6: =COUNTIFS(05_施策抽出!$E:$E,$A6,05_施策抽出!$B:$B,"○") -> 0 | H6: =IF($G6>0,"○","") | I6: =IF($H6="","",ROUND(SUMIFS(05_施策抽出!$C:$C,05_施策抽出!$E:$E,$A6,05_施策抽出!$B:$B,"○")*02_施策マスター!$P6*02_施策マスター!$K6,1)) | J6: =IF($I6="","",$I6+(1000-ROW())/1000000) | K6: =IF($H6="","",COUNTIFS($D$2:$D$208,$D6,$J$2:$J$208,">"&$J6)+1) | L6: =IF($K6="","",$D6&"-"&$K6)
A7: =02_施策マスター!A7 -> AIMF-GV-ORG-006 | B7: =02_施策マスター!B7 -> AI統括責任者（CAIO/AIセキュリティ責任者）の任命 | C7: =02_施策マスター!C7 -> GV | D7: =02_施策マスター!O7 -> 短期 | E7: =02_施策マスター!I7 -> 3 | F7: =02_施策マスター!H7 -> 2 | G7: =COUNTIFS(05_施策抽出!$E:$E,$A7,05_施策抽出!$B:$B,"○") -> 0 | H7: =IF($G7>0,"○","") | I7: =IF($H7="","",ROUND(SUMIFS(05_施策抽出!$C:$C,05_施策抽出!$E:$E,$A7,05_施策抽出!$B:$B,"○")*02_施策マスター!$P7*02_施策マスター!$K7,1)) | J7: =IF($I7="","",$I7+(1000-ROW())/1000000) | K7: =IF($H7="","",COUNTIFS($D$2:$D$208,$D7,$J$2:$J$208,">"&$J7)+1) | L7: =IF($K7="","",$D7&"-"&$K7)
A8: =02_施策マスター!A8 -> AIMF-GV-ORG-007 | B8: =02_施策マスター!B8 -> AIセキュリティ予算・リソースの確保 | C8: =02_施策マスター!C8 -> GV | D8: =02_施策マスター!O8 -> 短期 | E8: =02_施策マスター!I8 -> 3 | F8: =02_施策マスター!H8 -> 2 | G8: =COUNTIFS(05_施策抽出!$E:$E,$A8,05_施策抽出!$B:$B,"○") -> 0 | H8: =IF($G8>0,"○","") | I8: =IF($H8="","",ROUND(SUMIFS(05_施策抽出!$C:$C,05_施策抽出!$E:$E,$A8,05_施策抽出!$B:$B,"○")*02_施策マスター!$P8*02_施策マスター!$K8,1)) | J8: =IF($I8="","",$I8+(1000-ROW())/1000000) | K8: =IF($H8="","",COUNTIFS($D$2:$D$208,$D8,$J$2:$J$208,">"&$J8)+1) | L8: =IF($K8="","",$D8&"-"&$K8)
A9: =02_施策マスター!A9 -> AIMF-GV-ORG-008 | B9: =02_施策マスター!B9 -> AIライフサイクル全体のRACI定義 | C9: =02_施策マスター!C9 -> GV | D9: =02_施策マスター!O9 -> 短期 | E9: =02_施策マスター!I9 -> 3 | F9: =02_施策マスター!H9 -> 2 | G9: =COUNTIFS(05_施策抽出!$E:$E,$A9,05_施策抽出!$B:$B,"○") -> 0 | H9: =IF($G9>0,"○","") | I9: =IF($H9="","",ROUND(SUMIFS(05_施策抽出!$C:$C,05_施策抽出!$E:$E,$A9,05_施策抽出!$B:$B,"○")*02_施策マスター!$P9*02_施策マスター!$K9,1)) | J9: =IF($I9="","",$I9+(1000-ROW())/1000000) | K9: =IF($H9="","",COUNTIFS($D$2:$D$208,$D9,$J$2:$J$208,">"&$J9)+1) | L9: =IF($K9="","",$D9&"-"&$K9)
A10: =02_施策マスター!A10 -> AIMF-GV-ORG-009 | B10: =02_施策マスター!B10 -> AI倫理審査との連携プロセス | C10: =02_施策マスター!C10 -> GV | D10: =02_施策マスター!O10 -> 短期 | E10: =02_施策マスター!I10 -> 3 | F10: =02_施策マスター!H10 -> 2 | G10: =COUNTIFS(05_施策抽出!$E:$E,$A10,05_施策抽出!$B:$B,"○") -> 0 | H10: =IF($G10>0,"○","") | I10: =IF($H10="","",ROUND(SUMIFS(05_施策抽出!$C:$C,05_施策抽出!$E:$E,$A10,05_施策抽出!$B:$B,"○")*02_施策マスター!$P10*02_施策マスター!$K10,1)) | J10: =IF($I10="","",$I10+(1000-ROW())/1000000) | K10: =IF($H10="","",COUNTIFS($D$2:$D$208,$D10,$J$2:$J$208,">"&$J10)+1) | L10: =IF($K10="","",$D10&"-"&$K10)
A11: =02_施策マスター!A11 -> AIMF-GV-POL-001 | B11: =02_施策マスター!B11 -> AIポリシースイートの体系化 | C11: =02_施策マスター!C11 -> GV | D11: =02_施策マスター!O11 -> 短期 | E11: =02_施策マスター!I11 -> 3 | F11: =02_施策マスター!H11 -> 2 | G11: =COUNTIFS(05_施策抽出!$E:$E,$A11,05_施策抽出!$B:$B,"○") -> 0 | H11: =IF($G11>0,"○","") | I11: =IF($H11="","",ROUND(SUMIFS(05_施策抽出!$C:$C,05_施策抽出!$E:$E,$A11,05_施策抽出!$B:$B,"○")*02_施策マスター!$P11*02_施策マスター!$K11,1)) | J11: =IF($I11="","",$I11+(1000-ROW())/1000000) | K11: =IF($H11="","",COUNTIFS($D$2:$D$208,$D11,$J$2:$J$208,">"&$J11)+1) | L11: =IF($K11="","",$D11&"-"&$K11)
A12: =02_施策マスター!A12 -> AIMF-GV-POL-002 | B12: =02_施策マスター!B12 -> 生成AI利用細則（入力禁止情報・プロンプト取扱規程） | C12: =02_施策マスター!C12 -> GV | D12: =02_施策マスター!O12 -> 中期 | E12: =02_施策マスター!I12 -> 6 | F12: =02_施策マスター!H12 -> 3 | G12: =COUNTIFS(05_施策抽出!$E:$E,$A12,05_施策抽出!$B:$B,"○") -> 0 | H12: =IF($G12>0,"○","") | I12: =IF($H12="","",ROUND(SUMIFS(05_施策抽出!$C:$C,05_施策抽出!$E:$E,$A12,05_施策抽出!$B:$B,"○")*02_施策マスター!$P12*02_施策マスター!$K12,1)) | J12: =IF($I12="","",$I12+(1000-ROW())/1000000) | K12: =IF($H12="","",COUNTIFS($D$2:$D$208,$D12,$J$2:$J$208,">"&$J12)+1) | L12: =IF($K12="","",$D12&"-"&$K12)
A13: =02_施策マスター!A13 -> AIMF-GV-POL-003 | B13: =02_施策マスター!B13 -> 承認済みAIサービスカタログと例外管理 | C13: =02_施策マスター!C13 -> GV | D13: =02_施策マスター!O13 -> 短期 | E13: =02_施策マスター!I13 -> 3 | F13: =02_施策マスター!H13 -> 2 | G13: =COUNTIFS(05_施策抽出!$E:$E,$A13,05_施策抽出!$B:$B,"○") -> 0 | H13: =IF($G13>0,"○","") | I13: =IF($H13="","",ROUND(SUMIFS(05_施策抽出!$C:$C,05_施策抽出!$E:$E,$A13,05_施策抽出!$B:$B,"○")*02_施策マスター!$P13*02_施策マスター!$K13,1)) | J13: =IF($I13="","",$I13+(1000-ROW())/1000000) | K13: =IF($H13="","",COUNTIFS($D$2:$D$208,$D13,$J$2:$J$208,">"&$J13)+1) | L13: =IF($K13="","",$D13&"-"&$K13)
... A208: =02_施策マスター!A208 -> AIMF-RC-PMM-001 | B208: =02_施策マスター!B208 -> 市販後モニタリング計画（Post-market Monitoring） | C208: =02_施策マスター!C208 -> RC | D208: =02_施策マスター!O208 -> 中期 | E208: =02_施策マスター!I208 -> 6 | F208: =02_施策マスター!H208 -> 3 | G208: =COUNTIFS(05_施策抽出!$E:$E,$A208,05_施策抽出!$B:$B,"○") -> 0 | H208: =IF($G208>0,"○","") | I208: =IF($H208="","",ROUND(SUMIFS(05_施策抽出!$C:$C,05_施策抽出!$E:$E,$A208,05_施策抽出!$B:$B,"○")*02_施策マスター!$P208*02_施策マスター!$K208,1)) | J208: =IF($I208="","",$I208+(1000-ROW())/1000000) | K208: =IF($H208="","",COUNTIFS($D$2:$D$208,$D208,$J$2:$J$208,">"&$J208)+1) | L208: =IF($K208="","",$D208&"-"&$K208)

Sheet 07_短中長Top5
A1: 短期 Top5（〜6か月） | F1: 中期 Top5（6〜18か月） | K1: 長期 Top5（18か月〜）
A2: 順位 | B2: 施策ID | C2: 施策名 | D2: 推奨優先度 | F2: 順位 | G2: 施策ID | H2: 施策名 | I2: 推奨優先度 | K2: 順位 | L2: 施策ID | M2: 施策名 | N2: 推奨優先度
A3: 1 | B3: =IFERROR(INDEX(06_重複排除後!$A:$A,MATCH("短期-"&$A3,06_重複排除後!$L:$L,0)),"") | C3: =IF($B3="","",VLOOKUP($B3,06_重複排除後!$A:$B,2,0)) | D3: =IF($B3="","",VLOOKUP($B3,06_重複排除後!$A:$I,9,0)) | F3: 1 | G3: =IFERROR(INDEX(06_重複排除後!$A:$A,MATCH("中期-"&$F3,06_重複排除後!$L:$L,0)),"") | H3: =IF($G3="","",VLOOKUP($G3,06_重複排除後!$A:$B,2,0)) | I3: =IF($G3="","",VLOOKUP($G3,06_重複排除後!$A:$I,9,0)) | K3: 1 | L3: =IFERROR(INDEX(06_重複排除後!$A:$A,MATCH("長期-"&$K3,06_重複排除後!$L:$L,0)),"") | M3: =IF($L3="","",VLOOKUP($L3,06_重複排除後!$A:$B,2,0)) | N3: =IF($L3="","",VLOOKUP($L3,06_重複排除後!$A:$I,9,0))
A4: 2 | B4: =IFERROR(INDEX(06_重複排除後!$A:$A,MATCH("短期-"&$A4,06_重複排除後!$L:$L,0)),"") | C4: =IF($B4="","",VLOOKUP($B4,06_重複排除後!$A:$B,2,0)) | D4: =IF($B4="","",VLOOKUP($B4,06_重複排除後!$A:$I,9,0)) | F4: 2 | G4: =IFERROR(INDEX(06_重複排除後!$A:$A,MATCH("中期-"&$F4,06_重複排除後!$L:$L,0)),"") | H4: =IF($G4="","",VLOOKUP($G4,06_重複排除後!$A:$B,2,0)) | I4: =IF($G4="","",VLOOKUP($G4,06_重複排除後!$A:$I,9,0)) | K4: 2 | L4: =IFERROR(INDEX(06_重複排除後!$A:$A,MATCH("長期-"&$K4,06_重複排除後!$L:$L,0)),"") | M4: =IF($L4="","",VLOOKUP($L4,06_重複排除後!$A:$B,2,0)) | N4: =IF($L4="","",VLOOKUP($L4,06_重複排除後!$A:$I,9,0))
A5: 3 | B5: =IFERROR(INDEX(06_重複排除後!$A:$A,MATCH("短期-"&$A5,06_重複排除後!$L:$L,0)),"") | C5: =IF($B5="","",VLOOKUP($B5,06_重複排除後!$A:$B,2,0)) | D5: =IF($B5="","",VLOOKUP($B5,06_重複排除後!$A:$I,9,0)) | F5: 3 | G5: =IFERROR(INDEX(06_重複排除後!$A:$A,MATCH("中期-"&$F5,06_重複排除後!$L:$L,0)),"") | H5: =IF($G5="","",VLOOKUP($G5,06_重複排除後!$A:$B,2,0)) | I5: =IF($G5="","",VLOOKUP($G5,06_重複排除後!$A:$I,9,0)) | K5: 3 | L5: =IFERROR(INDEX(06_重複排除後!$A:$A,MATCH("長期-"&$K5,06_重複排除後!$L:$L,0)),"") | M5: =IF($L5="","",VLOOKUP($L5,06_重複排除後!$A:$B,2,0)) | N5: =IF($L5="","",VLOOKUP($L5,06_重複排除後!$A:$I,9,0))
A6: 4 | B6: =IFERROR(INDEX(06_重複排除後!$A:$A,MATCH("短期-"&$A6,06_重複排除後!$L:$L,0)),"") | C6: =IF($B6="","",VLOOKUP($B6,06_重複排除後!$A:$B,2,0)) | D6: =IF($B6="","",VLOOKUP($B6,06_重複排除後!$A:$I,9,0)) | F6: 4 | G6: =IFERROR(INDEX(06_重複排除後!$A:$A,MATCH("中期-"&$F6,06_重複排除後!$L:$L,0)),"") | H6: =IF($G6="","",VLOOKUP($G6,06_重複排除後!$A:$B,2,0)) | I6: =IF($G6="","",VLOOKUP($G6,06_重複排除後!$A:$I,9,0)) | K6: 4 | L6: =IFERROR(INDEX(06_重複排除後!$A:$A,MATCH("長期-"&$K6,06_重複排除後!$L:$L,0)),"") | M6: =IF($L6="","",VLOOKUP($L6,06_重複排除後!$A:$B,2,0)) | N6: =IF($L6="","",VLOOKUP($L6,06_重複排除後!$A:$I,9,0))
A7: 5 | B7: =IFERROR(INDEX(06_重複排除後!$A:$A,MATCH("短期-"&$A7,06_重複排除後!$L:$L,0)),"") | C7: =IF($B7="","",VLOOKUP($B7,06_重複排除後!$A:$B,2,0)) | D7: =IF($B7="","",VLOOKUP($B7,06_重複排除後!$A:$I,9,0)) | F7: 5 | G7: =IFERROR(INDEX(06_重複排除後!$A:$A,MATCH("中期-"&$F7,06_重複排除後!$L:$L,0)),"") | H7: =IF($G7="","",VLOOKUP($G7,06_重複排除後!$A:$B,2,0)) | I7: =IF($G7="","",VLOOKUP($G7,06_重複排除後!$A:$I,9,0)) | K7: 5 | L7: =IFERROR(INDEX(06_重複排除後!$A:$A,MATCH("長期-"&$K7,06_重複排除後!$L:$L,0)),"") | M7: =IF($L7="","",VLOOKUP($L7,06_重複排除後!$A:$B,2,0)) | N7: =IF($L7="","",VLOOKUP($L7,06_重複排除後!$A:$I,9,0))

Sheet 08_ロードマップ
A1: 区分 | B1: 順位 | C1: 施策ID | D1: 施策名 | E1: AIMF区分 | F1: 標準期間(月) | G1: 推奨優先度 | H1: (内部)区分 | I1: (内部)順位
A2: =IF($C2="","",$H2) | B2: =IF($C2="","",$I2) | C2: =IFERROR(INDEX(06_重複排除後!$A:$A,MATCH($H2&"-"&$I2,06_重複排除後!$L:$L,0)),"") | D2: =IF($C2="","",VLOOKUP($C2,06_重複排除後!$A:$B,2,0)) | E2: =IF($C2="","",VLOOKUP($C2,06_重複排除後!$A:$C,3,0)) | F2: =IF($C2="","",VLOOKUP($C2,06_重複排除後!$A:$E,5,0)) | G2: =IF($C2="","",VLOOKUP($C2,06_重複排除後!$A:$I,9,0)) | H2: 短期 | I2: 1
A3: =IF($C3="","",$H3) | B3: =IF($C3="","",$I3) | C3: =IFERROR(INDEX(06_重複排除後!$A:$A,MATCH($H3&"-"&$I3,06_重複排除後!$L:$L,0)),"") | D3: =IF($C3="","",VLOOKUP($C3,06_重複排除後!$A:$B,2,0)) | E3: =IF($C3="","",VLOOKUP($C3,06_重複排除後!$A:$C,3,0)) | F3: =IF($C3="","",VLOOKUP($C3,06_重複排除後!$A:$E,5,0)) | G3: =IF($C3="","",VLOOKUP($C3,06_重複排除後!$A:$I,9,0)) | H3: 短期 | I3: 2
A4: =IF($C4="","",$H4) | B4: =IF($C4="","",$I4) | C4: =IFERROR(INDEX(06_重複排除後!$A:$A,MATCH($H4&"-"&$I4,06_重複排除後!$L:$L,0)),"") | D4: =IF($C4="","",VLOOKUP($C4,06_重複排除後!$A:$B,2,0)) | E4: =IF($C4="","",VLOOKUP($C4,06_重複排除後!$A:$C,3,0)) | F4: =IF($C4="","",VLOOKUP($C4,06_重複排除後!$A:$E,5,0)) | G4: =IF($C4="","",VLOOKUP($C4,06_重複排除後!$A:$I,9,0)) | H4: 短期 | I4: 3
A5: =IF($C5="","",$H5) | B5: =IF($C5="","",$I5) | C5: =IFERROR(INDEX(06_重複排除後!$A:$A,MATCH($H5&"-"&$I5,06_重複排除後!$L:$L,0)),"") | D5: =IF($C5="","",VLOOKUP($C5,06_重複排除後!$A:$B,2,0)) | E5: =IF($C5="","",VLOOKUP($C5,06_重複排除後!$A:$C,3,0)) | F5: =IF($C5="","",VLOOKUP($C5,06_重複排除後!$A:$E,5,0)) | G5: =IF($C5="","",VLOOKUP($C5,06_重複排除後!$A:$I,9,0)) | H5: 短期 | I5: 4
A6: =IF($C6="","",$H6) | B6: =IF($C6="","",$I6) | C6: =IFERROR(INDEX(06_重複排除後!$A:$A,MATCH($H6&"-"&$I6,06_重複排除後!$L:$L,0)),"") | D6: =IF($C6="","",VLOOKUP($C6,06_重複排除後!$A:$B,2,0)) | E6: =IF($C6="","",VLOOKUP($C6,06_重複排除後!$A:$C,3,0)) | F6: =IF($C6="","",VLOOKUP($C6,06_重複排除後!$A:$E,5,0)) | G6: =IF($C6="","",VLOOKUP($C6,06_重複排除後!$A:$I,9,0)) | H6: 短期 | I6: 5
A7: =IF($C7="","",$H7) | B7: =IF($C7="","",$I7) | C7: =IFERROR(INDEX(06_重複排除後!$A:$A,MATCH($H7&"-"&$I7,06_重複排除後!$L:$L,0)),"") | D7: =IF($C7="","",VLOOKUP($C7,06_重複排除後!$A:$B,2,0)) | E7: =IF($C7="","",VLOOKUP($C7,06_重複排除後!$A:$C,3,0)) | F7: =IF($C7="","",VLOOKUP($C7,06_重複排除後!$A:$E,5,0)) | G7: =IF($C7="","",VLOOKUP($C7,06_重複排除後!$A:$I,9,0)) | H7: 短期 | I7: 6
A8: =IF($C8="","",$H8) | B8: =IF($C8="","",$I8) | C8: =IFERROR(INDEX(06_重複排除後!$A:$A,MATCH($H8&"-"&$I8,06_重複排除後!$L:$L,0)),"") | D8: =IF($C8="","",VLOOKUP($C8,06_重複排除後!$A:$B,2,0)) | E8: =IF($C8="","",VLOOKUP($C8,06_重複排除後!$A:$C,3,0)) | F8: =IF($C8="","",VLOOKUP($C8,06_重複排除後!$A:$E,5,0)) | G8: =IF($C8="","",VLOOKUP($C8,06_重複排除後!$A:$I,9,0)) | H8: 短期 | I8: 7
A9: =IF($C9="","",$H9) | B9: =IF($C9="","",$I9) | C9: =IFERROR(INDEX(06_重複排除後!$A:$A,MATCH($H9&"-"&$I9,06_重複排除後!$L:$L,0)),"") | D9: =IF($C9="","",VLOOKUP($C9,06_重複排除後!$A:$B,2,0)) | E9: =IF($C9="","",VLOOKUP($C9,06_重複排除後!$A:$C,3,0)) | F9: =IF($C9="","",VLOOKUP($C9,06_重複排除後!$A:$E,5,0)) | G9: =IF($C9="","",VLOOKUP($C9,06_重複排除後!$A:$I,9,0)) | H9: 短期 | I9: 8
A10: =IF($C10="","",$H10) | B10: =IF($C10="","",$I10) | C10: =IFERROR(INDEX(06_重複排除後!$A:$A,MATCH($H10&"-"&$I10,06_重複排除後!$L:$L,0)),"") | D10: =IF($C10="","",VLOOKUP($C10,06_重複排除後!$A:$B,2,0)) | E10: =IF($C10="","",VLOOKUP($C10,06_重複排除後!$A:$C,3,0)) | F10: =IF($C10="","",VLOOKUP($C10,06_重複排除後!$A:$E,5,0)) | G10: =IF($C10="","",VLOOKUP($C10,06_重複排除後!$A:$I,9,0)) | H10: 短期 | I10: 9
A11: =IF($C11="","",$H11) | B11: =IF($C11="","",$I11) | C11: =IFERROR(INDEX(06_重複排除後!$A:$A,MATCH($H11&"-"&$I11,06_重複排除後!$L:$L,0)),"") | D11: =IF($C11="","",VLOOKUP($C11,06_重複排除後!$A:$B,2,0)) | E11: =IF($C11="","",VLOOKUP($C11,06_重複排除後!$A:$C,3,0)) | F11: =IF($C11="","",VLOOKUP($C11,06_重複排除後!$A:$E,5,0)) | G11: =IF($C11="","",VLOOKUP($C11,06_重複排除後!$A:$I,9,0)) | H11: 短期 | I11: 10
A12: =IF($C12="","",$H12) | B12: =IF($C12="","",$I12) | C12: =IFERROR(INDEX(06_重複排除後!$A:$A,MATCH($H12&"-"&$I12,06_重複排除後!$L:$L,0)),"") | D12: =IF($C12="","",VLOOKUP($C12,06_重複排除後!$A:$B,2,0)) | E12: =IF($C12="","",VLOOKUP($C12,06_重複排除後!$A:$C,3,0)) | F12: =IF($C12="","",VLOOKUP($C12,06_重複排除後!$A:$E,5,0)) | G12: =IF($C12="","",VLOOKUP($C12,06_重複排除後!$A:$I,9,0)) | H12: 短期 | I12: 11
A13: =IF($C13="","",$H13) | B13: =IF($C13="","",$I13) | C13: =IFERROR(INDEX(06_重複排除後!$A:$A,MATCH($H13&"-"&$I13,06_重複排除後!$L:$L,0)),"") | D13: =IF($C13="","",VLOOKUP($C13,06_重複排除後!$A:$B,2,0)) | E13: =IF($C13="","",VLOOKUP($C13,06_重複排除後!$A:$C,3,0)) | F13: =IF($C13="","",VLOOKUP($C13,06_重複排除後!$A:$E,5,0)) | G13: =IF($C13="","",VLOOKUP($C13,06_重複排除後!$A:$I,9,0)) | H13: 短期 | I13: 12
... A208: =IF($C208="","",$H208) | B208: =IF($C208="","",$I208) | C208: =IFERROR(INDEX(06_重複排除後!$A:$A,MATCH($H208&"-"&$I208,06_重複排除後!$L:$L,0)),"") | D208: =IF($C208="","",VLOOKUP($C208,06_重複排除後!$A:$B,2,0)) | E208: =IF($C208="","",VLOOKUP($C208,06_重複排除後!$A:$C,3,0)) | F208: =IF($C208="","",VLOOKUP($C208,06_重複排除後!$A:$E,5,0)) | G208: =IF($C208="","",VLOOKUP($C208,06_重複排除後!$A:$I,9,0)) | H208: 長期 | I208: 87

Sheet 09_ガント元データ
A1: 施策ID | B1: 施策名 | C1: 区分 | D1: 標準期間(月) | E1: 依存施策ID | F1: 依存採用 | G1: 開始月 | H1: 終了月
A2: =08_ロードマップ!C2 | B2: =IF($A2="","",08_ロードマップ!D2) | C2: =IF($A2="","",08_ロードマップ!A2) | D2: =IF($A2="","",08_ロードマップ!F2) | E2: =IF($A2="","",IFERROR(VLOOKUP($A2,04_依存関係マスター!$A:$C,3,0),"")) | F2: =IF($E2="","",IF(COUNTIFS(06_重複排除後!$A:$A,$E2,06_重複排除後!$H:$H,"○")>0,"採用","")) | G2: =IF($A2="","",MAX(IF($C2="短期",00_はじめに!$B$20,IF($C2="中期",00_はじめに!$B$21,00_はじめに!$B$22)),IF($F2="採用",IFERROR(VLOOKUP($E2,$A:$H,8,0)+1,0),0))) | H2: =IF($A2="","",MIN(36,$G2+$D2-1))
A3: =08_ロードマップ!C3 | B3: =IF($A3="","",08_ロードマップ!D3) | C3: =IF($A3="","",08_ロードマップ!A3) | D3: =IF($A3="","",08_ロードマップ!F3) | E3: =IF($A3="","",IFERROR(VLOOKUP($A3,04_依存関係マスター!$A:$C,3,0),"")) | F3: =IF($E3="","",IF(COUNTIFS(06_重複排除後!$A:$A,$E3,06_重複排除後!$H:$H,"○")>0,"採用","")) | G3: =IF($A3="","",MAX(IF($C3="短期",00_はじめに!$B$20,IF($C3="中期",00_はじめに!$B$21,00_はじめに!$B$22)),IF($F3="採用",IFERROR(VLOOKUP($E3,$A:$H,8,0)+1,0),0))) | H3: =IF($A3="","",MIN(36,$G3+$D3-1))
A4: =08_ロードマップ!C4 | B4: =IF($A4="","",08_ロードマップ!D4) | C4: =IF($A4="","",08_ロードマップ!A4) | D4: =IF($A4="","",08_ロードマップ!F4) | E4: =IF($A4="","",IFERROR(VLOOKUP($A4,04_依存関係マスター!$A:$C,3,0),"")) | F4: =IF($E4="","",IF(COUNTIFS(06_重複排除後!$A:$A,$E4,06_重複排除後!$H:$H,"○")>0,"採用","")) | G4: =IF($A4="","",MAX(IF($C4="短期",00_はじめに!$B$20,IF($C4="中期",00_はじめに!$B$21,00_はじめに!$B$22)),IF($F4="採用",IFERROR(VLOOKUP($E4,$A:$H,8,0)+1,0),0))) | H4: =IF($A4="","",MIN(36,$G4+$D4-1))
A5: =08_ロードマップ!C5 | B5: =IF($A5="","",08_ロードマップ!D5) | C5: =IF($A5="","",08_ロードマップ!A5) | D5: =IF($A5="","",08_ロードマップ!F5) | E5: =IF($A5="","",IFERROR(VLOOKUP($A5,04_依存関係マスター!$A:$C,3,0),"")) | F5: =IF($E5="","",IF(COUNTIFS(06_重複排除後!$A:$A,$E5,06_重複排除後!$H:$H,"○")>0,"採用","")) | G5: =IF($A5="","",MAX(IF($C5="短期",00_はじめに!$B$20,IF($C5="中期",00_はじめに!$B$21,00_はじめに!$B$22)),IF($F5="採用",IFERROR(VLOOKUP($E5,$A:$H,8,0)+1,0),0))) | H5: =IF($A5="","",MIN(36,$G5+$D5-1))
A6: =08_ロードマップ!C6 | B6: =IF($A6="","",08_ロードマップ!D6) | C6: =IF($A6="","",08_ロードマップ!A6) | D6: =IF($A6="","",08_ロードマップ!F6) | E6: =IF($A6="","",IFERROR(VLOOKUP($A6,04_依存関係マスター!$A:$C,3,0),"")) | F6: =IF($E6="","",IF(COUNTIFS(06_重複排除後!$A:$A,$E6,06_重複排除後!$H:$H,"○")>0,"採用","")) | G6: =IF($A6="","",MAX(IF($C6="短期",00_はじめに!$B$20,IF($C6="中期",00_はじめに!$B$21,00_はじめに!$B$22)),IF($F6="採用",IFERROR(VLOOKUP($E6,$A:$H,8,0)+1,0),0))) | H6: =IF($A6="","",MIN(36,$G6+$D6-1))
A7: =08_ロードマップ!C7 | B7: =IF($A7="","",08_ロードマップ!D7) | C7: =IF($A7="","",08_ロードマップ!A7) | D7: =IF($A7="","",08_ロードマップ!F7) | E7: =IF($A7="","",IFERROR(VLOOKUP($A7,04_依存関係マスター!$A:$C,3,0),"")) | F7: =IF($E7="","",IF(COUNTIFS(06_重複排除後!$A:$A,$E7,06_重複排除後!$H:$H,"○")>0,"採用","")) | G7: =IF($A7="","",MAX(IF($C7="短期",00_はじめに!$B$20,IF($C7="中期",00_はじめに!$B$21,00_はじめに!$B$22)),IF($F7="採用",IFERROR(VLOOKUP($E7,$A:$H,8,0)+1,0),0))) | H7: =IF($A7="","",MIN(36,$G7+$D7-1))
A8: =08_ロードマップ!C8 | B8: =IF($A8="","",08_ロードマップ!D8) | C8: =IF($A8="","",08_ロードマップ!A8) | D8: =IF($A8="","",08_ロードマップ!F8) | E8: =IF($A8="","",IFERROR(VLOOKUP($A8,04_依存関係マスター!$A:$C,3,0),"")) | F8: =IF($E8="","",IF(COUNTIFS(06_重複排除後!$A:$A,$E8,06_重複排除後!$H:$H,"○")>0,"採用","")) | G8: =IF($A8="","",MAX(IF($C8="短期",00_はじめに!$B$20,IF($C8="中期",00_はじめに!$B$21,00_はじめに!$B$22)),IF($F8="採用",IFERROR(VLOOKUP($E8,$A:$H,8,0)+1,0),0))) | H8: =IF($A8="","",MIN(36,$G8+$D8-1))
A9: =08_ロードマップ!C9 | B9: =IF($A9="","",08_ロードマップ!D9) | C9: =IF($A9="","",08_ロードマップ!A9) | D9: =IF($A9="","",08_ロードマップ!F9) | E9: =IF($A9="","",IFERROR(VLOOKUP($A9,04_依存関係マスター!$A:$C,3,0),"")) | F9: =IF($E9="","",IF(COUNTIFS(06_重複排除後!$A:$A,$E9,06_重複排除後!$H:$H,"○")>0,"採用","")) | G9: =IF($A9="","",MAX(IF($C9="短期",00_はじめに!$B$20,IF($C9="中期",00_はじめに!$B$21,00_はじめに!$B$22)),IF($F9="採用",IFERROR(VLOOKUP($E9,$A:$H,8,0)+1,0),0))) | H9: =IF($A9="","",MIN(36,$G9+$D9-1))
A10: =08_ロードマップ!C10 | B10: =IF($A10="","",08_ロードマップ!D10) | C10: =IF($A10="","",08_ロードマップ!A10) | D10: =IF($A10="","",08_ロードマップ!F10) | E10: =IF($A10="","",IFERROR(VLOOKUP($A10,04_依存関係マスター!$A:$C,3,0),"")) | F10: =IF($E10="","",IF(COUNTIFS(06_重複排除後!$A:$A,$E10,06_重複排除後!$H:$H,"○")>0,"採用","")) | G10: =IF($A10="","",MAX(IF($C10="短期",00_はじめに!$B$20,IF($C10="中期",00_はじめに!$B$21,00_はじめに!$B$22)),IF($F10="採用",IFERROR(VLOOKUP($E10,$A:$H,8,0)+1,0),0))) | H10: =IF($A10="","",MIN(36,$G10+$D10-1))
A11: =08_ロードマップ!C11 | B11: =IF($A11="","",08_ロードマップ!D11) | C11: =IF($A11="","",08_ロードマップ!A11) | D11: =IF($A11="","",08_ロードマップ!F11) | E11: =IF($A11="","",IFERROR(VLOOKUP($A11,04_依存関係マスター!$A:$C,3,0),"")) | F11: =IF($E11="","",IF(COUNTIFS(06_重複排除後!$A:$A,$E11,06_重複排除後!$H:$H,"○")>0,"採用","")) | G11: =IF($A11="","",MAX(IF($C11="短期",00_はじめに!$B$20,IF($C11="中期",00_はじめに!$B$21,00_はじめに!$B$22)),IF($F11="採用",IFERROR(VLOOKUP($E11,$A:$H,8,0)+1,0),0))) | H11: =IF($A11="","",MIN(36,$G11+$D11-1))
A12: =08_ロードマップ!C12 | B12: =IF($A12="","",08_ロードマップ!D12) | C12: =IF($A12="","",08_ロードマップ!A12) | D12: =IF($A12="","",08_ロードマップ!F12) | E12: =IF($A12="","",IFERROR(VLOOKUP($A12,04_依存関係マスター!$A:$C,3,0),"")) | F12: =IF($E12="","",IF(COUNTIFS(06_重複排除後!$A:$A,$E12,06_重複排除後!$H:$H,"○")>0,"採用","")) | G12: =IF($A12="","",MAX(IF($C12="短期",00_はじめに!$B$20,IF($C12="中期",00_はじめに!$B$21,00_はじめに!$B$22)),IF($F12="採用",IFERROR(VLOOKUP($E12,$A:$H,8,0)+1,0),0))) | H12: =IF($A12="","",MIN(36,$G12+$D12-1))
A13: =08_ロードマップ!C13 | B13: =IF($A13="","",08_ロードマップ!D13) | C13: =IF($A13="","",08_ロードマップ!A13) | D13: =IF($A13="","",08_ロードマップ!F13) | E13: =IF($A13="","",IFERROR(VLOOKUP($A13,04_依存関係マスター!$A:$C,3,0),"")) | F13: =IF($E13="","",IF(COUNTIFS(06_重複排除後!$A:$A,$E13,06_重複排除後!$H:$H,"○")>0,"採用","")) | G13: =IF($A13="","",MAX(IF($C13="短期",00_はじめに!$B$20,IF($C13="中期",00_はじめに!$B$21,00_はじめに!$B$22)),IF($F13="採用",IFERROR(VLOOKUP($E13,$A:$H,8,0)+1,0),0))) | H13: =IF($A13="","",MIN(36,$G13+$D13-1))
... A208: =08_ロードマップ!C208 | B208: =IF($A208="","",08_ロードマップ!D208) | C208: =IF($A208="","",08_ロードマップ!A208) | D208: =IF($A208="","",08_ロードマップ!F208) | E208: =IF($A208="","",IFERROR(VLOOKUP($A208,04_依存関係マスター!$A:$C,3,0),"")) | F208: =IF($E208="","",IF(COUNTIFS(06_重複排除後!$A:$A,$E208,06_重複排除後!$H:$H,"○")>0,"採用","")) | G208: =IF($A208="","",MAX(IF($C208="短期",00_はじめに!$B$20,IF($C208="中期",00_はじめに!$B$21,00_はじめに!$B$22)),IF($F208="採用",IFERROR(VLOOKUP($E208,$A:$H,8,0)+1,0),0))) | H208: =IF($A208="","",MIN(36,$G208+$D208-1))

Sheet 10_ガントチャート
A1: 施策ID | B1: 施策名 | C1: 区分 | D1: Q1 | G1: Q2 | J1: Q3 | M1: Q4 | P1: Q5 | S1: Q6 | V1: Q7 | Y1: Q8 | AB1: Q9 | AE1: Q10 | AH1: Q11 | AK1: Q12
B2: 月 → | D2: 1 | E2: 2 | F2: 3 | G2: 4 | H2: 5 | I2: 6 | J2: 7 | K2: 8 | L2: 9 | M2: 10 | N2: 11 | O2: 12 | P2: 13 | Q2: 14 | R2: 15 | S2: 16 | T2: 17 | U2: 18 | V2: 19 | W2: 20 | X2: 21 | Y2: 22 | Z2: 23 | AA2: 24 | AB2: 25 | AC2: 26 | AD2: 27 | AE2: 28 | AF2: 29 | AG2: 30 | AH2: 31 | AI2: 32 | AJ2: 33 | AK2: 34 | AL2: 35 | AM2: 36
A3: =09_ガント元データ!A2 | B3: =09_ガント元データ!B2 | C3: =09_ガント元データ!C2 | D3: =IF($A3="","",IF(AND(D$2>=09_ガント元データ!$G2,D$2<=09_ガント元データ!$H2),"■","")) | E3: =IF($A3="","",IF(AND(E$2>=09_ガント元データ!$G2,E$2<=09_ガント元データ!$H2),"■","")) | F3: =IF($A3="","",IF(AND(F$2>=09_ガント元データ!$G2,F$2<=09_ガント元データ!$H2),"■","")) | G3: =IF($A3="","",IF(AND(G$2>=09_ガント元データ!$G2,G$2<=09_ガント元データ!$H2),"■","")) | H3: =IF($A3="","",IF(AND(H$2>=09_ガント元データ!$G2,H$2<=09_ガント元データ!$H2),"■","")) | I3: =IF($A3="","",IF(AND(I$2>=09_ガント元データ!$G2,I$2<=09_ガント元データ!$H2),"■","")) | J3: =IF($A3="","",IF(AND(J$2>=09_ガント元データ!$G2,J$2<=09_ガント元データ!$H2),"■","")) | K3: =IF($A3="","",IF(AND(K$2>=09_ガント元データ!$G2,K$2<=09_ガント元データ!$H2),"■","")) | ... AM3: =IF($A3="","",IF(AND(AM$2>=09_ガント元データ!$G2,AM$2<=09_ガント元データ!$H2),"■",""))
A4: =09_ガント元データ!A3 | B4: =09_ガント元データ!B3 | C4: =09_ガント元データ!C3 | D4: =IF($A4="","",IF(AND(D$2>=09_ガント元データ!$G3,D$2<=09_ガント元データ!$H3),"■","")) | E4: =IF($A4="","",IF(AND(E$2>=09_ガント元データ!$G3,E$2<=09_ガント元データ!$H3),"■","")) | F4: =IF($A4="","",IF(AND(F$2>=09_ガント元データ!$G3,F$2<=09_ガント元データ!$H3),"■","")) | G4: =IF($A4="","",IF(AND(G$2>=09_ガント元データ!$G3,G$2<=09_ガント元データ!$H3),"■","")) | H4: =IF($A4="","",IF(AND(H$2>=09_ガント元データ!$G3,H$2<=09_ガント元データ!$H3),"■","")) | I4: =IF($A4="","",IF(AND(I$2>=09_ガント元データ!$G3,I$2<=09_ガント元データ!$H3),"■","")) | J4: =IF($A4="","",IF(AND(J$2>=09_ガント元データ!$G3,J$2<=09_ガント元データ!$H3),"■","")) | K4: =IF($A4="","",IF(AND(K$2>=09_ガント元データ!$G3,K$2<=09_ガント元データ!$H3),"■","")) | ... AM4: =IF($A4="","",IF(AND(AM$2>=09_ガント元データ!$G3,AM$2<=09_ガント元データ!$H3),"■",""))
A5: =09_ガント元データ!A4 | B5: =09_ガント元データ!B4 | C5: =09_ガント元データ!C4 | D5: =IF($A5="","",IF(AND(D$2>=09_ガント元データ!$G4,D$2<=09_ガント元データ!$H4),"■","")) | E5: =IF($A5="","",IF(AND(E$2>=09_ガント元データ!$G4,E$2<=09_ガント元データ!$H4),"■","")) | F5: =IF($A5="","",IF(AND(F$2>=09_ガント元データ!$G4,F$2<=09_ガント元データ!$H4),"■","")) | G5: =IF($A5="","",IF(AND(G$2>=09_ガント元データ!$G4,G$2<=09_ガント元データ!$H4),"■","")) | H5: =IF($A5="","",IF(AND(H$2>=09_ガント元データ!$G4,H$2<=09_ガント元データ!$H4),"■","")) | I5: =IF($A5="","",IF(AND(I$2>=09_ガント元データ!$G4,I$2<=09_ガント元データ!$H4),"■","")) | J5: =IF($A5="","",IF(AND(J$2>=09_ガント元データ!$G4,J$2<=09_ガント元データ!$H4),"■","")) | K5: =IF($A5="","",IF(AND(K$2>=09_ガント元データ!$G4,K$2<=09_ガント元データ!$H4),"■","")) | ... AM5: =IF($A5="","",IF(AND(AM$2>=09_ガント元データ!$G4,AM$2<=09_ガント元データ!$H4),"■",""))
A6: =09_ガント元データ!A5 | B6: =09_ガント元データ!B5 | C6: =09_ガント元データ!C5 | D6: =IF($A6="","",IF(AND(D$2>=09_ガント元データ!$G5,D$2<=09_ガント元データ!$H5),"■","")) | E6: =IF($A6="","",IF(AND(E$2>=09_ガント元データ!$G5,E$2<=09_ガント元データ!$H5),"■","")) | F6: =IF($A6="","",IF(AND(F$2>=09_ガント元データ!$G5,F$2<=09_ガント元データ!$H5),"■","")) | G6: =IF($A6="","",IF(AND(G$2>=09_ガント元データ!$G5,G$2<=09_ガント元データ!$H5),"■","")) | H6: =IF($A6="","",IF(AND(H$2>=09_ガント元データ!$G5,H$2<=09_ガント元データ!$H5),"■","")) | I6: =IF($A6="","",IF(AND(I$2>=09_ガント元データ!$G5,I$2<=09_ガント元データ!$H5),"■","")) | J6: =IF($A6="","",IF(AND(J$2>=09_ガント元データ!$G5,J$2<=09_ガント元データ!$H5),"■","")) | K6: =IF($A6="","",IF(AND(K$2>=09_ガント元データ!$G5,K$2<=09_ガント元データ!$H5),"■","")) | ... AM6: =IF($A6="","",IF(AND(AM$2>=09_ガント元データ!$G5,AM$2<=09_ガント元データ!$H5),"■",""))
A7: =09_ガント元データ!A6 | B7: =09_ガント元データ!B6 | C7: =09_ガント元データ!C6 | D7: =IF($A7="","",IF(AND(D$2>=09_ガント元データ!$G6,D$2<=09_ガント元データ!$H6),"■","")) | E7: =IF($A7="","",IF(AND(E$2>=09_ガント元データ!$G6,E$2<=09_ガント元データ!$H6),"■","")) | F7: =IF($A7="","",IF(AND(F$2>=09_ガント元データ!$G6,F$2<=09_ガント元データ!$H6),"■","")) | G7: =IF($A7="","",IF(AND(G$2>=09_ガント元データ!$G6,G$2<=09_ガント元データ!$H6),"■","")) | H7: =IF($A7="","",IF(AND(H$2>=09_ガント元データ!$G6,H$2<=09_ガント元データ!$H6),"■","")) | I7: =IF($A7="","",IF(AND(I$2>=09_ガント元データ!$G6,I$2<=09_ガント元データ!$H6),"■","")) | J7: =IF($A7="","",IF(AND(J$2>=09_ガント元データ!$G6,J$2<=09_ガント元データ!$H6),"■","")) | K7: =IF($A7="","",IF(AND(K$2>=09_ガント元データ!$G6,K$2<=09_ガント元データ!$H6),"■","")) | ... AM7: =IF($A7="","",IF(AND(AM$2>=09_ガント元データ!$G6,AM$2<=09_ガント元データ!$H6),"■",""))
A8: =09_ガント元データ!A7 | B8: =09_ガント元データ!B7 | C8: =09_ガント元データ!C7 | D8: =IF($A8="","",IF(AND(D$2>=09_ガント元データ!$G7,D$2<=09_ガント元データ!$H7),"■","")) | E8: =IF($A8="","",IF(AND(E$2>=09_ガント元データ!$G7,E$2<=09_ガント元データ!$H7),"■","")) | F8: =IF($A8="","",IF(AND(F$2>=09_ガント元データ!$G7,F$2<=09_ガント元データ!$H7),"■","")) | G8: =IF($A8="","",IF(AND(G$2>=09_ガント元データ!$G7,G$2<=09_ガント元データ!$H7),"■","")) | H8: =IF($A8="","",IF(AND(H$2>=09_ガント元データ!$G7,H$2<=09_ガント元データ!$H7),"■","")) | I8: =IF($A8="","",IF(AND(I$2>=09_ガント元データ!$G7,I$2<=09_ガント元データ!$H7),"■","")) | J8: =IF($A8="","",IF(AND(J$2>=09_ガント元データ!$G7,J$2<=09_ガント元データ!$H7),"■","")) | K8: =IF($A8="","",IF(AND(K$2>=09_ガント元データ!$G7,K$2<=09_ガント元データ!$H7),"■","")) | ... AM8: =IF($A8="","",IF(AND(AM$2>=09_ガント元データ!$G7,AM$2<=09_ガント元データ!$H7),"■",""))
A9: =09_ガント元データ!A8 | B9: =09_ガント元データ!B8 | C9: =09_ガント元データ!C8 | D9: =IF($A9="","",IF(AND(D$2>=09_ガント元データ!$G8,D$2<=09_ガント元データ!$H8),"■","")) | E9: =IF($A9="","",IF(AND(E$2>=09_ガント元データ!$G8,E$2<=09_ガント元データ!$H8),"■","")) | F9: =IF($A9="","",IF(AND(F$2>=09_ガント元データ!$G8,F$2<=09_ガント元データ!$H8),"■","")) | G9: =IF($A9="","",IF(AND(G$2>=09_ガント元データ!$G8,G$2<=09_ガント元データ!$H8),"■","")) | H9: =IF($A9="","",IF(AND(H$2>=09_ガント元データ!$G8,H$2<=09_ガント元データ!$H8),"■","")) | I9: =IF($A9="","",IF(AND(I$2>=09_ガント元データ!$G8,I$2<=09_ガント元データ!$H8),"■","")) | J9: =IF($A9="","",IF(AND(J$2>=09_ガント元データ!$G8,J$2<=09_ガント元データ!$H8),"■","")) | K9: =IF($A9="","",IF(AND(K$2>=09_ガント元データ!$G8,K$2<=09_ガント元データ!$H8),"■","")) | ... AM9: =IF($A9="","",IF(AND(AM$2>=09_ガント元データ!$G8,AM$2<=09_ガント元データ!$H8),"■",""))
A10: =09_ガント元データ!A9 | B10: =09_ガント元データ!B9 | C10: =09_ガント元データ!C9 | D10: =IF($A10="","",IF(AND(D$2>=09_ガント元データ!$G9,D$2<=09_ガント元データ!$H9),"■","")) | E10: =IF($A10="","",IF(AND(E$2>=09_ガント元データ!$G9,E$2<=09_ガント元データ!$H9),"■","")) | F10: =IF($A10="","",IF(AND(F$2>=09_ガント元データ!$G9,F$2<=09_ガント元データ!$H9),"■","")) | G10: =IF($A10="","",IF(AND(G$2>=09_ガント元データ!$G9,G$2<=09_ガント元データ!$H9),"■","")) | H10: =IF($A10="","",IF(AND(H$2>=09_ガント元データ!$G9,H$2<=09_ガント元データ!$H9),"■","")) | I10: =IF($A10="","",IF(AND(I$2>=09_ガント元データ!$G9,I$2<=09_ガント元データ!$H9),"■","")) | J10: =IF($A10="","",IF(AND(J$2>=09_ガント元データ!$G9,J$2<=09_ガント元データ!$H9),"■","")) | K10: =IF($A10="","",IF(AND(K$2>=09_ガント元データ!$G9,K$2<=09_ガント元データ!$H9),"■","")) | ... AM10: =IF($A10="","",IF(AND(AM$2>=09_ガント元データ!$G9,AM$2<=09_ガント元データ!$H9),"■",""))
A11: =09_ガント元データ!A10 | B11: =09_ガント元データ!B10 | C11: =09_ガント元データ!C10 | D11: =IF($A11="","",IF(AND(D$2>=09_ガント元データ!$G10,D$2<=09_ガント元データ!$H10),"■","")) | E11: =IF($A11="","",IF(AND(E$2>=09_ガント元データ!$G10,E$2<=09_ガント元データ!$H10),"■","")) | F11: =IF($A11="","",IF(AND(F$2>=09_ガント元データ!$G10,F$2<=09_ガント元データ!$H10),"■","")) | G11: =IF($A11="","",IF(AND(G$2>=09_ガント元データ!$G10,G$2<=09_ガント元データ!$H10),"■","")) | H11: =IF($A11="","",IF(AND(H$2>=09_ガント元データ!$G10,H$2<=09_ガント元データ!$H10),"■","")) | I11: =IF($A11="","",IF(AND(I$2>=09_ガント元データ!$G10,I$2<=09_ガント元データ!$H10),"■","")) | J11: =IF($A11="","",IF(AND(J$2>=09_ガント元データ!$G10,J$2<=09_ガント元データ!$H10),"■","")) | K11: =IF($A11="","",IF(AND(K$2>=09_ガント元データ!$G10,K$2<=09_ガント元データ!$H10),"■","")) | ... AM11: =IF($A11="","",IF(AND(AM$2>=09_ガント元データ!$G10,AM$2<=09_ガント元データ!$H10),"■",""))
A12: =09_ガント元データ!A11 | B12: =09_ガント元データ!B11 | C12: =09_ガント元データ!C11 | D12: =IF($A12="","",IF(AND(D$2>=09_ガント元データ!$G11,D$2<=09_ガント元データ!$H11),"■","")) | E12: =IF($A12="","",IF(AND(E$2>=09_ガント元データ!$G11,E$2<=09_ガント元データ!$H11),"■","")) | F12: =IF($A12="","",IF(AND(F$2>=09_ガント元データ!$G11,F$2<=09_ガント元データ!$H11),"■","")) | G12: =IF($A12="","",IF(AND(G$2>=09_ガント元データ!$G11,G$2<=09_ガント元データ!$H11),"■","")) | H12: =IF($A12="","",IF(AND(H$2>=09_ガント元データ!$G11,H$2<=09_ガント元データ!$H11),"■","")) | I12: =IF($A12="","",IF(AND(I$2>=09_ガント元データ!$G11,I$2<=09_ガント元データ!$H11),"■","")) | J12: =IF($A12="","",IF(AND(J$2>=09_ガント元データ!$G11,J$2<=09_ガント元データ!$H11),"■","")) | K12: =IF($A12="","",IF(AND(K$2>=09_ガント元データ!$G11,K$2<=09_ガント元データ!$H11),"■","")) | ... AM12: =IF($A12="","",IF(AND(AM$2>=09_ガント元データ!$G11,AM$2<=09_ガント元データ!$H11),"■",""))
A13: =09_ガント元データ!A12 | B13: =09_ガント元データ!B12 | C13: =09_ガント元データ!C12 | D13: =IF($A13="","",IF(AND(D$2>=09_ガント元データ!$G12,D$2<=09_ガント元データ!$H12),"■","")) | E13: =IF($A13="","",IF(AND(E$2>=09_ガント元データ!$G12,E$2<=09_ガント元データ!$H12),"■","")) | F13: =IF($A13="","",IF(AND(F$2>=09_ガント元データ!$G12,F$2<=09_ガント元データ!$H12),"■","")) | G13: =IF($A13="","",IF(AND(G$2>=09_ガント元データ!$G12,G$2<=09_ガント元データ!$H12),"■","")) | H13: =IF($A13="","",IF(AND(H$2>=09_ガント元データ!$G12,H$2<=09_ガント元データ!$H12),"■","")) | I13: =IF($A13="","",IF(AND(I$2>=09_ガント元データ!$G12,I$2<=09_ガント元データ!$H12),"■","")) | J13: =IF($A13="","",IF(AND(J$2>=09_ガント元データ!$G12,J$2<=09_ガント元データ!$H12),"■","")) | K13: =IF($A13="","",IF(AND(K$2>=09_ガント元データ!$G12,K$2<=09_ガント元データ!$H12),"■","")) | ... AM13: =IF($A13="","",IF(AND(AM$2>=09_ガント元データ!$G12,AM$2<=09_ガント元データ!$H12),"■",""))
A14: =09_ガント元データ!A13 | B14: =09_ガント元データ!B13 | C14: =09_ガント元データ!C13 | D14: =IF($A14="","",IF(AND(D$2>=09_ガント元データ!$G13,D$2<=09_ガント元データ!$H13),"■","")) | E14: =IF($A14="","",IF(AND(E$2>=09_ガント元データ!$G13,E$2<=09_ガント元データ!$H13),"■","")) | F14: =IF($A14="","",IF(AND(F$2>=09_ガント元データ!$G13,F$2<=09_ガント元データ!$H13),"■","")) | G14: =IF($A14="","",IF(AND(G$2>=09_ガント元データ!$G13,G$2<=09_ガント元データ!$H13),"■","")) | H14: =IF($A14="","",IF(AND(H$2>=09_ガント元データ!$G13,H$2<=09_ガント元データ!$H13),"■","")) | I14: =IF($A14="","",IF(AND(I$2>=09_ガント元データ!$G13,I$2<=09_ガント元データ!$H13),"■","")) | J14: =IF($A14="","",IF(AND(J$2>=09_ガント元データ!$G13,J$2<=09_ガント元データ!$H13),"■","")) | K14: =IF($A14="","",IF(AND(K$2>=09_ガント元データ!$G13,K$2<=09_ガント元データ!$H13),"■","")) | ... AM14: =IF($A14="","",IF(AND(AM$2>=09_ガント元データ!$G13,AM$2<=09_ガント元データ!$H13),"■",""))
... A209: =09_ガント元データ!A208 | B209: =09_ガント元データ!B208 | C209: =09_ガント元データ!C208 | D209: =IF($A209="","",IF(AND(D$2>=09_ガント元データ!$G208,D$2<=09_ガント元データ!$H208),"■","")) | E209: =IF($A209="","",IF(AND(E$2>=09_ガント元データ!$G208,E$2<=09_ガント元データ!$H208),"■","")) | F209: =IF($A209="","",IF(AND(F$2>=09_ガント元データ!$G208,F$2<=09_ガント元データ!$H208),"■","")) | G209: =IF($A209="","",IF(AND(G$2>=09_ガント元データ!$G208,G$2<=09_ガント元データ!$H208),"■","")) | H209: =IF($A209="","",IF(AND(H$2>=09_ガント元データ!$G208,H$2<=09_ガント元データ!$H208),"■","")) | I209: =IF($A209="","",IF(AND(I$2>=09_ガント元データ!$G208,I$2<=09_ガント元データ!$H208),"■","")) | J209: =IF($A209="","",IF(AND(J$2>=09_ガント元データ!$G208,J$2<=09_ガント元データ!$H208),"■","")) | K209: =IF($A209="","",IF(AND(K$2>=09_ガント元データ!$G208,K$2<=09_ガント元データ!$H208),"■","")) | ... AM209: =IF($A209="","",IF(AND(AM$2>=09_ガント元データ!$G208,AM$2<=09_ガント元データ!$H208),"■",""))

Sheet 11_ダッシュボード
A1: AIMF v0.1（β版）成熟度ダッシュボード
A3: ■ 回答進捗（適用対象ベース：AI利用プロファイルにより対象外は分母から自動除外）
A4: 適用対象数 | B4: 対象外数 | C4: 回答済み | D4: 進捗率 | E4: うちベースライン回答済み | F4: うち拡張回答済み
A5: =COUNTIF(01_評価入力!$H$2:$H$208,"○") -> 207 | B5: =COUNTIF(01_評価入力!$H$2:$H$208,"対象外") -> 0 | C5: =COUNTIFS(01_評価入力!$H$2:$H$208,"○",01_評価入力!$I$2:$I$208,"<>") -> 0 | D5: =IF($A5=0,0,$C5/$A5) -> 0 | E5: =COUNTIFS(01_評価入力!$H$2:$H$208,"○",01_評価入力!$I$2:$I$208,"<>",01_評価入力!$X$2:$X$208,"baseline")&" / "&COUNTIFS(01_評価入力!$H$2:$H$208,"○",01_評価入力!$X$2:$X$208,"baseline") -> 0 / 71 | F5: =COUNTIFS(01_評価入力!$H$2:$H$208,"○",01_評価入力!$I$2:$I$208,"<>",01_評価入力!$X$2:$X$208,"extended")&" / "&COUNTIFS(01_評価入力!$H$2:$H$208,"○",01_評価入力!$X$2:$X$208,"extended") -> 0 / 136
A7: ■ 区分別成熟度（NIST CSF 2.0の6機能）
A8: 区分 | B8: 適用設問数 | C8: 現状平均 | D8: 目標平均 | E8: ギャップ平均 | F8: 達成率 | G8: 採用施策数
A9: GV | B9: =COUNTIFS(01_評価入力!$B:$B,$A9,01_評価入力!$H:$H,"○") -> 36 | C9: =IFERROR(ROUND(AVERAGEIFS(01_評価入力!$I:$I,01_評価入力!$B:$B,$A9,01_評価入力!$H:$H,"○"),2),0) -> 0 | D9: =IFERROR(ROUND(AVERAGEIFS(01_評価入力!$J:$J,01_評価入力!$B:$B,$A9,01_評価入力!$H:$H,"○"),2),0) -> 3.39 | E9: =IF(OR($C9="",$D9=""),"",ROUND($D9-$C9,2)) -> 3.39 | F9: =IF(OR($D9=0,$C9=""),"",$C9/$D9) -> 0 | G9: =COUNTIFS(06_重複排除後!$C:$C,$A9,06_重複排除後!$H:$H,"○") -> 0
A10: ID | B10: =COUNTIFS(01_評価入力!$B:$B,$A10,01_評価入力!$H:$H,"○") -> 29 | C10: =IFERROR(ROUND(AVERAGEIFS(01_評価入力!$I:$I,01_評価入力!$B:$B,$A10,01_評価入力!$H:$H,"○"),2),0) -> 0 | D10: =IFERROR(ROUND(AVERAGEIFS(01_評価入力!$J:$J,01_評価入力!$B:$B,$A10,01_評価入力!$H:$H,"○"),2),0) -> 3.28 | E10: =IF(OR($C10="",$D10=""),"",ROUND($D10-$C10,2)) -> 3.28 | F10: =IF(OR($D10=0,$C10=""),"",$C10/$D10) -> 0 | G10: =COUNTIFS(06_重複排除後!$C:$C,$A10,06_重複排除後!$H:$H,"○") -> 0
A11: PR | B11: =COUNTIFS(01_評価入力!$B:$B,$A11,01_評価入力!$H:$H,"○") -> 74 | C11: =IFERROR(ROUND(AVERAGEIFS(01_評価入力!$I:$I,01_評価入力!$B:$B,$A11,01_評価入力!$H:$H,"○"),2),0) -> 0 | D11: =IFERROR(ROUND(AVERAGEIFS(01_評価入力!$J:$J,01_評価入力!$B:$B,$A11,01_評価入力!$H:$H,"○"),2),0) -> 3.35 | E11: =IF(OR($C11="",$D11=""),"",ROUND($D11-$C11,2)) -> 3.35 | F11: =IF(OR($D11=0,$C11=""),"",$C11/$D11) -> 0 | G11: =COUNTIFS(06_重複排除後!$C:$C,$A11,06_重複排除後!$H:$H,"○") -> 0
A12: DE | B12: =COUNTIFS(01_評価入力!$B:$B,$A12,01_評価入力!$H:$H,"○") -> 32 | C12: =IFERROR(ROUND(AVERAGEIFS(01_評価入力!$I:$I,01_評価入力!$B:$B,$A12,01_評価入力!$H:$H,"○"),2),0) -> 0 | D12: =IFERROR(ROUND(AVERAGEIFS(01_評価入力!$J:$J,01_評価入力!$B:$B,$A12,01_評価入力!$H:$H,"○"),2),0) -> 3.25 | E12: =IF(OR($C12="",$D12=""),"",ROUND($D12-$C12,2)) -> 3.25 | F12: =IF(OR($D12=0,$C12=""),"",$C12/$D12) -> 0 | G12: =COUNTIFS(06_重複排除後!$C:$C,$A12,06_重複排除後!$H:$H,"○") -> 0
A13: RS | B13: =COUNTIFS(01_評価入力!$B:$B,$A13,01_評価入力!$H:$H,"○") -> 20 | C13: =IFERROR(ROUND(AVERAGEIFS(01_評価入力!$I:$I,01_評価入力!$B:$B,$A13,01_評価入力!$H:$H,"○"),2),0) -> 0 | D13: =IFERROR(ROUND(AVERAGEIFS(01_評価入力!$J:$J,01_評価入力!$B:$B,$A13,01_評価入力!$H:$H,"○"),2),0) -> 3.3 | E13: =IF(OR($C13="",$D13=""),"",ROUND($D13-$C13,2)) -> 3.3 | F13: =IF(OR($D13=0,$C13=""),"",$C13/$D13) -> 0 | G13: =COUNTIFS(06_重複排除後!$C:$C,$A13,06_重複排除後!$H:$H,"○") -> 0
A14: RC | B14: =COUNTIFS(01_評価入力!$B:$B,$A14,01_評価入力!$H:$H,"○") -> 16 | C14: =IFERROR(ROUND(AVERAGEIFS(01_評価入力!$I:$I,01_評価入力!$B:$B,$A14,01_評価入力!$H:$H,"○"),2),0) -> 0 | D14: =IFERROR(ROUND(AVERAGEIFS(01_評価入力!$J:$J,01_評価入力!$B:$B,$A14,01_評価入力!$H:$H,"○"),2),0) -> 3.56 | E14: =IF(OR($C14="",$D14=""),"",ROUND($D14-$C14,2)) -> 3.56 | F14: =IF(OR($D14=0,$C14=""),"",$C14/$D14) -> 0 | G14: =COUNTIFS(06_重複排除後!$C:$C,$A14,06_重複排除後!$H:$H,"○") -> 0
A16: ■ control-type別（未実装の性質を区別：Enhancement=既存運用の適用漏れ／Expansion=AI固有統制の未整備）
A17: control-type | B17: 適用設問数 | C17: 現状平均 | D17: 目標平均 | E17: ギャップ平均 | F17: 解釈
A18: AI-Expansion | B18: =COUNTIFS(01_評価入力!$F:$F,$A18,01_評価入力!$H:$H,"○") -> 108 | C18: =IFERROR(ROUND(AVERAGEIFS(01_評価入力!$I:$I,01_評価入力!$F:$F,$A18,01_評価入力!$H:$H,"○"),2),0) -> 0 | D18: =IFERROR(ROUND(AVERAGEIFS(01_評価入力!$J:$J,01_評価入力!$F:$F,$A18,01_評価入力!$H:$H,"○"),2),0) -> 3.3 | E18: =IF(OR($C18="",$D18=""),"",ROUND($D18-$C18,2)) -> 3.3 | F18: AI特有の新設統制。低い場合はAI固有統制が未整備 → 新規の設計・体制整備が必要
A19: AI-Enhancement | B19: =COUNTIFS(01_評価入力!$F:$F,$A19,01_評価入力!$H:$H,"○") -> 99 | C19: =IFERROR(ROUND(AVERAGEIFS(01_評価入力!$I:$I,01_評価入力!$F:$F,$A19,01_評価入力!$H:$H,"○"),2),0) -> 0 | D19: =IFERROR(ROUND(AVERAGEIFS(01_評価入力!$J:$J,01_評価入力!$F:$F,$A19,01_評価入力!$H:$H,"○"),2),0) -> 3.39 | E19: =IF(OR($C19="",$D19=""),"",ROUND($D19-$C19,2)) -> 3.39 | F19: 既存統制のAI拡張。低い場合は既存セキュリティ運用の適用漏れ → 既存ISMSへの追補で対応可
A21: ■ AI類型別レディネス（各類型に適用される設問＝類型固有＋all の現状平均）
A22: AI類型 | B22: 利用 | C22: 対象設問数 | D22: 現状平均 | E22: 目標平均
A23: 従来型AI | B23: =00_はじめに!$B$24 -> Y | C23: =COUNTIFS(01_評価入力!$G:$G,"*traditional*",01_評価入力!$H:$H,"○")+COUNTIFS(01_評価入力!$G:$G,"all",01_評価入力!$H:$H,"○") -> 143 | D23: =IFERROR(ROUND((SUMIFS(01_評価入力!$I:$I,01_評価入力!$G:$G,"*traditional*")+SUMIFS(01_評価入力!$I:$I,01_評価入力!$G:$G,"all"))/(COUNTIFS(01_評価入力!$G:$G,"*traditional*",01_評価入力!$I:$I,"<>")+COUNTIFS(01_評価入力!$G:$G,"all",01_評価入力!$I:$I,"<>")),2),0) -> 0 | E23: =IFERROR(ROUND((SUMIFS(01_評価入力!$J:$J,01_評価入力!$G:$G,"*traditional*",01_評価入力!$H:$H,"○")+SUMIFS(01_評価入力!$J:$J,01_評価入力!$G:$G,"all",01_評価入力!$H:$H,"○"))/(COUNTIFS(01_評価入力!$G:$G,"*traditional*",01_評価入力!$H:$H,"○")+COUNTIFS(01_評価入力!$G:$G,"all",01_評価入力!$H:$H,"○")),2),0) -> 3.33
A24: 生成AI（LLM・RAG） | B24: =00_はじめに!$B$25 -> Y | C24: =COUNTIFS(01_評価入力!$G:$G,"*generative*",01_評価入力!$H:$H,"○")+COUNTIFS(01_評価入力!$G:$G,"all",01_評価入力!$H:$H,"○") -> 174 | D24: =IFERROR(ROUND((SUMIFS(01_評価入力!$I:$I,01_評価入力!$G:$G,"*generative*")+SUMIFS(01_評価入力!$I:$I,01_評価入力!$G:$G,"all"))/(COUNTIFS(01_評価入力!$G:$G,"*generative*",01_評価入力!$I:$I,"<>")+COUNTIFS(01_評価入力!$G:$G,"all",01_評価入力!$I:$I,"<>")),2),0) -> 0 | E24: =IFERROR(ROUND((SUMIFS(01_評価入力!$J:$J,01_評価入力!$G:$G,"*generative*",01_評価入力!$H:$H,"○")+SUMIFS(01_評価入力!$J:$J,01_評価入力!$G:$G,"all",01_評価入力!$H:$H,"○"))/(COUNTIFS(01_評価入力!$G:$G,"*generative*",01_評価入力!$H:$H,"○")+COUNTIFS(01_評価入力!$G:$G,"all",01_評価入力!$H:$H,"○")),2),0) -> 3.34
A25: AIエージェント | B25: =00_はじめに!$B$26 -> Y | C25: =COUNTIFS(01_評価入力!$G:$G,"*ai-agent*",01_評価入力!$H:$H,"○")+COUNTIFS(01_評価入力!$G:$G,"all",01_評価入力!$H:$H,"○") -> 181 | D25: =IFERROR(ROUND((SUMIFS(01_評価入力!$I:$I,01_評価入力!$G:$G,"*ai-agent*")+SUMIFS(01_評価入力!$I:$I,01_評価入力!$G:$G,"all"))/(COUNTIFS(01_評価入力!$G:$G,"*ai-agent*",01_評価入力!$I:$I,"<>")+COUNTIFS(01_評価入力!$G:$G,"all",01_評価入力!$I:$I,"<>")),2),0) -> 0 | E25: =IFERROR(ROUND((SUMIFS(01_評価入力!$J:$J,01_評価入力!$G:$G,"*ai-agent*",01_評価入力!$H:$H,"○")+SUMIFS(01_評価入力!$J:$J,01_評価入力!$G:$G,"all",01_評価入力!$H:$H,"○"))/(COUNTIFS(01_評価入力!$G:$G,"*ai-agent*",01_評価入力!$H:$H,"○")+COUNTIFS(01_評価入力!$G:$G,"all",01_評価入力!$H:$H,"○")),2),0) -> 3.33
A26: マルチエージェント | B26: =00_はじめに!$B$27 -> Y | C26: =COUNTIFS(01_評価入力!$G:$G,"*multi-agent*",01_評価入力!$H:$H,"○")+COUNTIFS(01_評価入力!$G:$G,"all",01_評価入力!$H:$H,"○") -> 170 | D26: =IFERROR(ROUND((SUMIFS(01_評価入力!$I:$I,01_評価入力!$G:$G,"*multi-agent*")+SUMIFS(01_評価入力!$I:$I,01_評価入力!$G:$G,"all"))/(COUNTIFS(01_評価入力!$G:$G,"*multi-agent*",01_評価入力!$I:$I,"<>")+COUNTIFS(01_評価入力!$G:$G,"all",01_評価入力!$I:$I,"<>")),2),0) -> 0 | E26: =IFERROR(ROUND((SUMIFS(01_評価入力!$J:$J,01_評価入力!$G:$G,"*multi-agent*",01_評価入力!$H:$H,"○")+SUMIFS(01_評価入力!$J:$J,01_評価入力!$G:$G,"all",01_評価入力!$H:$H,"○"))/(COUNTIFS(01_評価入力!$G:$G,"*multi-agent*",01_評価入力!$H:$H,"○")+COUNTIFS(01_評価入力!$G:$G,"all",01_評価入力!$H:$H,"○")),2),0) -> 3.33
A28: ■ ロードマップ区分別 採用施策数
A29: 区分 | B29: 採用施策数
A30: 短期 | B30: =COUNTIFS(06_重複排除後!$D:$D,$A30,06_重複排除後!$H:$H,"○") -> 0
A31: 中期 | B31: =COUNTIFS(06_重複排除後!$D:$D,$A31,06_重複排除後!$H:$H,"○") -> 0
A32: 長期 | B32: =COUNTIFS(06_重複排除後!$D:$D,$A32,06_重複排除後!$H:$H,"○") -> 0
A34: ■ カテゴリ別 平均ギャップ ワースト10（優先的に底上げすべき領域） | J34: （内部計算：カテゴリ別集計）
A35: 順位 | B35: 区分 | C35: カテゴリ | D35: カテゴリ名称 | E35: 平均ギャップ | F35: 採用施策数 | J35: 区分 | K35: カテゴリ | L35: 名称 | M35: 平均ギャップ | N35: 調整値
A36: 1 | B36: =IFERROR(INDEX($J$36:$J$72,MATCH(LARGE($N$36:$N$72,$A36),$N$36:$N$72,0)),"") | C36: =IFERROR(INDEX($K$36:$K$72,MATCH(LARGE($N$36:$N$72,$A36),$N$36:$N$72,0)),"") | D36: =IFERROR(INDEX($L$36:$L$72,MATCH(LARGE($N$36:$N$72,$A36),$N$36:$N$72,0)),"") | E36: =IFERROR(LARGE($M$36:$M$72,$A36),"") | F36: =IF($B36="","",COUNTIFS(06_重複排除後!$C:$C,$B36,06_重複排除後!$H:$H,"○",06_重複排除後!$A:$A,"AIMF-"&$B36&"-"&$C36&"-*")) | J36: GV | K36: ORG | L36: ガバナンス・組織体制の確立と文化の醸成 | M36: =IFERROR(ROUND(AVERAGEIFS(01_評価入力!$K:$K,01_評価入力!$B:$B,$J36,01_評価入力!$C:$C,$K36),2),"") | N36: =IF($M36="","",$M36+(500-ROW())/1000000)
A37: 2 | B37: =IFERROR(INDEX($J$36:$J$72,MATCH(LARGE($N$36:$N$72,$A37),$N$36:$N$72,0)),"") | C37: =IFERROR(INDEX($K$36:$K$72,MATCH(LARGE($N$36:$N$72,$A37),$N$36:$N$72,0)),"") | D37: =IFERROR(INDEX($L$36:$L$72,MATCH(LARGE($N$36:$N$72,$A37),$N$36:$N$72,0)),"") | E37: =IFERROR(LARGE($M$36:$M$72,$A37),"") | F37: =IF($B37="","",COUNTIFS(06_重複排除後!$C:$C,$B37,06_重複排除後!$H:$H,"○",06_重複排除後!$A:$A,"AIMF-"&$B37&"-"&$C37&"-*")) | J37: GV | K37: POL | L37: AI方針・規程体系 | M37: =IFERROR(ROUND(AVERAGEIFS(01_評価入力!$K:$K,01_評価入力!$B:$B,$J37,01_評価入力!$C:$C,$K37),2),"") | N37: =IF($M37="","",$M37+(500-ROW())/1000000)
A38: 3 | B38: =IFERROR(INDEX($J$36:$J$72,MATCH(LARGE($N$36:$N$72,$A38),$N$36:$N$72,0)),"") | C38: =IFERROR(INDEX($K$36:$K$72,MATCH(LARGE($N$36:$N$72,$A38),$N$36:$N$72,0)),"") | D38: =IFERROR(INDEX($L$36:$L$72,MATCH(LARGE($N$36:$N$72,$A38),$N$36:$N$72,0)),"") | E38: =IFERROR(LARGE($M$36:$M$72,$A38),"") | F38: =IF($B38="","",COUNTIFS(06_重複排除後!$C:$C,$B38,06_重複排除後!$H:$H,"○",06_重複排除後!$A:$A,"AIMF-"&$B38&"-"&$C38&"-*")) | J38: GV | K38: RSM | L38: AIリスクマネジメント | M38: =IFERROR(ROUND(AVERAGEIFS(01_評価入力!$K:$K,01_評価入力!$B:$B,$J38,01_評価入力!$C:$C,$K38),2),"") | N38: =IF($M38="","",$M38+(500-ROW())/1000000)
A39: 4 | B39: =IFERROR(INDEX($J$36:$J$72,MATCH(LARGE($N$36:$N$72,$A39),$N$36:$N$72,0)),"") | C39: =IFERROR(INDEX($K$36:$K$72,MATCH(LARGE($N$36:$N$72,$A39),$N$36:$N$72,0)),"") | D39: =IFERROR(INDEX($L$36:$L$72,MATCH(LARGE($N$36:$N$72,$A39),$N$36:$N$72,0)),"") | E39: =IFERROR(LARGE($M$36:$M$72,$A39),"") | F39: =IF($B39="","",COUNTIFS(06_重複排除後!$C:$C,$B39,06_重複排除後!$H:$H,"○",06_重複排除後!$A:$A,"AIMF-"&$B39&"-"&$C39&"-*")) | J39: GV | K39: LGL | L39: 法規制・コンプライアンス | M39: =IFERROR(ROUND(AVERAGEIFS(01_評価入力!$K:$K,01_評価入力!$B:$B,$J39,01_評価入力!$C:$C,$K39),2),"") | N39: =IF($M39="","",$M39+(500-ROW())/1000000)
A40: 5 | B40: =IFERROR(INDEX($J$36:$J$72,MATCH(LARGE($N$36:$N$72,$A40),$N$36:$N$72,0)),"") | C40: =IFERROR(INDEX($K$36:$K$72,MATCH(LARGE($N$36:$N$72,$A40),$N$36:$N$72,0)),"") | D40: =IFERROR(INDEX($L$36:$L$72,MATCH(LARGE($N$36:$N$72,$A40),$N$36:$N$72,0)),"") | E40: =IFERROR(LARGE($M$36:$M$72,$A40),"") | F40: =IF($B40="","",COUNTIFS(06_重複排除後!$C:$C,$B40,06_重複排除後!$H:$H,"○",06_重複排除後!$A:$A,"AIMF-"&$B40&"-"&$C40&"-*")) | J40: GV | K40: AUD | L40: 監査・保証・成熟度評価 | M40: =IFERROR(ROUND(AVERAGEIFS(01_評価入力!$K:$K,01_評価入力!$B:$B,$J40,01_評価入力!$C:$C,$K40),2),"") | N40: =IF($M40="","",$M40+(500-ROW())/1000000)
A41: 6 | B41: =IFERROR(INDEX($J$36:$J$72,MATCH(LARGE($N$36:$N$72,$A41),$N$36:$N$72,0)),"") | C41: =IFERROR(INDEX($K$36:$K$72,MATCH(LARGE($N$36:$N$72,$A41),$N$36:$N$72,0)),"") | D41: =IFERROR(INDEX($L$36:$L$72,MATCH(LARGE($N$36:$N$72,$A41),$N$36:$N$72,0)),"") | E41: =IFERROR(LARGE($M$36:$M$72,$A41),"") | F41: =IF($B41="","",COUNTIFS(06_重複排除後!$C:$C,$B41,06_重複排除後!$H:$H,"○",06_重複排除後!$A:$A,"AIMF-"&$B41&"-"&$C41&"-*")) | J41: GV | K41: TRA | L41: 透明性・説明責任 | M41: =IFERROR(ROUND(AVERAGEIFS(01_評価入力!$K:$K,01_評価入力!$B:$B,$J41,01_評価入力!$C:$C,$K41),2),"") | N41: =IF($M41="","",$M41+(500-ROW())/1000000)
A42: 7 | B42: =IFERROR(INDEX($J$36:$J$72,MATCH(LARGE($N$36:$N$72,$A42),$N$36:$N$72,0)),"") | C42: =IFERROR(INDEX($K$36:$K$72,MATCH(LARGE($N$36:$N$72,$A42),$N$36:$N$72,0)),"") | D42: =IFERROR(INDEX($L$36:$L$72,MATCH(LARGE($N$36:$N$72,$A42),$N$36:$N$72,0)),"") | E42: =IFERROR(LARGE($M$36:$M$72,$A42),"") | F42: =IF($B42="","",COUNTIFS(06_重複排除後!$C:$C,$B42,06_重複排除後!$H:$H,"○",06_重複排除後!$A:$A,"AIMF-"&$B42&"-"&$C42&"-*")) | J42: ID | K42: AST | L42: AI資産・コンテキスト・インフラの可視化と棚卸し | M42: =IFERROR(ROUND(AVERAGEIFS(01_評価入力!$K:$K,01_評価入力!$B:$B,$J42,01_評価入力!$C:$C,$K42),2),"") | N42: =IF($M42="","",$M42+(500-ROW())/1000000)
A43: 8 | B43: =IFERROR(INDEX($J$36:$J$72,MATCH(LARGE($N$36:$N$72,$A43),$N$36:$N$72,0)),"") | C43: =IFERROR(INDEX($K$36:$K$72,MATCH(LARGE($N$36:$N$72,$A43),$N$36:$N$72,0)),"") | D43: =IFERROR(INDEX($L$36:$L$72,MATCH(LARGE($N$36:$N$72,$A43),$N$36:$N$72,0)),"") | E43: =IFERROR(LARGE($M$36:$M$72,$A43),"") | F43: =IF($B43="","",COUNTIFS(06_重複排除後!$C:$C,$B43,06_重複排除後!$H:$H,"○",06_重複排除後!$A:$A,"AIMF-"&$B43&"-"&$C43&"-*")) | J43: ID | K43: CTX | L43: ユースケース・事業コンテキスト管理 | M43: =IFERROR(ROUND(AVERAGEIFS(01_評価入力!$K:$K,01_評価入力!$B:$B,$J43,01_評価入力!$C:$C,$K43),2),"") | N43: =IF($M43="","",$M43+(500-ROW())/1000000)
A44: 9 | B44: =IFERROR(INDEX($J$36:$J$72,MATCH(LARGE($N$36:$N$72,$A44),$N$36:$N$72,0)),"") | C44: =IFERROR(INDEX($K$36:$K$72,MATCH(LARGE($N$36:$N$72,$A44),$N$36:$N$72,0)),"") | D44: =IFERROR(INDEX($L$36:$L$72,MATCH(LARGE($N$36:$N$72,$A44),$N$36:$N$72,0)),"") | E44: =IFERROR(LARGE($M$36:$M$72,$A44),"") | F44: =IF($B44="","",COUNTIFS(06_重複排除後!$C:$C,$B44,06_重複排除後!$H:$H,"○",06_重複排除後!$A:$A,"AIMF-"&$B44&"-"&$C44&"-*")) | J44: ID | K44: SCM | L44: サプライチェーンリスク管理 | M44: =IFERROR(ROUND(AVERAGEIFS(01_評価入力!$K:$K,01_評価入力!$B:$B,$J44,01_評価入力!$C:$C,$K44),2),"") | N44: =IF($M44="","",$M44+(500-ROW())/1000000)
A45: 10 | B45: =IFERROR(INDEX($J$36:$J$72,MATCH(LARGE($N$36:$N$72,$A45),$N$36:$N$72,0)),"") | C45: =IFERROR(INDEX($K$36:$K$72,MATCH(LARGE($N$36:$N$72,$A45),$N$36:$N$72,0)),"") | D45: =IFERROR(INDEX($L$36:$L$72,MATCH(LARGE($N$36:$N$72,$A45),$N$36:$N$72,0)),"") | E45: =IFERROR(LARGE($M$36:$M$72,$A45),"") | F45: =IF($B45="","",COUNTIFS(06_重複排除後!$C:$C,$B45,06_重複排除後!$H:$H,"○",06_重複排除後!$A:$A,"AIMF-"&$B45&"-"&$C45&"-*")) | J45: ID | K45: DGV | L45: データガバナンス | M45: =IFERROR(ROUND(AVERAGEIFS(01_評価入力!$K:$K,01_評価入力!$B:$B,$J45,01_評価入力!$C:$C,$K45),2),"") | N45: =IF($M45="","",$M45+(500-ROW())/1000000)
J46: ID | K46: THR | L46: AI脅威分析・脅威インテリジェンス | M46: =IFERROR(ROUND(AVERAGEIFS(01_評価入力!$K:$K,01_評価入力!$B:$B,$J46,01_評価入力!$C:$C,$K46),2),"") | N46: =IF($M46="","",$M46+(500-ROW())/1000000)
A47: ■ 優先度スコア Top10 課題 | J47: PR | K47: VUL | L47: 迅速な脆弱性対応・リスク判断フロー | M47: =IFERROR(ROUND(AVERAGEIFS(01_評価入力!$K:$K,01_評価入力!$B:$B,$J47,01_評価入力!$C:$C,$K47),2),"") | N47: =IF($M47="","",$M47+(500-ROW())/1000000)
A48: 順位 | B48: 質問ID | C48: 区分 | D48: Type | E48: 質問 | F48: 現状 | G48: 目標 | H48: 優先度スコア | J48: PR | K48: INF | L48: AIインフラ・ネットワークの要塞化 | M48: =IFERROR(ROUND(AVERAGEIFS(01_評価入力!$K:$K,01_評価入力!$B:$B,$J48,01_評価入力!$C:$C,$K48),2),"") | N48: =IF($M48="","",$M48+(500-ROW())/1000000)
A49: 1 | B49: =IFERROR(INDEX(01_評価入力!$A:$A,MATCH(LARGE(01_評価入力!$V$2:$V$208,$A49),01_評価入力!$V:$V,0)),"") | C49: =IF($B49="","",VLOOKUP($B49,01_評価入力!$A:$B,2,0)) | D49: =IF($B49="","",VLOOKUP($B49,01_評価入力!$A:$F,6,0)) | E49: =IF($B49="","",VLOOKUP($B49,01_評価入力!$A:$E,5,0)) | F49: =IF($B49="","",VLOOKUP($B49,01_評価入力!$A:$I,9,0)) | G49: =IF($B49="","",VLOOKUP($B49,01_評価入力!$A:$J,10,0)) | H49: =IF($B49="","",ROUND(VLOOKUP($B49,01_評価入力!$A:$R,18,0),1)) | J49: PR | K49: IAM | L49: アイデンティティ・アクセス制御 | M49: =IFERROR(ROUND(AVERAGEIFS(01_評価入力!$K:$K,01_評価入力!$B:$B,$J49,01_評価入力!$C:$C,$K49),2),"") | N49: =IF($M49="","",$M49+(500-ROW())/1000000)
A50: 2 | B50: =IFERROR(INDEX(01_評価入力!$A:$A,MATCH(LARGE(01_評価入力!$V$2:$V$208,$A50),01_評価入力!$V:$V,0)),"") | C50: =IF($B50="","",VLOOKUP($B50,01_評価入力!$A:$B,2,0)) | D50: =IF($B50="","",VLOOKUP($B50,01_評価入力!$A:$F,6,0)) | E50: =IF($B50="","",VLOOKUP($B50,01_評価入力!$A:$E,5,0)) | F50: =IF($B50="","",VLOOKUP($B50,01_評価入力!$A:$I,9,0)) | G50: =IF($B50="","",VLOOKUP($B50,01_評価入力!$A:$J,10,0)) | H50: =IF($B50="","",ROUND(VLOOKUP($B50,01_評価入力!$A:$R,18,0),1)) | J50: PR | K50: DAT | L50: AIデータ保護 | M50: =IFERROR(ROUND(AVERAGEIFS(01_評価入力!$K:$K,01_評価入力!$B:$B,$J50,01_評価入力!$C:$C,$K50),2),"") | N50: =IF($M50="","",$M50+(500-ROW())/1000000)
A51: 3 | B51: =IFERROR(INDEX(01_評価入力!$A:$A,MATCH(LARGE(01_評価入力!$V$2:$V$208,$A51),01_評価入力!$V:$V,0)),"") | C51: =IF($B51="","",VLOOKUP($B51,01_評価入力!$A:$B,2,0)) | D51: =IF($B51="","",VLOOKUP($B51,01_評価入力!$A:$F,6,0)) | E51: =IF($B51="","",VLOOKUP($B51,01_評価入力!$A:$E,5,0)) | F51: =IF($B51="","",VLOOKUP($B51,01_評価入力!$A:$I,9,0)) | G51: =IF($B51="","",VLOOKUP($B51,01_評価入力!$A:$J,10,0)) | H51: =IF($B51="","",ROUND(VLOOKUP($B51,01_評価入力!$A:$R,18,0),1)) | J51: PR | K51: MDL | L51: モデルライフサイクル・成果物完全性 | M51: =IFERROR(ROUND(AVERAGEIFS(01_評価入力!$K:$K,01_評価入力!$B:$B,$J51,01_評価入力!$C:$C,$K51),2),"") | N51: =IF($M51="","",$M51+(500-ROW())/1000000)
A52: 4 | B52: =IFERROR(INDEX(01_評価入力!$A:$A,MATCH(LARGE(01_評価入力!$V$2:$V$208,$A52),01_評価入力!$V:$V,0)),"") | C52: =IF($B52="","",VLOOKUP($B52,01_評価入力!$A:$B,2,0)) | D52: =IF($B52="","",VLOOKUP($B52,01_評価入力!$A:$F,6,0)) | E52: =IF($B52="","",VLOOKUP($B52,01_評価入力!$A:$E,5,0)) | F52: =IF($B52="","",VLOOKUP($B52,01_評価入力!$A:$I,9,0)) | G52: =IF($B52="","",VLOOKUP($B52,01_評価入力!$A:$J,10,0)) | H52: =IF($B52="","",ROUND(VLOOKUP($B52,01_評価入力!$A:$R,18,0),1)) | J52: PR | K52: RED | L52: プロアクティブなリスク評価・実戦演習 | M52: =IFERROR(ROUND(AVERAGEIFS(01_評価入力!$K:$K,01_評価入力!$B:$B,$J52,01_評価入力!$C:$C,$K52),2),"") | N52: =IF($M52="","",$M52+(500-ROW())/1000000)
A53: 5 | B53: =IFERROR(INDEX(01_評価入力!$A:$A,MATCH(LARGE(01_評価入力!$V$2:$V$208,$A53),01_評価入力!$V:$V,0)),"") | C53: =IF($B53="","",VLOOKUP($B53,01_評価入力!$A:$B,2,0)) | D53: =IF($B53="","",VLOOKUP($B53,01_評価入力!$A:$F,6,0)) | E53: =IF($B53="","",VLOOKUP($B53,01_評価入力!$A:$E,5,0)) | F53: =IF($B53="","",VLOOKUP($B53,01_評価入力!$A:$I,9,0)) | G53: =IF($B53="","",VLOOKUP($B53,01_評価入力!$A:$J,10,0)) | H53: =IF($B53="","",ROUND(VLOOKUP($B53,01_評価入力!$A:$R,18,0),1)) | J53: PR | K53: GRD | L53: ガードレール・出力統制 | M53: =IFERROR(ROUND(AVERAGEIFS(01_評価入力!$K:$K,01_評価入力!$B:$B,$J53,01_評価入力!$C:$C,$K53),2),"") | N53: =IF($M53="","",$M53+(500-ROW())/1000000)
A54: 6 | B54: =IFERROR(INDEX(01_評価入力!$A:$A,MATCH(LARGE(01_評価入力!$V$2:$V$208,$A54),01_評価入力!$V:$V,0)),"") | C54: =IF($B54="","",VLOOKUP($B54,01_評価入力!$A:$B,2,0)) | D54: =IF($B54="","",VLOOKUP($B54,01_評価入力!$A:$F,6,0)) | E54: =IF($B54="","",VLOOKUP($B54,01_評価入力!$A:$E,5,0)) | F54: =IF($B54="","",VLOOKUP($B54,01_評価入力!$A:$I,9,0)) | G54: =IF($B54="","",VLOOKUP($B54,01_評価入力!$A:$J,10,0)) | H54: =IF($B54="","",ROUND(VLOOKUP($B54,01_評価入力!$A:$R,18,0),1)) | J54: PR | K54: AGT | L54: エージェント・ツール接続セキュリティ | M54: =IFERROR(ROUND(AVERAGEIFS(01_評価入力!$K:$K,01_評価入力!$B:$B,$J54,01_評価入力!$C:$C,$K54),2),"") | N54: =IF($M54="","",$M54+(500-ROW())/1000000)
A55: 7 | B55: =IFERROR(INDEX(01_評価入力!$A:$A,MATCH(LARGE(01_評価入力!$V$2:$V$208,$A55),01_評価入力!$V:$V,0)),"") | C55: =IF($B55="","",VLOOKUP($B55,01_評価入力!$A:$B,2,0)) | D55: =IF($B55="","",VLOOKUP($B55,01_評価入力!$A:$F,6,0)) | E55: =IF($B55="","",VLOOKUP($B55,01_評価入力!$A:$E,5,0)) | F55: =IF($B55="","",VLOOKUP($B55,01_評価入力!$A:$I,9,0)) | G55: =IF($B55="","",VLOOKUP($B55,01_評価入力!$A:$J,10,0)) | H55: =IF($B55="","",ROUND(VLOOKUP($B55,01_評価入力!$A:$R,18,0),1)) | J55: PR | K55: HOV | L55: 人間による監督 | M55: =IFERROR(ROUND(AVERAGEIFS(01_評価入力!$K:$K,01_評価入力!$B:$B,$J55,01_評価入力!$C:$C,$K55),2),"") | N55: =IF($M55="","",$M55+(500-ROW())/1000000)
A56: 8 | B56: =IFERROR(INDEX(01_評価入力!$A:$A,MATCH(LARGE(01_評価入力!$V$2:$V$208,$A56),01_評価入力!$V:$V,0)),"") | C56: =IF($B56="","",VLOOKUP($B56,01_評価入力!$A:$B,2,0)) | D56: =IF($B56="","",VLOOKUP($B56,01_評価入力!$A:$F,6,0)) | E56: =IF($B56="","",VLOOKUP($B56,01_評価入力!$A:$E,5,0)) | F56: =IF($B56="","",VLOOKUP($B56,01_評価入力!$A:$I,9,0)) | G56: =IF($B56="","",VLOOKUP($B56,01_評価入力!$A:$J,10,0)) | H56: =IF($B56="","",ROUND(VLOOKUP($B56,01_評価入力!$A:$R,18,0),1)) | J56: PR | K56: ADV | L56: 敵対的堅牢性 | M56: =IFERROR(ROUND(AVERAGEIFS(01_評価入力!$K:$K,01_評価入力!$B:$B,$J56,01_評価入力!$C:$C,$K56),2),"") | N56: =IF($M56="","",$M56+(500-ROW())/1000000)
A57: 9 | B57: =IFERROR(INDEX(01_評価入力!$A:$A,MATCH(LARGE(01_評価入力!$V$2:$V$208,$A57),01_評価入力!$V:$V,0)),"") | C57: =IF($B57="","",VLOOKUP($B57,01_評価入力!$A:$B,2,0)) | D57: =IF($B57="","",VLOOKUP($B57,01_評価入力!$A:$F,6,0)) | E57: =IF($B57="","",VLOOKUP($B57,01_評価入力!$A:$E,5,0)) | F57: =IF($B57="","",VLOOKUP($B57,01_評価入力!$A:$I,9,0)) | G57: =IF($B57="","",VLOOKUP($B57,01_評価入力!$A:$J,10,0)) | H57: =IF($B57="","",ROUND(VLOOKUP($B57,01_評価入力!$A:$R,18,0),1)) | J57: PR | K57: CAI | L57: AI時代に対応する既存セキュリティの強化 | M57: =IFERROR(ROUND(AVERAGEIFS(01_評価入力!$K:$K,01_評価入力!$B:$B,$J57,01_評価入力!$C:$C,$K57),2),"") | N57: =IF($M57="","",$M57+(500-ROW())/1000000)
A58: 10 | B58: =IFERROR(INDEX(01_評価入力!$A:$A,MATCH(LARGE(01_評価入力!$V$2:$V$208,$A58),01_評価入力!$V:$V,0)),"") | C58: =IF($B58="","",VLOOKUP($B58,01_評価入力!$A:$B,2,0)) | D58: =IF($B58="","",VLOOKUP($B58,01_評価入力!$A:$F,6,0)) | E58: =IF($B58="","",VLOOKUP($B58,01_評価入力!$A:$E,5,0)) | F58: =IF($B58="","",VLOOKUP($B58,01_評価入力!$A:$I,9,0)) | G58: =IF($B58="","",VLOOKUP($B58,01_評価入力!$A:$J,10,0)) | H58: =IF($B58="","",ROUND(VLOOKUP($B58,01_評価入力!$A:$R,18,0),1)) | J58: PR | K58: EDU | L58: 層別AIセキュリティ教育 | M58: =IFERROR(ROUND(AVERAGEIFS(01_評価入力!$K:$K,01_評価入力!$B:$B,$J58,01_評価入力!$C:$C,$K58),2),"") | N58: =IF($M58="","",$M58+(500-ROW())/1000000)
J59: DE | K59: VUL | L59: サプライチェーン脆弱性の継続的・動的検知 | M59: =IFERROR(ROUND(AVERAGEIFS(01_評価入力!$K:$K,01_評価入力!$B:$B,$J59,01_評価入力!$C:$C,$K59),2),"") | N59: =IF($M59="","",$M59+(500-ROW())/1000000)
J60: DE | K60: IOM | L60: 意味論・入出力監視 | M60: =IFERROR(ROUND(AVERAGEIFS(01_評価入力!$K:$K,01_評価入力!$B:$B,$J60,01_評価入力!$C:$C,$K60),2),"") | N60: =IF($M60="","",$M60+(500-ROW())/1000000)
J61: DE | K61: AGT | L61: エージェント挙動・ツール実行の動的監視 | M61: =IFERROR(ROUND(AVERAGEIFS(01_評価入力!$K:$K,01_評価入力!$B:$B,$J61,01_評価入力!$C:$C,$K61),2),"") | N61: =IF($M61="","",$M61+(500-ROW())/1000000)
J62: DE | K62: HLT | L62: インフラ・データ・モデルの健全性監視 | M62: =IFERROR(ROUND(AVERAGEIFS(01_評価入力!$K:$K,01_評価入力!$B:$B,$J62,01_評価入力!$C:$C,$K62),2),"") | N62: =IF($M62="","",$M62+(500-ROW())/1000000)
J63: DE | K63: SOC | L63: SOC統合・検知運用 | M63: =IFERROR(ROUND(AVERAGEIFS(01_評価入力!$K:$K,01_評価入力!$B:$B,$J63,01_評価入力!$C:$C,$K63),2),"") | N63: =IF($M63="","",$M63+(500-ROW())/1000000)
J64: DE | K64: LOG | L64: ログ・証跡基盤 | M64: =IFERROR(ROUND(AVERAGEIFS(01_評価入力!$K:$K,01_評価入力!$B:$B,$J64,01_評価入力!$C:$C,$K64),2),"") | N64: =IF($M64="","",$M64+(500-ROW())/1000000)
J65: RS | K65: IRP | L65: インシデントレスポンス体制の拡張と自動化 | M65: =IFERROR(ROUND(AVERAGEIFS(01_評価入力!$K:$K,01_評価入力!$B:$B,$J65,01_評価入力!$C:$C,$K65),2),"") | N65: =IF($M65="","",$M65+(500-ROW())/1000000)
J66: RS | K66: CON | L66: 封じ込め・隔離 | M66: =IFERROR(ROUND(AVERAGEIFS(01_評価入力!$K:$K,01_評価入力!$B:$B,$J66,01_評価入力!$C:$C,$K66),2),"") | N66: =IF($M66="","",$M66+(500-ROW())/1000000)
J67: RS | K67: RPT | L67: 外部報告・ステークホルダー通知 | M67: =IFERROR(ROUND(AVERAGEIFS(01_評価入力!$K:$K,01_評価入力!$B:$B,$J67,01_評価入力!$C:$C,$K67),2),"") | N67: =IF($M67="","",$M67+(500-ROW())/1000000)
J68: RS | K68: ANL | L68: インシデント事後分析 | M68: =IFERROR(ROUND(AVERAGEIFS(01_評価入力!$K:$K,01_評価入力!$B:$B,$J68,01_評価入力!$C:$C,$K68),2),"") | N68: =IF($M68="","",$M68+(500-ROW())/1000000)
J69: RC | K69: RES | L69: レジリエンスの最大化 | M69: =IFERROR(ROUND(AVERAGEIFS(01_評価入力!$K:$K,01_評価入力!$B:$B,$J69,01_評価入力!$C:$C,$K69),2),"") | N69: =IF($M69="","",$M69+(500-ROW())/1000000)
J70: RC | K70: CIM | L70: 継続的改善 | M70: =IFERROR(ROUND(AVERAGEIFS(01_評価入力!$K:$K,01_評価入力!$B:$B,$J70,01_評価入力!$C:$C,$K70),2),"") | N70: =IF($M70="","",$M70+(500-ROW())/1000000)
... J72: RC | K72: PMM | L72: 市販後モニタリング | M72: =IFERROR(ROUND(AVERAGEIFS(01_評価入力!$K:$K,01_評価入力!$B:$B,$J72,01_評価入力!$C:$C,$K72),2),"") | N72: =IF($M72="","",$M72+(500-ROW())/1000000)

Sheet 12_PPT出力データ
A1: PowerPoint報告書 転記ガイド
A3: スライド | B3: 内容 | C3: 参照シート | D3: 参照箇所
A4: 1. エグゼクティブサマリー | B4: 回答進捗・区分別成熟度・採用施策数 | C4: 11_ダッシュボード | D4: A3:F5 / A7:G14
A5: 2. 区分別レーダーチャート | B5: 現状 vs 目標の成熟度レーダー（6区分） | C5: 11_ダッシュボード | D5: レーダーチャート（H2）
A6: 3. control-type分析 | B6: AI固有統制の未整備 vs 既存運用の適用漏れ | C6: 11_ダッシュボード | D6: A16:F19＋棒グラフ
A7: 4. AI類型別レディネス | B7: 従来型AI／生成AI／エージェント／マルチの現状 | C7: 11_ダッシュボード | D7: A21:E26＋棒グラフ
A8: 5. 重点改善領域 | B8: カテゴリ別ギャップ ワースト10 | C8: 11_ダッシュボード | D8: A34:F45
A9: 6. 優先課題Top10 | B9: 優先度スコア上位の課題一覧 | C9: 11_ダッシュボード | D9: A47:H58
A10: 7. 実行計画 | B10: 短中長Top5と区分別ロードマップ | C10: 07_短中長Top5 / 08_ロードマップ | D10: 各シート全体
A11: 8. スケジュール | B11: 36か月ガントチャート | C11: 10_ガントチャート | D11: 採用施策の行のみ抜粋
